Workbook

Sheet Purchase Orders
A1: DC_CODE | B1: PURCH_ORDER_NUMBER | C1: PURCH_ORDER_DATE | D1: EXPECTED_DATE | E1: SUPPLIER_CODE | F1: SUPPLIER NAME | G1: PURCH_ORDER_LINE | H1: EAN_NO | I1: PRODUCT_CODE | J1: PRODUCT_DESCRIPTION | K1: VENDOR_ITEM_CODE | L1: ORDERING_UNIT | M1: QTY_PER_PACK_OF_ORDERING_UOM | N1: NO_OF_PACKS_ORDERED | O1: TOTAL_QUANTITY | P1: CLOSING_STOCK | Q1: MRP_PER_UNIT | R1: LANDING_COST_INCL_TAX_PER_UNIT | S1: SALES_TAX | T1: COST_PRICE_INCL_TAX_PER_PO_OU | U1: TAX_PER | V1: CURRENCY | W1: HSN | X1: MASTER PRODUCT CODE | Y1: Order type | Z1: S | AA1: M | AB1: L | AC1: XL | AD1: XXL | AE1: SKU | AF1: Colour | AG1: location | AH1: RP DESCRPTION
A2: SZAF | B2: 5114202424 | C2: 01.05.2026 | D2: 23.07.2026 | E2: 10337044 | F2: UNITED TEXTILE MILLS PRIVATE LIMITE | G2: 1 | H2: 8909490134375 | I2: 441811508001 | J2: KRTS-APWN26-GETKRTSFUT61, OFF WHITE, 2XL | L2: EA | M2: 1 | N2: 30 | O2: 30 | Q2: 314.7 | R2: 314.7 | S2: 472.05 | T2: 9441 | U2: 5 | V2: INR | X2: =IF(ISNUMBER(VALUE(LEFT(J2,1))),LEFT(J2,MIN(IFERROR(FIND("A",UPPER(J2)),LEN(J2)+1),IFERROR(FIND("B",UPPER(J2)),LEN(J2)+1),IFERROR(FIND("C",UPPER(J2)),LEN(J2)+1),IFERROR(FIND("D",UPPER(J2)),LEN(J2)+1),IFERROR(FIND("E",UPPER(J2)),LEN(J2)+1),IFERROR(FIND("F",UPPER(J2)),LEN(J2)+1),IFERROR(FIND("G",UPPER(J2)),LEN(J2)+1),IFERROR(FIND("H",UPPER(J2)),LEN(J2)+1),IFERROR(FIND("I",UPPER(J2)),LEN(J2)+1),IFERROR(FIND("J",UPPER(J2)),LEN(J2)+1),IFERROR(FIND("K",UPPER(J2)),LEN(J2)+1),IFERROR(FIND("L",UPPER(J2)),LEN(J2)+1),IFERROR(FIND("M",UPPER(J2)),LEN(J2)+1),IFERROR(FIND("N",UPPER(J2)),LEN(J2)+1),IFERROR(FIND("O",UPPER(J2)),LEN(J2)+1),IFERROR(FIND("P",UPPER(J2)),LEN(J2)+1),IFERROR(FIND("Q",UPPER(J2)),LEN(J2)+1),IFERROR(FIND("R",UPPER(J2)),LEN(J2)+1),IFERROR(FIND("S",UPPER(J2)),LEN(J2)+1),IFERROR(FIND("T",UPPER(J2)),LEN(J2)+1),IFERROR(FIND("U",UPPER(J2)),LEN(J2)+1),IFERROR(FIND("V",UPPER(J2)),LEN(J2)+1),IFERROR(FIND("W",UPPER(J2)),LEN(J2)+1),IFERROR(FIND("X",UPPER(J2)),LEN(J2)+1),IFERROR(FIND("Y",UPPER(J2)),LEN(J2)+1),IFERROR(FIND("Z",UPPER(J2)),LEN(J2)+1))-1),LEFT(TEXT(I2,"0"),LEN(TEXT(I2,"0"))-3)) -> 441811508 | Y2: =IF(ISNUMBER(SEARCH("(RP)",J2)),"RP","DC") -> DC | Z2: =IF(ISNUMBER(SEARCH("(RP)",J2)),O2,IF(RIGHT(TRIM(J2),3)=", S",O2,0)) -> 0 | AA2: =IF(ISNUMBER(SEARCH("(RP)",J2)),O2,IF(RIGHT(TRIM(J2),3)=", M",O2,0)) -> 0 | AB2: =IF(ISNUMBER(SEARCH("(RP)",J2)),O2,IF(RIGHT(TRIM(J2),3)=", L",O2,0)) -> 0 | AC2: =IF(ISNUMBER(SEARCH("(RP)",J2)),O2,IF(RIGHT(TRIM(J2),4)=", XL",O2,0)) -> 0 | AD2: =IF(ISNUMBER(SEARCH("(RP)",J2)),O2,IF(OR(RIGHT(TRIM(J2),5)=", XXL",RIGHT(TRIM(J2),5)=", 2XL"),O2,0)) -> 30 | AE2: {=IFERROR(_xlfn.XLOOKUP(H2,Sheet1!$G:$G,Sheet1!$F:$F),IFERROR(_xlfn.XLOOKUP(1,(--($X$2:$X$1074=X2))*(--ISNUMBER(MATCH($H$2:$H$1074,Sheet1!$G:$G,0))),_xlfn.XLOOKUP($H$2:$H$1074,Sheet1!$G:$G,Sheet1!$F:$F,"")),"NOT FOUND"))} -> GETKRTSFUT6125 | AF2: =IFERROR(IF(ISNUMBER(SEARCH("(RP)",J2)),TRIM(SUBSTITUTE(MID(J2,10,LEN(J2)),"(RP)","")),TRIM(MID(J2,FIND(",",J2)+1,FIND(",",J2,FIND(",",J2)+1)-FIND(",",J2)-1))),"") -> OFF WHITE | AG2: =IF(A2="SZAF","Bangalore",IF(A2="SAEX","JHAJJAR",IF(A2="S0EU","HARIPAL",""))) -> Bangalore | AH2: =IF(OR(J2="",AE2="",AE2="NOT FOUND"),"",IF(Y2="RP",IFERROR(LEFT(_xlfn.XLOOKUP(AE2,Sheet1!$F:$F,Sheet1!$W:$W),FIND("-",_xlfn.XLOOKUP(AE2,Sheet1!$F:$F,Sheet1!$W:$W),FIND("-",_xlfn.XLOOKUP(AE2,Sheet1!$F:$F,Sheet1!$W:$W))+1))&AE2,"NOT FOUND"),LEFT(J2,FIND("-",J2,FIND("-",J2)+1))&AE2)) -> KRTS-APWN26-GETKRTSFUT6125
A3: SZAF | B3: 5114202424 | C3: 01.05.2026 | D3: 23.07.2026 | E3: 10337044 | F3: UNITED TEXTILE MILLS PRIVATE LIMITE | G3: 2 | H3: 8909490134382 | I3: 441811508002 | J3: KRTS-APWN26-GETKRTSFUT6125, OFF WHITE, L | L3: EA | M3: 1 | N3: 257 | O3: 257 | Q3: 314.7 | R3: 314.7 | S3: 4043.9 | T3: 80877.9 | U3: 5 | V3: INR | X3: =IF(ISNUMBER(VALUE(LEFT(J3,1))),LEFT(J3,MIN(IFERROR(FIND("A",UPPER(J3)),LEN(J3)+1),IFERROR(FIND("B",UPPER(J3)),LEN(J3)+1),IFERROR(FIND("C",UPPER(J3)),LEN(J3)+1),IFERROR(FIND("D",UPPER(J3)),LEN(J3)+1),IFERROR(FIND("E",UPPER(J3)),LEN(J3)+1),IFERROR(FIND("F",UPPER(J3)),LEN(J3)+1),IFERROR(FIND("G",UPPER(J3)),LEN(J3)+1),IFERROR(FIND("H",UPPER(J3)),LEN(J3)+1),IFERROR(FIND("I",UPPER(J3)),LEN(J3)+1),IFERROR(FIND("J",UPPER(J3)),LEN(J3)+1),IFERROR(FIND("K",UPPER(J3)),LEN(J3)+1),IFERROR(FIND("L",UPPER(J3)),LEN(J3)+1),IFERROR(FIND("M",UPPER(J3)),LEN(J3)+1),IFERROR(FIND("N",UPPER(J3)),LEN(J3)+1),IFERROR(FIND("O",UPPER(J3)),LEN(J3)+1),IFERROR(FIND("P",UPPER(J3)),LEN(J3)+1),IFERROR(FIND("Q",UPPER(J3)),LEN(J3)+1),IFERROR(FIND("R",UPPER(J3)),LEN(J3)+1),IFERROR(FIND("S",UPPER(J3)),LEN(J3)+1),IFERROR(FIND("T",UPPER(J3)),LEN(J3)+1),IFERROR(FIND("U",UPPER(J3)),LEN(J3)+1),IFERROR(FIND("V",UPPER(J3)),LEN(J3)+1),IFERROR(FIND("W",UPPER(J3)),LEN(J3)+1),IFERROR(FIND("X",UPPER(J3)),LEN(J3)+1),IFERROR(FIND("Y",UPPER(J3)),LEN(J3)+1),IFERROR(FIND("Z",UPPER(J3)),LEN(J3)+1))-1),LEFT(TEXT(I3,"0"),LEN(TEXT(I3,"0"))-3)) -> 441811508 | Y3: =IF(ISNUMBER(SEARCH("(RP)",J3)),"RP","DC") -> DC | Z3: =IF(ISNUMBER(SEARCH("(RP)",J3)),O3,IF(RIGHT(TRIM(J3),3)=", S",O3,0)) -> 0 | AA3: =IF(ISNUMBER(SEARCH("(RP)",J3)),O3,IF(RIGHT(TRIM(J3),3)=", M",O3,0)) -> 0 | AB3: =IF(ISNUMBER(SEARCH("(RP)",J3)),O3,IF(RIGHT(TRIM(J3),3)=", L",O3,0)) -> 257 | AC3: =IF(ISNUMBER(SEARCH("(RP)",J3)),O3,IF(RIGHT(TRIM(J3),4)=", XL",O3,0)) -> 0 | AD3: =IF(ISNUMBER(SEARCH("(RP)",J3)),O3,IF(OR(RIGHT(TRIM(J3),5)=", XXL",RIGHT(TRIM(J3),5)=", 2XL"),O3,0)) -> 0 | AE3: {=IFERROR(_xlfn.XLOOKUP(H3,Sheet1!$G:$G,Sheet1!$F:$F),IFERROR(_xlfn.XLOOKUP(1,(--($X$2:$X$1074=X3))*(--ISNUMBER(MATCH($H$2:$H$1074,Sheet1!$G:$G,0))),_xlfn.XLOOKUP($H$2:$H$1074,Sheet1!$G:$G,Sheet1!$F:$F,"")),"NOT FOUND"))} -> GETKRTSFUT6125 | AF3: =IFERROR(IF(ISNUMBER(SEARCH("(RP)",J3)),TRIM(SUBSTITUTE(MID(J3,10,LEN(J3)),"(RP)","")),TRIM(MID(J3,FIND(",",J3)+1,FIND(",",J3,FIND(",",J3)+1)-FIND(",",J3)-1))),"") -> OFF WHITE | AG3: =IF(A3="SZAF","Bangalore",IF(A3="SAEX","JHAJJAR",IF(A3="S0EU","HARIPAL",""))) -> Bangalore | AH3: =IF(OR(J3="",AE3="",AE3="NOT FOUND"),"",IF(Y3="RP",IFERROR(LEFT(_xlfn.XLOOKUP(AE3,Sheet1!$F:$F,Sheet1!$W:$W),FIND("-",_xlfn.XLOOKUP(AE3,Sheet1!$F:$F,Sheet1!$W:$W),FIND("-",_xlfn.XLOOKUP(AE3,Sheet1!$F:$F,Sheet1!$W:$W))+1))&AE3,"NOT FOUND"),LEFT(J3,FIND("-",J3,FIND("-",J3)+1))&AE3)) -> KRTS-APWN26-GETKRTSFUT6125
A4: SZAF | B4: 5114202424 | C4: 01.05.2026 | D4: 23.07.2026 | E4: 10337044 | F4: UNITED TEXTILE MILLS PRIVATE LIMITE | G4: 3 | H4: 8909490134399 | I4: 441811508003 | J4: KRTS-APWN26-GETKRTSFUT6125, OFF WHITE, M | L4: EA | M4: 1 | N4: 257 | O4: 257 | Q4: 314.7 | R4: 314.7 | S4: 4043.9 | T4: 80877.9 | U4: 5 | V4: INR | X4: =IF(ISNUMBER(VALUE(LEFT(J4,1))),LEFT(J4,MIN(IFERROR(FIND("A",UPPER(J4)),LEN(J4)+1),IFERROR(FIND("B",UPPER(J4)),LEN(J4)+1),IFERROR(FIND("C",UPPER(J4)),LEN(J4)+1),IFERROR(FIND("D",UPPER(J4)),LEN(J4)+1),IFERROR(FIND("E",UPPER(J4)),LEN(J4)+1),IFERROR(FIND("F",UPPER(J4)),LEN(J4)+1),IFERROR(FIND("G",UPPER(J4)),LEN(J4)+1),IFERROR(FIND("H",UPPER(J4)),LEN(J4)+1),IFERROR(FIND("I",UPPER(J4)),LEN(J4)+1),IFERROR(FIND("J",UPPER(J4)),LEN(J4)+1),IFERROR(FIND("K",UPPER(J4)),LEN(J4)+1),IFERROR(FIND("L",UPPER(J4)),LEN(J4)+1),IFERROR(FIND("M",UPPER(J4)),LEN(J4)+1),IFERROR(FIND("N",UPPER(J4)),LEN(J4)+1),IFERROR(FIND("O",UPPER(J4)),LEN(J4)+1),IFERROR(FIND("P",UPPER(J4)),LEN(J4)+1),IFERROR(FIND("Q",UPPER(J4)),LEN(J4)+1),IFERROR(FIND("R",UPPER(J4)),LEN(J4)+1),IFERROR(FIND("S",UPPER(J4)),LEN(J4)+1),IFERROR(FIND("T",UPPER(J4)),LEN(J4)+1),IFERROR(FIND("U",UPPER(J4)),LEN(J4)+1),IFERROR(FIND("V",UPPER(J4)),LEN(J4)+1),IFERROR(FIND("W",UPPER(J4)),LEN(J4)+1),IFERROR(FIND("X",UPPER(J4)),LEN(J4)+1),IFERROR(FIND("Y",UPPER(J4)),LEN(J4)+1),IFERROR(FIND("Z",UPPER(J4)),LEN(J4)+1))-1),LEFT(TEXT(I4,"0"),LEN(TEXT(I4,"0"))-3)) -> 441811508 | Y4: =IF(ISNUMBER(SEARCH("(RP)",J4)),"RP","DC") -> DC | Z4: =IF(ISNUMBER(SEARCH("(RP)",J4)),O4,IF(RIGHT(TRIM(J4),3)=", S",O4,0)) -> 0 | AA4: =IF(ISNUMBER(SEARCH("(RP)",J4)),O4,IF(RIGHT(TRIM(J4),3)=", M",O4,0)) -> 257 | AB4: =IF(ISNUMBER(SEARCH("(RP)",J4)),O4,IF(RIGHT(TRIM(J4),3)=", L",O4,0)) -> 0 | AC4: =IF(ISNUMBER(SEARCH("(RP)",J4)),O4,IF(RIGHT(TRIM(J4),4)=", XL",O4,0)) -> 0 | AD4: =IF(ISNUMBER(SEARCH("(RP)",J4)),O4,IF(OR(RIGHT(TRIM(J4),5)=", XXL",RIGHT(TRIM(J4),5)=", 2XL"),O4,0)) -> 0 | AE4: {=IFERROR(_xlfn.XLOOKUP(H4,Sheet1!$G:$G,Sheet1!$F:$F),IFERROR(_xlfn.XLOOKUP(1,(--($X$2:$X$1074=X4))*(--ISNUMBER(MATCH($H$2:$H$1074,Sheet1!$G:$G,0))),_xlfn.XLOOKUP($H$2:$H$1074,Sheet1!$G:$G,Sheet1!$F:$F,"")),"NOT FOUND"))} -> GETKRTSFUT6125 | AF4: =IFERROR(IF(ISNUMBER(SEARCH("(RP)",J4)),TRIM(SUBSTITUTE(MID(J4,10,LEN(J4)),"(RP)","")),TRIM(MID(J4,FIND(",",J4)+1,FIND(",",J4,FIND(",",J4)+1)-FIND(",",J4)-1))),"") -> OFF WHITE | AG4: =IF(A4="SZAF","Bangalore",IF(A4="SAEX","JHAJJAR",IF(A4="S0EU","HARIPAL",""))) -> Bangalore | AH4: =IF(OR(J4="",AE4="",AE4="NOT FOUND"),"",IF(Y4="RP",IFERROR(LEFT(_xlfn.XLOOKUP(AE4,Sheet1!$F:$F,Sheet1!$W:$W),FIND("-",_xlfn.XLOOKUP(AE4,Sheet1!$F:$F,Sheet1!$W:$W),FIND("-",_xlfn.XLOOKUP(AE4,Sheet1!$F:$F,Sheet1!$W:$W))+1))&AE4,"NOT FOUND"),LEFT(J4,FIND("-",J4,FIND("-",J4)+1))&AE4)) -> KRTS-APWN26-GETKRTSFUT6125
A5: SZAF | B5: 5114202424 | C5: 01.05.2026 | D5: 23.07.2026 | E5: 10337044 | F5: UNITED TEXTILE MILLS PRIVATE LIMITE | G5: 4 | H5: 8909490134405 | I5: 441811508004 | J5: KRTS-APWN26-GETKRTSFUT6125, OFF WHITE, S | L5: EA | M5: 1 | N5: 30 | O5: 30 | Q5: 314.7 | R5: 314.7 | S5: 472.05 | T5: 9441 | U5: 5 | V5: INR | X5: =IF(ISNUMBER(VALUE(LEFT(J5,1))),LEFT(J5,MIN(IFERROR(FIND("A",UPPER(J5)),LEN(J5)+1),IFERROR(FIND("B",UPPER(J5)),LEN(J5)+1),IFERROR(FIND("C",UPPER(J5)),LEN(J5)+1),IFERROR(FIND("D",UPPER(J5)),LEN(J5)+1),IFERROR(FIND("E",UPPER(J5)),LEN(J5)+1),IFERROR(FIND("F",UPPER(J5)),LEN(J5)+1),IFERROR(FIND("G",UPPER(J5)),LEN(J5)+1),IFERROR(FIND("H",UPPER(J5)),LEN(J5)+1),IFERROR(FIND("I",UPPER(J5)),LEN(J5)+1),IFERROR(FIND("J",UPPER(J5)),LEN(J5)+1),IFERROR(FIND("K",UPPER(J5)),LEN(J5)+1),IFERROR(FIND("L",UPPER(J5)),LEN(J5)+1),IFERROR(FIND("M",UPPER(J5)),LEN(J5)+1),IFERROR(FIND("N",UPPER(J5)),LEN(J5)+1),IFERROR(FIND("O",UPPER(J5)),LEN(J5)+1),IFERROR(FIND("P",UPPER(J5)),LEN(J5)+1),IFERROR(FIND("Q",UPPER(J5)),LEN(J5)+1),IFERROR(FIND("R",UPPER(J5)),LEN(J5)+1),IFERROR(FIND("S",UPPER(J5)),LEN(J5)+1),IFERROR(FIND("T",UPPER(J5)),LEN(J5)+1),IFERROR(FIND("U",UPPER(J5)),LEN(J5)+1),IFERROR(FIND("V",UPPER(J5)),LEN(J5)+1),IFERROR(FIND("W",UPPER(J5)),LEN(J5)+1),IFERROR(FIND("X",UPPER(J5)),LEN(J5)+1),IFERROR(FIND("Y",UPPER(J5)),LEN(J5)+1),IFERROR(FIND("Z",UPPER(J5)),LEN(J5)+1))-1),LEFT(TEXT(I5,"0"),LEN(TEXT(I5,"0"))-3)) -> 441811508 | Y5: =IF(ISNUMBER(SEARCH("(RP)",J5)),"RP","DC") -> DC | Z5: =IF(ISNUMBER(SEARCH("(RP)",J5)),O5,IF(RIGHT(TRIM(J5),3)=", S",O5,0)) -> 30 | AA5: =IF(ISNUMBER(SEARCH("(RP)",J5)),O5,IF(RIGHT(TRIM(J5),3)=", M",O5,0)) -> 0 | AB5: =IF(ISNUMBER(SEARCH("(RP)",J5)),O5,IF(RIGHT(TRIM(J5),3)=", L",O5,0)) -> 0 | AC5: =IF(ISNUMBER(SEARCH("(RP)",J5)),O5,IF(RIGHT(TRIM(J5),4)=", XL",O5,0)) -> 0 | AD5: =IF(ISNUMBER(SEARCH("(RP)",J5)),O5,IF(OR(RIGHT(TRIM(J5),5)=", XXL",RIGHT(TRIM(J5),5)=", 2XL"),O5,0)) -> 0 | AE5: {=IFERROR(_xlfn.XLOOKUP(H5,Sheet1!$G:$G,Sheet1!$F:$F),IFERROR(_xlfn.XLOOKUP(1,(--($X$2:$X$1074=X5))*(--ISNUMBER(MATCH($H$2:$H$1074,Sheet1!$G:$G,0))),_xlfn.XLOOKUP($H$2:$H$1074,Sheet1!$G:$G,Sheet1!$F:$F,"")),"NOT FOUND"))} -> GETKRTSFUT6125 | AF5: =IFERROR(IF(ISNUMBER(SEARCH("(RP)",J5)),TRIM(SUBSTITUTE(MID(J5,10,LEN(J5)),"(RP)","")),TRIM(MID(J5,FIND(",",J5)+1,FIND(",",J5,FIND(",",J5)+1)-FIND(",",J5)-1))),"") -> OFF WHITE | AG5: =IF(A5="SZAF","Bangalore",IF(A5="SAEX","JHAJJAR",IF(A5="S0EU","HARIPAL",""))) -> Bangalore | AH5: =IF(OR(J5="",AE5="",AE5="NOT FOUND"),"",IF(Y5="RP",IFERROR(LEFT(_xlfn.XLOOKUP(AE5,Sheet1!$F:$F,Sheet1!$W:$W),FIND("-",_xlfn.XLOOKUP(AE5,Sheet1!$F:$F,Sheet1!$W:$W),FIND("-",_xlfn.XLOOKUP(AE5,Sheet1!$F:$F,Sheet1!$W:$W))+1))&AE5,"NOT FOUND"),LEFT(J5,FIND("-",J5,FIND("-",J5)+1))&AE5)) -> KRTS-APWN26-GETKRTSFUT6125
A6: SZAF | B6: 5114202424 | C6: 01.05.2026 | D6: 23.07.2026 | E6: 10337044 | F6: UNITED TEXTILE MILLS PRIVATE LIMITE | G6: 5 | H6: 8909490134412 | I6: 441811508005 | J6: KRTS-APWN26-GETKRTSFUT612, OFF WHITE, XL | L6: EA | M6: 1 | N6: 217 | O6: 217 | Q6: 314.7 | R6: 314.7 | S6: 3414.5 | T6: 68289.9 | U6: 5 | V6: INR | X6: =IF(ISNUMBER(VALUE(LEFT(J6,1))),LEFT(J6,MIN(IFERROR(FIND("A",UPPER(J6)),LEN(J6)+1),IFERROR(FIND("B",UPPER(J6)),LEN(J6)+1),IFERROR(FIND("C",UPPER(J6)),LEN(J6)+1),IFERROR(FIND("D",UPPER(J6)),LEN(J6)+1),IFERROR(FIND("E",UPPER(J6)),LEN(J6)+1),IFERROR(FIND("F",UPPER(J6)),LEN(J6)+1),IFERROR(FIND("G",UPPER(J6)),LEN(J6)+1),IFERROR(FIND("H",UPPER(J6)),LEN(J6)+1),IFERROR(FIND("I",UPPER(J6)),LEN(J6)+1),IFERROR(FIND("J",UPPER(J6)),LEN(J6)+1),IFERROR(FIND("K",UPPER(J6)),LEN(J6)+1),IFERROR(FIND("L",UPPER(J6)),LEN(J6)+1),IFERROR(FIND("M",UPPER(J6)),LEN(J6)+1),IFERROR(FIND("N",UPPER(J6)),LEN(J6)+1),IFERROR(FIND("O",UPPER(J6)),LEN(J6)+1),IFERROR(FIND("P",UPPER(J6)),LEN(J6)+1),IFERROR(FIND("Q",UPPER(J6)),LEN(J6)+1),IFERROR(FIND("R",UPPER(J6)),LEN(J6)+1),IFERROR(FIND("S",UPPER(J6)),LEN(J6)+1),IFERROR(FIND("T",UPPER(J6)),LEN(J6)+1),IFERROR(FIND("U",UPPER(J6)),LEN(J6)+1),IFERROR(FIND("V",UPPER(J6)),LEN(J6)+1),IFERROR(FIND("W",UPPER(J6)),LEN(J6)+1),IFERROR(FIND("X",UPPER(J6)),LEN(J6)+1),IFERROR(FIND("Y",UPPER(J6)),LEN(J6)+1),IFERROR(FIND("Z",UPPER(J6)),LEN(J6)+1))-1),LEFT(TEXT(I6,"0"),LEN(TEXT(I6,"0"))-3)) -> 441811508 | Y6: =IF(ISNUMBER(SEARCH("(RP)",J6)),"RP","DC") -> DC | Z6: =IF(ISNUMBER(SEARCH("(RP)",J6)),O6,IF(RIGHT(TRIM(J6),3)=", S",O6,0)) -> 0 | AA6: =IF(ISNUMBER(SEARCH("(RP)",J6)),O6,IF(RIGHT(TRIM(J6),3)=", M",O6,0)) -> 0 | AB6: =IF(ISNUMBER(SEARCH("(RP)",J6)),O6,IF(RIGHT(TRIM(J6),3)=", L",O6,0)) -> 0 | AC6: =IF(ISNUMBER(SEARCH("(RP)",J6)),O6,IF(RIGHT(TRIM(J6),4)=", XL",O6,0)) -> 217 | AD6: =IF(ISNUMBER(SEARCH("(RP)",J6)),O6,IF(OR(RIGHT(TRIM(J6),5)=", XXL",RIGHT(TRIM(J6),5)=", 2XL"),O6,0)) -> 0 | AE6: {=IFERROR(_xlfn.XLOOKUP(H6,Sheet1!$G:$G,Sheet1!$F:$F),IFERROR(_xlfn.XLOOKUP(1,(--($X$2:$X$1074=X6))*(--ISNUMBER(MATCH($H$2:$H$1074,Sheet1!$G:$G,0))),_xlfn.XLOOKUP($H$2:$H$1074,Sheet1!$G:$G,Sheet1!$F:$F,"")),"NOT FOUND"))} -> GETKRTSFUT6125 | AF6: =IFERROR(IF(ISNUMBER(SEARCH("(RP)",J6)),TRIM(SUBSTITUTE(MID(J6,10,LEN(J6)),"(RP)","")),TRIM(MID(J6,FIND(",",J6)+1,FIND(",",J6,FIND(",",J6)+1)-FIND(",",J6)-1))),"") -> OFF WHITE | AG6: =IF(A6="SZAF","Bangalore",IF(A6="SAEX","JHAJJAR",IF(A6="S0EU","HARIPAL",""))) -> Bangalore | AH6: =IF(OR(J6="",AE6="",AE6="NOT FOUND"),"",IF(Y6="RP",IFERROR(LEFT(_xlfn.XLOOKUP(AE6,Sheet1!$F:$F,Sheet1!$W:$W),FIND("-",_xlfn.XLOOKUP(AE6,Sheet1!$F:$F,Sheet1!$W:$W),FIND("-",_xlfn.XLOOKUP(AE6,Sheet1!$F:$F,Sheet1!$W:$W))+1))&AE6,"NOT FOUND"),LEFT(J6,FIND("-",J6,FIND("-",J6)+1))&AE6)) -> KRTS-APWN26-GETKRTSFUT6125
A7: SAEX | B7: 5114202422 | C7: 01.05.2026 | D7: 23.07.2026 | E7: 10337044 | F7: UNITED TEXTILE MILLS PRIVATE LIMITE | G7: 1 | H7: 8909490134375 | I7: 441811508001 | J7: KRTS-APWN26-GETKRTSFUT61, OFF WHITE, 2XL | L7: EA | M7: 1 | N7: 30 | O7: 30 | Q7: 314.7 | R7: 314.7 | S7: 472.05 | T7: 9441 | U7: 5 | V7: INR | X7: =IF(ISNUMBER(VALUE(LEFT(J7,1))),LEFT(J7,MIN(IFERROR(FIND("A",UPPER(J7)),LEN(J7)+1),IFERROR(FIND("B",UPPER(J7)),LEN(J7)+1),IFERROR(FIND("C",UPPER(J7)),LEN(J7)+1),IFERROR(FIND("D",UPPER(J7)),LEN(J7)+1),IFERROR(FIND("E",UPPER(J7)),LEN(J7)+1),IFERROR(FIND("F",UPPER(J7)),LEN(J7)+1),IFERROR(FIND("G",UPPER(J7)),LEN(J7)+1),IFERROR(FIND("H",UPPER(J7)),LEN(J7)+1),IFERROR(FIND("I",UPPER(J7)),LEN(J7)+1),IFERROR(FIND("J",UPPER(J7)),LEN(J7)+1),IFERROR(FIND("K",UPPER(J7)),LEN(J7)+1),IFERROR(FIND("L",UPPER(J7)),LEN(J7)+1),IFERROR(FIND("M",UPPER(J7)),LEN(J7)+1),IFERROR(FIND("N",UPPER(J7)),LEN(J7)+1),IFERROR(FIND("O",UPPER(J7)),LEN(J7)+1),IFERROR(FIND("P",UPPER(J7)),LEN(J7)+1),IFERROR(FIND("Q",UPPER(J7)),LEN(J7)+1),IFERROR(FIND("R",UPPER(J7)),LEN(J7)+1),IFERROR(FIND("S",UPPER(J7)),LEN(J7)+1),IFERROR(FIND("T",UPPER(J7)),LEN(J7)+1),IFERROR(FIND("U",UPPER(J7)),LEN(J7)+1),IFERROR(FIND("V",UPPER(J7)),LEN(J7)+1),IFERROR(FIND("W",UPPER(J7)),LEN(J7)+1),IFERROR(FIND("X",UPPER(J7)),LEN(J7)+1),IFERROR(FIND("Y",UPPER(J7)),LEN(J7)+1),IFERROR(FIND("Z",UPPER(J7)),LEN(J7)+1))-1),LEFT(TEXT(I7,"0"),LEN(TEXT(I7,"0"))-3)) -> 441811508 | Y7: =IF(ISNUMBER(SEARCH("(RP)",J7)),"RP","DC") -> DC | Z7: =IF(ISNUMBER(SEARCH("(RP)",J7)),O7,IF(RIGHT(TRIM(J7),3)=", S",O7,0)) -> 0 | AA7: =IF(ISNUMBER(SEARCH("(RP)",J7)),O7,IF(RIGHT(TRIM(J7),3)=", M",O7,0)) -> 0 | AB7: =IF(ISNUMBER(SEARCH("(RP)",J7)),O7,IF(RIGHT(TRIM(J7),3)=", L",O7,0)) -> 0 | AC7: =IF(ISNUMBER(SEARCH("(RP)",J7)),O7,IF(RIGHT(TRIM(J7),4)=", XL",O7,0)) -> 0 | AD7: =IF(ISNUMBER(SEARCH("(RP)",J7)),O7,IF(OR(RIGHT(TRIM(J7),5)=", XXL",RIGHT(TRIM(J7),5)=", 2XL"),O7,0)) -> 30 | AE7: {=IFERROR(_xlfn.XLOOKUP(H7,Sheet1!$G:$G,Sheet1!$F:$F),IFERROR(_xlfn.XLOOKUP(1,(--($X$2:$X$1074=X7))*(--ISNUMBER(MATCH($H$2:$H$1074,Sheet1!$G:$G,0))),_xlfn.XLOOKUP($H$2:$H$1074,Sheet1!$G:$G,Sheet1!$F:$F,"")),"NOT FOUND"))} -> GETKRTSFUT6125 | AF7: =IFERROR(IF(ISNUMBER(SEARCH("(RP)",J7)),TRIM(SUBSTITUTE(MID(J7,10,LEN(J7)),"(RP)","")),TRIM(MID(J7,FIND(",",J7)+1,FIND(",",J7,FIND(",",J7)+1)-FIND(",",J7)-1))),"") -> OFF WHITE | AG7: =IF(A7="SZAF","Bangalore",IF(A7="SAEX","JHAJJAR",IF(A7="S0EU","HARIPAL",""))) -> JHAJJAR | AH7: =IF(OR(J7="",AE7="",AE7="NOT FOUND"),"",IF(Y7="RP",IFERROR(LEFT(_xlfn.XLOOKUP(AE7,Sheet1!$F:$F,Sheet1!$W:$W),FIND("-",_xlfn.XLOOKUP(AE7,Sheet1!$F:$F,Sheet1!$W:$W),FIND("-",_xlfn.XLOOKUP(AE7,Sheet1!$F:$F,Sheet1!$W:$W))+1))&AE7,"NOT FOUND"),LEFT(J7,FIND("-",J7,FIND("-",J7)+1))&AE7)) -> KRTS-APWN26-GETKRTSFUT6125
A8: SAEX | B8: 5114202422 | C8: 01.05.2026 | D8: 23.07.2026 | E8: 10337044 | F8: UNITED TEXTILE MILLS PRIVATE LIMITE | G8: 2 | H8: 8909490134382 | I8: 441811508002 | J8: KRTS-APWN26-GETKRTSFUT6125, OFF WHITE, L | L8: EA | M8: 1 | N8: 156 | O8: 156 | Q8: 314.7 | R8: 314.7 | S8: 2454.66 | T8: 49093.2 | U8: 5 | V8: INR | X8: =IF(ISNUMBER(VALUE(LEFT(J8,1))),LEFT(J8,MIN(IFERROR(FIND("A",UPPER(J8)),LEN(J8)+1),IFERROR(FIND("B",UPPER(J8)),LEN(J8)+1),IFERROR(FIND("C",UPPER(J8)),LEN(J8)+1),IFERROR(FIND("D",UPPER(J8)),LEN(J8)+1),IFERROR(FIND("E",UPPER(J8)),LEN(J8)+1),IFERROR(FIND("F",UPPER(J8)),LEN(J8)+1),IFERROR(FIND("G",UPPER(J8)),LEN(J8)+1),IFERROR(FIND("H",UPPER(J8)),LEN(J8)+1),IFERROR(FIND("I",UPPER(J8)),LEN(J8)+1),IFERROR(FIND("J",UPPER(J8)),LEN(J8)+1),IFERROR(FIND("K",UPPER(J8)),LEN(J8)+1),IFERROR(FIND("L",UPPER(J8)),LEN(J8)+1),IFERROR(FIND("M",UPPER(J8)),LEN(J8)+1),IFERROR(FIND("N",UPPER(J8)),LEN(J8)+1),IFERROR(FIND("O",UPPER(J8)),LEN(J8)+1),IFERROR(FIND("P",UPPER(J8)),LEN(J8)+1),IFERROR(FIND("Q",UPPER(J8)),LEN(J8)+1),IFERROR(FIND("R",UPPER(J8)),LEN(J8)+1),IFERROR(FIND("S",UPPER(J8)),LEN(J8)+1),IFERROR(FIND("T",UPPER(J8)),LEN(J8)+1),IFERROR(FIND("U",UPPER(J8)),LEN(J8)+1),IFERROR(FIND("V",UPPER(J8)),LEN(J8)+1),IFERROR(FIND("W",UPPER(J8)),LEN(J8)+1),IFERROR(FIND("X",UPPER(J8)),LEN(J8)+1),IFERROR(FIND("Y",UPPER(J8)),LEN(J8)+1),IFERROR(FIND("Z",UPPER(J8)),LEN(J8)+1))-1),LEFT(TEXT(I8,"0"),LEN(TEXT(I8,"0"))-3)) -> 441811508 | Y8: =IF(ISNUMBER(SEARCH("(RP)",J8)),"RP","DC") -> DC | Z8: =IF(ISNUMBER(SEARCH("(RP)",J8)),O8,IF(RIGHT(TRIM(J8),3)=", S",O8,0)) -> 0 | AA8: =IF(ISNUMBER(SEARCH("(RP)",J8)),O8,IF(RIGHT(TRIM(J8),3)=", M",O8,0)) -> 0 | AB8: =IF(ISNUMBER(SEARCH("(RP)",J8)),O8,IF(RIGHT(TRIM(J8),3)=", L",O8,0)) -> 156 | AC8: =IF(ISNUMBER(SEARCH("(RP)",J8)),O8,IF(RIGHT(TRIM(J8),4)=", XL",O8,0)) -> 0 | AD8: =IF(ISNUMBER(SEARCH("(RP)",J8)),O8,IF(OR(RIGHT(TRIM(J8),5)=", XXL",RIGHT(TRIM(J8),5)=", 2XL"),O8,0)) -> 0 | AE8: {=IFERROR(_xlfn.XLOOKUP(H8,Sheet1!$G:$G,Sheet1!$F:$F),IFERROR(_xlfn.XLOOKUP(1,(--($X$2:$X$1074=X8))*(--ISNUMBER(MATCH($H$2:$H$1074,Sheet1!$G:$G,0))),_xlfn.XLOOKUP($H$2:$H$1074,Sheet1!$G:$G,Sheet1!$F:$F,"")),"NOT FOUND"))} -> GETKRTSFUT6125 | AF8: =IFERROR(IF(ISNUMBER(SEARCH("(RP)",J8)),TRIM(SUBSTITUTE(MID(J8,10,LEN(J8)),"(RP)","")),TRIM(MID(J8,FIND(",",J8)+1,FIND(",",J8,FIND(",",J8)+1)-FIND(",",J8)-1))),"") -> OFF WHITE | AG8: =IF(A8="SZAF","Bangalore",IF(A8="SAEX","JHAJJAR",IF(A8="S0EU","HARIPAL",""))) -> JHAJJAR | AH8: =IF(OR(J8="",AE8="",AE8="NOT FOUND"),"",IF(Y8="RP",IFERROR(LEFT(_xlfn.XLOOKUP(AE8,Sheet1!$F:$F,Sheet1!$W:$W),FIND("-",_xlfn.XLOOKUP(AE8,Sheet1!$F:$F,Sheet1!$W:$W),FIND("-",_xlfn.XLOOKUP(AE8,Sheet1!$F:$F,Sheet1!$W:$W))+1))&AE8,"NOT FOUND"),LEFT(J8,FIND("-",J8,FIND("-",J8)+1))&AE8)) -> KRTS-APWN26-GETKRTSFUT6125
A9: SAEX | B9: 5114202422 | C9: 01.05.2026 | D9: 23.07.2026 | E9: 10337044 | F9: UNITED TEXTILE MILLS PRIVATE LIMITE | G9: 3 | H9: 8909490134399 | I9: 441811508003 | J9: KRTS-APWN26-GETKRTSFUT6125, OFF WHITE, M | L9: EA | M9: 1 | N9: 156 | O9: 156 | Q9: 314.7 | R9: 314.7 | S9: 2454.66 | T9: 49093.2 | U9: 5 | V9: INR | X9: =IF(ISNUMBER(VALUE(LEFT(J9,1))),LEFT(J9,MIN(IFERROR(FIND("A",UPPER(J9)),LEN(J9)+1),IFERROR(FIND("B",UPPER(J9)),LEN(J9)+1),IFERROR(FIND("C",UPPER(J9)),LEN(J9)+1),IFERROR(FIND("D",UPPER(J9)),LEN(J9)+1),IFERROR(FIND("E",UPPER(J9)),LEN(J9)+1),IFERROR(FIND("F",UPPER(J9)),LEN(J9)+1),IFERROR(FIND("G",UPPER(J9)),LEN(J9)+1),IFERROR(FIND("H",UPPER(J9)),LEN(J9)+1),IFERROR(FIND("I",UPPER(J9)),LEN(J9)+1),IFERROR(FIND("J",UPPER(J9)),LEN(J9)+1),IFERROR(FIND("K",UPPER(J9)),LEN(J9)+1),IFERROR(FIND("L",UPPER(J9)),LEN(J9)+1),IFERROR(FIND("M",UPPER(J9)),LEN(J9)+1),IFERROR(FIND("N",UPPER(J9)),LEN(J9)+1),IFERROR(FIND("O",UPPER(J9)),LEN(J9)+1),IFERROR(FIND("P",UPPER(J9)),LEN(J9)+1),IFERROR(FIND("Q",UPPER(J9)),LEN(J9)+1),IFERROR(FIND("R",UPPER(J9)),LEN(J9)+1),IFERROR(FIND("S",UPPER(J9)),LEN(J9)+1),IFERROR(FIND("T",UPPER(J9)),LEN(J9)+1),IFERROR(FIND("U",UPPER(J9)),LEN(J9)+1),IFERROR(FIND("V",UPPER(J9)),LEN(J9)+1),IFERROR(FIND("W",UPPER(J9)),LEN(J9)+1),IFERROR(FIND("X",UPPER(J9)),LEN(J9)+1),IFERROR(FIND("Y",UPPER(J9)),LEN(J9)+1),IFERROR(FIND("Z",UPPER(J9)),LEN(J9)+1))-1),LEFT(TEXT(I9,"0"),LEN(TEXT(I9,"0"))-3)) -> 441811508 | Y9: =IF(ISNUMBER(SEARCH("(RP)",J9)),"RP","DC") -> DC | Z9: =IF(ISNUMBER(SEARCH("(RP)",J9)),O9,IF(RIGHT(TRIM(J9),3)=", S",O9,0)) -> 0 | AA9: =IF(ISNUMBER(SEARCH("(RP)",J9)),O9,IF(RIGHT(TRIM(J9),3)=", M",O9,0)) -> 156 | AB9: =IF(ISNUMBER(SEARCH("(RP)",J9)),O9,IF(RIGHT(TRIM(J9),3)=", L",O9,0)) -> 0 | AC9: =IF(ISNUMBER(SEARCH("(RP)",J9)),O9,IF(RIGHT(TRIM(J9),4)=", XL",O9,0)) -> 0 | AD9: =IF(ISNUMBER(SEARCH("(RP)",J9)),O9,IF(OR(RIGHT(TRIM(J9),5)=", XXL",RIGHT(TRIM(J9),5)=", 2XL"),O9,0)) -> 0 | AE9: {=IFERROR(_xlfn.XLOOKUP(H9,Sheet1!$G:$G,Sheet1!$F:$F),IFERROR(_xlfn.XLOOKUP(1,(--($X$2:$X$1074=X9))*(--ISNUMBER(MATCH($H$2:$H$1074,Sheet1!$G:$G,0))),_xlfn.XLOOKUP($H$2:$H$1074,Sheet1!$G:$G,Sheet1!$F:$F,"")),"NOT FOUND"))} -> GETKRTSFUT6125 | AF9: =IFERROR(IF(ISNUMBER(SEARCH("(RP)",J9)),TRIM(SUBSTITUTE(MID(J9,10,LEN(J9)),"(RP)","")),TRIM(MID(J9,FIND(",",J9)+1,FIND(",",J9,FIND(",",J9)+1)-FIND(",",J9)-1))),"") -> OFF WHITE | AG9: =IF(A9="SZAF","Bangalore",IF(A9="SAEX","JHAJJAR",IF(A9="S0EU","HARIPAL",""))) -> JHAJJAR | AH9: =IF(OR(J9="",AE9="",AE9="NOT FOUND"),"",IF(Y9="RP",IFERROR(LEFT(_xlfn.XLOOKUP(AE9,Sheet1!$F:$F,Sheet1!$W:$W),FIND("-",_xlfn.XLOOKUP(AE9,Sheet1!$F:$F,Sheet1!$W:$W),FIND("-",_xlfn.XLOOKUP(AE9,Sheet1!$F:$F,Sheet1!$W:$W))+1))&AE9,"NOT FOUND"),LEFT(J9,FIND("-",J9,FIND("-",J9)+1))&AE9)) -> KRTS-APWN26-GETKRTSFUT6125
A10: SAEX | B10: 5114202422 | C10: 01.05.2026 | D10: 23.07.2026 | E10: 10337044 | F10: UNITED TEXTILE MILLS PRIVATE LIMITE | G10: 4 | H10: 8909490134405 | I10: 441811508004 | J10: KRTS-APWN26-GETKRTSFUT6125, OFF WHITE, S | L10: EA | M10: 1 | N10: 30 | O10: 30 | Q10: 314.7 | R10: 314.7 | S10: 472.05 | T10: 9441 | U10: 5 | V10: INR | X10: =IF(ISNUMBER(VALUE(LEFT(J10,1))),LEFT(J10,MIN(IFERROR(FIND("A",UPPER(J10)),LEN(J10)+1),IFERROR(FIND("B",UPPER(J10)),LEN(J10)+1),IFERROR(FIND("C",UPPER(J10)),LEN(J10)+1),IFERROR(FIND("D",UPPER(J10)),LEN(J10)+1),IFERROR(FIND("E",UPPER(J10)),LEN(J10)+1),IFERROR(FIND("F",UPPER(J10)),LEN(J10)+1),IFERROR(FIND("G",UPPER(J10)),LEN(J10)+1),IFERROR(FIND("H",UPPER(J10)),LEN(J10)+1),IFERROR(FIND("I",UPPER(J10)),LEN(J10)+1),IFERROR(FIND("J",UPPER(J10)),LEN(J10)+1),IFERROR(FIND("K",UPPER(J10)),LEN(J10)+1),IFERROR(FIND("L",UPPER(J10)),LEN(J10)+1),IFERROR(FIND("M",UPPER(J10)),LEN(J10)+1),IFERROR(FIND("N",UPPER(J10)),LEN(J10)+1),IFERROR(FIND("O",UPPER(J10)),LEN(J10)+1),IFERROR(FIND("P",UPPER(J10)),LEN(J10)+1),IFERROR(FIND("Q",UPPER(J10)),LEN(J10)+1),IFERROR(FIND("R",UPPER(J10)),LEN(J10)+1),IFERROR(FIND("S",UPPER(J10)),LEN(J10)+1),IFERROR(FIND("T",UPPER(J10)),LEN(J10)+1),IFERROR(FIND("U",UPPER(J10)),LEN(J10)+1),IFERROR(FIND("V",UPPER(J10)),LEN(J10)+1),IFERROR(FIND("W",UPPER(J10)),LEN(J10)+1),IFERROR(FIND("X",UPPER(J10)),LEN(J10)+1),IFERROR(FIND("Y",UPPER(J10)),LEN(J10)+1),IFERROR(FIND("Z",UPPER(J10)),LEN(J10)+1))-1),LEFT(TEXT(I10,"0"),LEN(TEXT(I10,"0"))-3)) -> 441811508 | Y10: =IF(ISNUMBER(SEARCH("(RP)",J10)),"RP","DC") -> DC | Z10: =IF(ISNUMBER(SEARCH("(RP)",J10)),O10,IF(RIGHT(TRIM(J10),3)=", S",O10,0)) -> 30 | AA10: =IF(ISNUMBER(SEARCH("(RP)",J10)),O10,IF(RIGHT(TRIM(J10),3)=", M",O10,0)) -> 0 | AB10: =IF(ISNUMBER(SEARCH("(RP)",J10)),O10,IF(RIGHT(TRIM(J10),3)=", L",O10,0)) -> 0 | AC10: =IF(ISNUMBER(SEARCH("(RP)",J10)),O10,IF(RIGHT(TRIM(J10),4)=", XL",O10,0)) -> 0 | AD10: =IF(ISNUMBER(SEARCH("(RP)",J10)),O10,IF(OR(RIGHT(TRIM(J10),5)=", XXL",RIGHT(TRIM(J10),5)=", 2XL"),O10,0)) -> 0 | AE10: {=IFERROR(_xlfn.XLOOKUP(H10,Sheet1!$G:$G,Sheet1!$F:$F),IFERROR(_xlfn.XLOOKUP(1,(--($X$2:$X$1074=X10))*(--ISNUMBER(MATCH($H$2:$H$1074,Sheet1!$G:$G,0))),_xlfn.XLOOKUP($H$2:$H$1074,Sheet1!$G:$G,Sheet1!$F:$F,"")),"NOT FOUND"))} -> GETKRTSFUT6125 | AF10: =IFERROR(IF(ISNUMBER(SEARCH("(RP)",J10)),TRIM(SUBSTITUTE(MID(J10,10,LEN(J10)),"(RP)","")),TRIM(MID(J10,FIND(",",J10)+1,FIND(",",J10,FIND(",",J10)+1)-FIND(",",J10)-1))),"") -> OFF WHITE | AG10: =IF(A10="SZAF","Bangalore",IF(A10="SAEX","JHAJJAR",IF(A10="S0EU","HARIPAL",""))) -> JHAJJAR | AH10: =IF(OR(J10="",AE10="",AE10="NOT FOUND"),"",IF(Y10="RP",IFERROR(LEFT(_xlfn.XLOOKUP(AE10,Sheet1!$F:$F,Sheet1!$W:$W),FIND("-",_xlfn.XLOOKUP(AE10,Sheet1!$F:$F,Sheet1!$W:$W),FIND("-",_xlfn.XLOOKUP(AE10,Sheet1!$F:$F,Sheet1!$W:$W))+1))&AE10,"NOT FOUND"),LEFT(J10,FIND("-",J10,FIND("-",J10)+1))&AE10)) -> KRTS-APWN26-GETKRTSFUT6125
A11: SAEX | B11: 5114202422 | C11: 01.05.2026 | D11: 23.07.2026 | E11: 10337044 | F11: UNITED TEXTILE MILLS PRIVATE LIMITE | G11: 5 | H11: 8909490134412 | I11: 441811508005 | J11: KRTS-APWN26-GETKRTSFUT612, OFF WHITE, XL | L11: EA | M11: 1 | N11: 132 | O11: 132 | Q11: 314.7 | R11: 314.7 | S11: 2077.02 | T11: 41540.4 | U11: 5 | V11: INR | X11: =IF(ISNUMBER(VALUE(LEFT(J11,1))),LEFT(J11,MIN(IFERROR(FIND("A",UPPER(J11)),LEN(J11)+1),IFERROR(FIND("B",UPPER(J11)),LEN(J11)+1),IFERROR(FIND("C",UPPER(J11)),LEN(J11)+1),IFERROR(FIND("D",UPPER(J11)),LEN(J11)+1),IFERROR(FIND("E",UPPER(J11)),LEN(J11)+1),IFERROR(FIND("F",UPPER(J11)),LEN(J11)+1),IFERROR(FIND("G",UPPER(J11)),LEN(J11)+1),IFERROR(FIND("H",UPPER(J11)),LEN(J11)+1),IFERROR(FIND("I",UPPER(J11)),LEN(J11)+1),IFERROR(FIND("J",UPPER(J11)),LEN(J11)+1),IFERROR(FIND("K",UPPER(J11)),LEN(J11)+1),IFERROR(FIND("L",UPPER(J11)),LEN(J11)+1),IFERROR(FIND("M",UPPER(J11)),LEN(J11)+1),IFERROR(FIND("N",UPPER(J11)),LEN(J11)+1),IFERROR(FIND("O",UPPER(J11)),LEN(J11)+1),IFERROR(FIND("P",UPPER(J11)),LEN(J11)+1),IFERROR(FIND("Q",UPPER(J11)),LEN(J11)+1),IFERROR(FIND("R",UPPER(J11)),LEN(J11)+1),IFERROR(FIND("S",UPPER(J11)),LEN(J11)+1),IFERROR(FIND("T",UPPER(J11)),LEN(J11)+1),IFERROR(FIND("U",UPPER(J11)),LEN(J11)+1),IFERROR(FIND("V",UPPER(J11)),LEN(J11)+1),IFERROR(FIND("W",UPPER(J11)),LEN(J11)+1),IFERROR(FIND("X",UPPER(J11)),LEN(J11)+1),IFERROR(FIND("Y",UPPER(J11)),LEN(J11)+1),IFERROR(FIND("Z",UPPER(J11)),LEN(J11)+1))-1),LEFT(TEXT(I11,"0"),LEN(TEXT(I11,"0"))-3)) -> 441811508 | Y11: =IF(ISNUMBER(SEARCH("(RP)",J11)),"RP","DC") -> DC | Z11: =IF(ISNUMBER(SEARCH("(RP)",J11)),O11,IF(RIGHT(TRIM(J11),3)=", S",O11,0)) -> 0 | AA11: =IF(ISNUMBER(SEARCH("(RP)",J11)),O11,IF(RIGHT(TRIM(J11),3)=", M",O11,0)) -> 0 | AB11: =IF(ISNUMBER(SEARCH("(RP)",J11)),O11,IF(RIGHT(TRIM(J11),3)=", L",O11,0)) -> 0 | AC11: =IF(ISNUMBER(SEARCH("(RP)",J11)),O11,IF(RIGHT(TRIM(J11),4)=", XL",O11,0)) -> 132 | AD11: =IF(ISNUMBER(SEARCH("(RP)",J11)),O11,IF(OR(RIGHT(TRIM(J11),5)=", XXL",RIGHT(TRIM(J11),5)=", 2XL"),O11,0)) -> 0 | AE11: {=IFERROR(_xlfn.XLOOKUP(H11,Sheet1!$G:$G,Sheet1!$F:$F),IFERROR(_xlfn.XLOOKUP(1,(--($X$2:$X$1074=X11))*(--ISNUMBER(MATCH($H$2:$H$1074,Sheet1!$G:$G,0))),_xlfn.XLOOKUP($H$2:$H$1074,Sheet1!$G:$G,Sheet1!$F:$F,"")),"NOT FOUND"))} -> GETKRTSFUT6125 | AF11: =IFERROR(IF(ISNUMBER(SEARCH("(RP)",J11)),TRIM(SUBSTITUTE(MID(J11,10,LEN(J11)),"(RP)","")),TRIM(MID(J11,FIND(",",J11)+1,FIND(",",J11,FIND(",",J11)+1)-FIND(",",J11)-1))),"") -> OFF WHITE | AG11: =IF(A11="SZAF","Bangalore",IF(A11="SAEX","JHAJJAR",IF(A11="S0EU","HARIPAL",""))) -> JHAJJAR | AH11: =IF(OR(J11="",AE11="",AE11="NOT FOUND"),"",IF(Y11="RP",IFERROR(LEFT(_xlfn.XLOOKUP(AE11,Sheet1!$F:$F,Sheet1!$W:$W),FIND("-",_xlfn.XLOOKUP(AE11,Sheet1!$F:$F,Sheet1!$W:$W),FIND("-",_xlfn.XLOOKUP(AE11,Sheet1!$F:$F,Sheet1!$W:$W))+1))&AE11,"NOT FOUND"),LEFT(J11,FIND("-",J11,FIND("-",J11)+1))&AE11)) -> KRTS-APWN26-GETKRTSFUT6125
A12: S0EU | B12: 5114202420 | C12: 01.05.2026 | D12: 23.07.2026 | E12: 10337044 | F12: UNITED TEXTILE MILLS PRIVATE LIMITE | G12: 1 | H12: 8909490134375 | I12: 441811508001 | J12: KRTS-APWN26-GETKRTSFUT61, OFF WHITE, 2XL | L12: EA | M12: 1 | N12: 30 | O12: 30 | Q12: 314.7 | R12: 314.7 | S12: 472.05 | T12: 9441 | U12: 5 | V12: INR | X12: =IF(ISNUMBER(VALUE(LEFT(J12,1))),LEFT(J12,MIN(IFERROR(FIND("A",UPPER(J12)),LEN(J12)+1),IFERROR(FIND("B",UPPER(J12)),LEN(J12)+1),IFERROR(FIND("C",UPPER(J12)),LEN(J12)+1),IFERROR(FIND("D",UPPER(J12)),LEN(J12)+1),IFERROR(FIND("E",UPPER(J12)),LEN(J12)+1),IFERROR(FIND("F",UPPER(J12)),LEN(J12)+1),IFERROR(FIND("G",UPPER(J12)),LEN(J12)+1),IFERROR(FIND("H",UPPER(J12)),LEN(J12)+1),IFERROR(FIND("I",UPPER(J12)),LEN(J12)+1),IFERROR(FIND("J",UPPER(J12)),LEN(J12)+1),IFERROR(FIND("K",UPPER(J12)),LEN(J12)+1),IFERROR(FIND("L",UPPER(J12)),LEN(J12)+1),IFERROR(FIND("M",UPPER(J12)),LEN(J12)+1),IFERROR(FIND("N",UPPER(J12)),LEN(J12)+1),IFERROR(FIND("O",UPPER(J12)),LEN(J12)+1),IFERROR(FIND("P",UPPER(J12)),LEN(J12)+1),IFERROR(FIND("Q",UPPER(J12)),LEN(J12)+1),IFERROR(FIND("R",UPPER(J12)),LEN(J12)+1),IFERROR(FIND("S",UPPER(J12)),LEN(J12)+1),IFERROR(FIND("T",UPPER(J12)),LEN(J12)+1),IFERROR(FIND("U",UPPER(J12)),LEN(J12)+1),IFERROR(FIND("V",UPPER(J12)),LEN(J12)+1),IFERROR(FIND("W",UPPER(J12)),LEN(J12)+1),IFERROR(FIND("X",UPPER(J12)),LEN(J12)+1),IFERROR(FIND("Y",UPPER(J12)),LEN(J12)+1),IFERROR(FIND("Z",UPPER(J12)),LEN(J12)+1))-1),LEFT(TEXT(I12,"0"),LEN(TEXT(I12,"0"))-3)) -> 441811508 | Y12: =IF(ISNUMBER(SEARCH("(RP)",J12)),"RP","DC") -> DC | Z12: =IF(ISNUMBER(SEARCH("(RP)",J12)),O12,IF(RIGHT(TRIM(J12),3)=", S",O12,0)) -> 0 | AA12: =IF(ISNUMBER(SEARCH("(RP)",J12)),O12,IF(RIGHT(TRIM(J12),3)=", M",O12,0)) -> 0 | AB12: =IF(ISNUMBER(SEARCH("(RP)",J12)),O12,IF(RIGHT(TRIM(J12),3)=", L",O12,0)) -> 0 | AC12: =IF(ISNUMBER(SEARCH("(RP)",J12)),O12,IF(RIGHT(TRIM(J12),4)=", XL",O12,0)) -> 0 | AD12: =IF(ISNUMBER(SEARCH("(RP)",J12)),O12,IF(OR(RIGHT(TRIM(J12),5)=", XXL",RIGHT(TRIM(J12),5)=", 2XL"),O12,0)) -> 30 | AE12: {=IFERROR(_xlfn.XLOOKUP(H12,Sheet1!$G:$G,Sheet1!$F:$F),IFERROR(_xlfn.XLOOKUP(1,(--($X$2:$X$1074=X12))*(--ISNUMBER(MATCH($H$2:$H$1074,Sheet1!$G:$G,0))),_xlfn.XLOOKUP($H$2:$H$1074,Sheet1!$G:$G,Sheet1!$F:$F,"")),"NOT FOUND"))} -> GETKRTSFUT6125 | AF12: =IFERROR(IF(ISNUMBER(SEARCH("(RP)",J12)),TRIM(SUBSTITUTE(MID(J12,10,LEN(J12)),"(RP)","")),TRIM(MID(J12,FIND(",",J12)+1,FIND(",",J12,FIND(",",J12)+1)-FIND(",",J12)-1))),"") -> OFF WHITE | AG12: =IF(A12="SZAF","Bangalore",IF(A12="SAEX","JHAJJAR",IF(A12="S0EU","HARIPAL",""))) -> HARIPAL | AH12: =IF(OR(J12="",AE12="",AE12="NOT FOUND"),"",IF(Y12="RP",IFERROR(LEFT(_xlfn.XLOOKUP(AE12,Sheet1!$F:$F,Sheet1!$W:$W),FIND("-",_xlfn.XLOOKUP(AE12,Sheet1!$F:$F,Sheet1!$W:$W),FIND("-",_xlfn.XLOOKUP(AE12,Sheet1!$F:$F,Sheet1!$W:$W))+1))&AE12,"NOT FOUND"),LEFT(J12,FIND("-",J12,FIND("-",J12)+1))&AE12)) -> KRTS-APWN26-GETKRTSFUT6125
A13: S0EU | B13: 5114202420 | C13: 01.05.2026 | D13: 23.07.2026 | E13: 10337044 | F13: UNITED TEXTILE MILLS PRIVATE LIMITE | G13: 2 | H13: 8909490134382 | I13: 441811508002 | J13: KRTS-APWN26-GETKRTSFUT6125, OFF WHITE, L | L13: EA | M13: 1 | N13: 186 | O13: 186 | Q13: 314.7 | R13: 314.7 | S13: 2926.71 | T13: 58534.2 | U13: 5 | V13: INR | X13: =IF(ISNUMBER(VALUE(LEFT(J13,1))),LEFT(J13,MIN(IFERROR(FIND("A",UPPER(J13)),LEN(J13)+1),IFERROR(FIND("B",UPPER(J13)),LEN(J13)+1),IFERROR(FIND("C",UPPER(J13)),LEN(J13)+1),IFERROR(FIND("D",UPPER(J13)),LEN(J13)+1),IFERROR(FIND("E",UPPER(J13)),LEN(J13)+1),IFERROR(FIND("F",UPPER(J13)),LEN(J13)+1),IFERROR(FIND("G",UPPER(J13)),LEN(J13)+1),IFERROR(FIND("H",UPPER(J13)),LEN(J13)+1),IFERROR(FIND("I",UPPER(J13)),LEN(J13)+1),IFERROR(FIND("J",UPPER(J13)),LEN(J13)+1),IFERROR(FIND("K",UPPER(J13)),LEN(J13)+1),IFERROR(FIND("L",UPPER(J13)),LEN(J13)+1),IFERROR(FIND("M",UPPER(J13)),LEN(J13)+1),IFERROR(FIND("N",UPPER(J13)),LEN(J13)+1),IFERROR(FIND("O",UPPER(J13)),LEN(J13)+1),IFERROR(FIND("P",UPPER(J13)),LEN(J13)+1),IFERROR(FIND("Q",UPPER(J13)),LEN(J13)+1),IFERROR(FIND("R",UPPER(J13)),LEN(J13)+1),IFERROR(FIND("S",UPPER(J13)),LEN(J13)+1),IFERROR(FIND("T",UPPER(J13)),LEN(J13)+1),IFERROR(FIND("U",UPPER(J13)),LEN(J13)+1),IFERROR(FIND("V",UPPER(J13)),LEN(J13)+1),IFERROR(FIND("W",UPPER(J13)),LEN(J13)+1),IFERROR(FIND("X",UPPER(J13)),LEN(J13)+1),IFERROR(FIND("Y",UPPER(J13)),LEN(J13)+1),IFERROR(FIND("Z",UPPER(J13)),LEN(J13)+1))-1),LEFT(TEXT(I13,"0"),LEN(TEXT(I13,"0"))-3)) -> 441811508 | Y13: =IF(ISNUMBER(SEARCH("(RP)",J13)),"RP","DC") -> DC | Z13: =IF(ISNUMBER(SEARCH("(RP)",J13)),O13,IF(RIGHT(TRIM(J13),3)=", S",O13,0)) -> 0 | AA13: =IF(ISNUMBER(SEARCH("(RP)",J13)),O13,IF(RIGHT(TRIM(J13),3)=", M",O13,0)) -> 0 | AB13: =IF(ISNUMBER(SEARCH("(RP)",J13)),O13,IF(RIGHT(TRIM(J13),3)=", L",O13,0)) -> 186 | AC13: =IF(ISNUMBER(SEARCH("(RP)",J13)),O13,IF(RIGHT(TRIM(J13),4)=", XL",O13,0)) -> 0 | AD13: =IF(ISNUMBER(SEARCH("(RP)",J13)),O13,IF(OR(RIGHT(TRIM(J13),5)=", XXL",RIGHT(TRIM(J13),5)=", 2XL"),O13,0)) -> 0 | AE13: {=IFERROR(_xlfn.XLOOKUP(H13,Sheet1!$G:$G,Sheet1!$F:$F),IFERROR(_xlfn.XLOOKUP(1,(--($X$2:$X$1074=X13))*(--ISNUMBER(MATCH($H$2:$H$1074,Sheet1!$G:$G,0))),_xlfn.XLOOKUP($H$2:$H$1074,Sheet1!$G:$G,Sheet1!$F:$F,"")),"NOT FOUND"))} -> GETKRTSFUT6125 | AF13: =IFERROR(IF(ISNUMBER(SEARCH("(RP)",J13)),TRIM(SUBSTITUTE(MID(J13,10,LEN(J13)),"(RP)","")),TRIM(MID(J13,FIND(",",J13)+1,FIND(",",J13,FIND(",",J13)+1)-FIND(",",J13)-1))),"") -> OFF WHITE | AG13: =IF(A13="SZAF","Bangalore",IF(A13="SAEX","JHAJJAR",IF(A13="S0EU","HARIPAL",""))) -> HARIPAL | AH13: =IF(OR(J13="",AE13="",AE13="NOT FOUND"),"",IF(Y13="RP",IFERROR(LEFT(_xlfn.XLOOKUP(AE13,Sheet1!$F:$F,Sheet1!$W:$W),FIND("-",_xlfn.XLOOKUP(AE13,Sheet1!$F:$F,Sheet1!$W:$W),FIND("-",_xlfn.XLOOKUP(AE13,Sheet1!$F:$F,Sheet1!$W:$W))+1))&AE13,"NOT FOUND"),LEFT(J13,FIND("-",J13,FIND("-",J13)+1))&AE13)) -> KRTS-APWN26-GETKRTSFUT6125
A14: S0EU | B14: 5114202420 | C14: 01.05.2026 | D14: 23.07.2026 | E14: 10337044 | F14: UNITED TEXTILE MILLS PRIVATE LIMITE | G14: 3 | H14: 8909490134399 | I14: 441811508003 | J14: KRTS-APWN26-GETKRTSFUT6125, OFF WHITE, M | L14: EA | M14: 1 | N14: 186 | O14: 186 | Q14: 314.7 | R14: 314.7 | S14: 2926.71 | T14: 58534.2 | U14: 5 | V14: INR | X14: =IF(ISNUMBER(VALUE(LEFT(J14,1))),LEFT(J14,MIN(IFERROR(FIND("A",UPPER(J14)),LEN(J14)+1),IFERROR(FIND("B",UPPER(J14)),LEN(J14)+1),IFERROR(FIND("C",UPPER(J14)),LEN(J14)+1),IFERROR(FIND("D",UPPER(J14)),LEN(J14)+1),IFERROR(FIND("E",UPPER(J14)),LEN(J14)+1),IFERROR(FIND("F",UPPER(J14)),LEN(J14)+1),IFERROR(FIND("G",UPPER(J14)),LEN(J14)+1),IFERROR(FIND("H",UPPER(J14)),LEN(J14)+1),IFERROR(FIND("I",UPPER(J14)),LEN(J14)+1),IFERROR(FIND("J",UPPER(J14)),LEN(J14)+1),IFERROR(FIND("K",UPPER(J14)),LEN(J14)+1),IFERROR(FIND("L",UPPER(J14)),LEN(J14)+1),IFERROR(FIND("M",UPPER(J14)),LEN(J14)+1),IFERROR(FIND("N",UPPER(J14)),LEN(J14)+1),IFERROR(FIND("O",UPPER(J14)),LEN(J14)+1),IFERROR(FIND("P",UPPER(J14)),LEN(J14)+1),IFERROR(FIND("Q",UPPER(J14)),LEN(J14)+1),IFERROR(FIND("R",UPPER(J14)),LEN(J14)+1),IFERROR(FIND("S",UPPER(J14)),LEN(J14)+1),IFERROR(FIND("T",UPPER(J14)),LEN(J14)+1),IFERROR(FIND("U",UPPER(J14)),LEN(J14)+1),IFERROR(FIND("V",UPPER(J14)),LEN(J14)+1),IFERROR(FIND("W",UPPER(J14)),LEN(J14)+1),IFERROR(FIND("X",UPPER(J14)),LEN(J14)+1),IFERROR(FIND("Y",UPPER(J14)),LEN(J14)+1),IFERROR(FIND("Z",UPPER(J14)),LEN(J14)+1))-1),LEFT(TEXT(I14,"0"),LEN(TEXT(I14,"0"))-3)) -> 441811508 | Y14: =IF(ISNUMBER(SEARCH("(RP)",J14)),"RP","DC") -> DC | Z14: =IF(ISNUMBER(SEARCH("(RP)",J14)),O14,IF(RIGHT(TRIM(J14),3)=", S",O14,0)) -> 0 | AA14: =IF(ISNUMBER(SEARCH("(RP)",J14)),O14,IF(RIGHT(TRIM(J14),3)=", M",O14,0)) -> 186 | AB14: =IF(ISNUMBER(SEARCH("(RP)",J14)),O14,IF(RIGHT(TRIM(J14),3)=", L",O14,0)) -> 0 | AC14: =IF(ISNUMBER(SEARCH("(RP)",J14)),O14,IF(RIGHT(TRIM(J14),4)=", XL",O14,0)) -> 0 | AD14: =IF(ISNUMBER(SEARCH("(RP)",J14)),O14,IF(OR(RIGHT(TRIM(J14),5)=", XXL",RIGHT(TRIM(J14),5)=", 2XL"),O14,0)) -> 0 | AE14: {=IFERROR(_xlfn.XLOOKUP(H14,Sheet1!$G:$G,Sheet1!$F:$F),IFERROR(_xlfn.XLOOKUP(1,(--($X$2:$X$1074=X14))*(--ISNUMBER(MATCH($H$2:$H$1074,Sheet1!$G:$G,0))),_xlfn.XLOOKUP($H$2:$H$1074,Sheet1!$G:$G,Sheet1!$F:$F,"")),"NOT FOUND"))} -> GETKRTSFUT6125 | AF14: =IFERROR(IF(ISNUMBER(SEARCH("(RP)",J14)),TRIM(SUBSTITUTE(MID(J14,10,LEN(J14)),"(RP)","")),TRIM(MID(J14,FIND(",",J14)+1,FIND(",",J14,FIND(",",J14)+1)-FIND(",",J14)-1))),"") -> OFF WHITE | AG14: =IF(A14="SZAF","Bangalore",IF(A14="SAEX","JHAJJAR",IF(A14="S0EU","HARIPAL",""))) -> HARIPAL | AH14: =IF(OR(J14="",AE14="",AE14="NOT FOUND"),"",IF(Y14="RP",IFERROR(LEFT(_xlfn.XLOOKUP(AE14,Sheet1!$F:$F,Sheet1!$W:$W),FIND("-",_xlfn.XLOOKUP(AE14,Sheet1!$F:$F,Sheet1!$W:$W),FIND("-",_xlfn.XLOOKUP(AE14,Sheet1!$F:$F,Sheet1!$W:$W))+1))&AE14,"NOT FOUND"),LEFT(J14,FIND("-",J14,FIND("-",J14)+1))&AE14)) -> KRTS-APWN26-GETKRTSFUT6125
... A636: SZAF | B636: 5112963769 | C636: 30.01.2026 | D636: 30.06.2026 | E636: 10337044 | F636: UNITED TEXTILE MILLS PRIVATE LIMITE | G636: 5 | H636: 8909103992484 | I636: 441857089014 | J636: KRTS-APSU26-YETKRTSCUT5008, RUST, M | L636: EA | M636: 1 | N636: 566 | O636: 566 | Q636: 0 | R636: 0 | S636: 0 | T636: 0 | U636: 0 | V636: INR | X636: =IF(ISNUMBER(VALUE(LEFT(J636,1))),LEFT(J636,MIN(IFERROR(FIND("A",UPPER(J636)),LEN(J636)+1),IFERROR(FIND("B",UPPER(J636)),LEN(J636)+1),IFERROR(FIND("C",UPPER(J636)),LEN(J636)+1),IFERROR(FIND("D",UPPER(J636)),LEN(J636)+1),IFERROR(FIND("E",UPPER(J636)),LEN(J636)+1),IFERROR(FIND("F",UPPER(J636)),LEN(J636)+1),IFERROR(FIND("G",UPPER(J636)),LEN(J636)+1),IFERROR(FIND("H",UPPER(J636)),LEN(J636)+1),IFERROR(FIND("I",UPPER(J636)),LEN(J636)+1),IFERROR(FIND("J",UPPER(J636)),LEN(J636)+1),IFERROR(FIND("K",UPPER(J636)),LEN(J636)+1),IFERROR(FIND("L",UPPER(J636)),LEN(J636)+1),IFERROR(FIND("M",UPPER(J636)),LEN(J636)+1),IFERROR(FIND("N",UPPER(J636)),LEN(J636)+1),IFERROR(FIND("O",UPPER(J636)),LEN(J636)+1),IFERROR(FIND("P",UPPER(J636)),LEN(J636)+1),IFERROR(FIND("Q",UPPER(J636)),LEN(J636)+1),IFERROR(FIND("R",UPPER(J636)),LEN(J636)+1),IFERROR(FIND("S",UPPER(J636)),LEN(J636)+1),IFERROR(FIND("T",UPPER(J636)),LEN(J636)+1),IFERROR(FIND("U",UPPER(J636)),LEN(J636)+1),IFERROR(FIND("V",UPPER(J636)),LEN(J636)+1),IFERROR(FIND("W",UPPER(J636)),LEN(J636)+1),IFERROR(FIND("X",UPPER(J636)),LEN(J636)+1),IFERROR(FIND("Y",UPPER(J636)),LEN(J636)+1),IFERROR(FIND("Z",UPPER(J636)),LEN(J636)+1))-1),LEFT(TEXT(I636,"0"),LEN(TEXT(I636,"0"))-3)) -> 441857089 | Y636: =IF(ISNUMBER(SEARCH("(RP)",J636)),"RP","DC") -> DC | Z636: =IF(ISNUMBER(SEARCH("(RP)",J636)),O636,IF(RIGHT(TRIM(J636),3)=", S",O636,0)) -> 0 | AA636: =IF(ISNUMBER(SEARCH("(RP)",J636)),O636,IF(RIGHT(TRIM(J636),3)=", M",O636,0)) -> 566 | AB636: =IF(ISNUMBER(SEARCH("(RP)",J636)),O636,IF(RIGHT(TRIM(J636),3)=", L",O636,0)) -> 0 | AC636: =IF(ISNUMBER(SEARCH("(RP)",J636)),O636,IF(RIGHT(TRIM(J636),4)=", XL",O636,0)) -> 0 | AD636: =IF(ISNUMBER(SEARCH("(RP)",J636)),O636,IF(OR(RIGHT(TRIM(J636),5)=", XXL",RIGHT(TRIM(J636),5)=", 2XL"),O636,0)) -> 0 | AE636: {=IFERROR(_xlfn.XLOOKUP(H636,Sheet1!$G:$G,Sheet1!$F:$F),IFERROR(_xlfn.XLOOKUP(1,(--($X$2:$X$1074=X636))*(--ISNUMBER(MATCH($H$2:$H$1074,Sheet1!$G:$G,0))),_xlfn.XLOOKUP($H$2:$H$1074,Sheet1!$G:$G,Sheet1!$F:$F,"")),"NOT FOUND"))} -> YETKRTSCUT5008 | AF636: =IFERROR(IF(ISNUMBER(SEARCH("(RP)",J636)),TRIM(SUBSTITUTE(MID(J636,10,LEN(J636)),"(RP)","")),TRIM(MID(J636,FIND(",",J636)+1,FIND(",",J636,FIND(",",J636)+1)-FIND(",",J636)-1))),"") -> RUST | AG636: =IF(A636="SZAF","Bangalore",IF(A636="SAEX","JHAJJAR",IF(A636="S0EU","HARIPAL",""))) -> Bangalore | AH636: =IF(OR(J636="",AE636="",AE636="NOT FOUND"),"",IF(Y636="RP",IFERROR(LEFT(_xlfn.XLOOKUP(AE636,Sheet1!$F:$F,Sheet1!$W:$W),FIND("-",_xlfn.XLOOKUP(AE636,Sheet1!$F:$F,Sheet1!$W:$W),FIND("-",_xlfn.XLOOKUP(AE636,Sheet1!$F:$F,Sheet1!$W:$W))+1))&AE636,"NOT FOUND"),LEFT(J636,FIND("-",J636,FIND("-",J636)+1))&AE636)) -> KRTS-APSU26-YETKRTSCUT5008
A637: SZAF | B637: 5112963769 | C637: 30.01.2026 | D637: 30.06.2026 | E637: 10337044 | F637: UNITED TEXTILE MILLS PRIVATE LIMITE | G637: 6 | H637: 8909103992477 | I637: 441857089015 | J637: KRTS-APSU26-YETKRTSCUT5008, RUST, S | L637: EA | M637: 1 | N637: 566 | O637: 566 | Q637: 0 | R637: 0 | S637: 0 | T637: 0 | U637: 0 | X637: =IF(ISNUMBER(VALUE(LEFT(J637,1))),LEFT(J637,MIN(IFERROR(FIND("A",UPPER(J637)),LEN(J637)+1),IFERROR(FIND("B",UPPER(J637)),LEN(J637)+1),IFERROR(FIND("C",UPPER(J637)),LEN(J637)+1),IFERROR(FIND("D",UPPER(J637)),LEN(J637)+1),IFERROR(FIND("E",UPPER(J637)),LEN(J637)+1),IFERROR(FIND("F",UPPER(J637)),LEN(J637)+1),IFERROR(FIND("G",UPPER(J637)),LEN(J637)+1),IFERROR(FIND("H",UPPER(J637)),LEN(J637)+1),IFERROR(FIND("I",UPPER(J637)),LEN(J637)+1),IFERROR(FIND("J",UPPER(J637)),LEN(J637)+1),IFERROR(FIND("K",UPPER(J637)),LEN(J637)+1),IFERROR(FIND("L",UPPER(J637)),LEN(J637)+1),IFERROR(FIND("M",UPPER(J637)),LEN(J637)+1),IFERROR(FIND("N",UPPER(J637)),LEN(J637)+1),IFERROR(FIND("O",UPPER(J637)),LEN(J637)+1),IFERROR(FIND("P",UPPER(J637)),LEN(J637)+1),IFERROR(FIND("Q",UPPER(J637)),LEN(J637)+1),IFERROR(FIND("R",UPPER(J637)),LEN(J637)+1),IFERROR(FIND("S",UPPER(J637)),LEN(J637)+1),IFERROR(FIND("T",UPPER(J637)),LEN(J637)+1),IFERROR(FIND("U",UPPER(J637)),LEN(J637)+1),IFERROR(FIND("V",UPPER(J637)),LEN(J637)+1),IFERROR(FIND("W",UPPER(J637)),LEN(J637)+1),IFERROR(FIND("X",UPPER(J637)),LEN(J637)+1),IFERROR(FIND("Y",UPPER(J637)),LEN(J637)+1),IFERROR(FIND("Z",UPPER(J637)),LEN(J637)+1))-1),LEFT(TEXT(I637,"0"),LEN(TEXT(I637,"0"))-3)) -> 441857089 | Y637: =IF(ISNUMBER(SEARCH("(RP)",J637)),"RP","DC") -> DC | Z637: =IF(ISNUMBER(SEARCH("(RP)",J637)),O637,IF(RIGHT(TRIM(J637),3)=", S",O637,0)) -> 566 | AA637: =IF(ISNUMBER(SEARCH("(RP)",J637)),O637,IF(RIGHT(TRIM(J637),3)=", M",O637,0)) -> 0 | AB637: =IF(ISNUMBER(SEARCH("(RP)",J637)),O637,IF(RIGHT(TRIM(J637),3)=", L",O637,0)) -> 0 | AC637: =IF(ISNUMBER(SEARCH("(RP)",J637)),O637,IF(RIGHT(TRIM(J637),4)=", XL",O637,0)) -> 0 | AD637: =IF(ISNUMBER(SEARCH("(RP)",J637)),O637,IF(OR(RIGHT(TRIM(J637),5)=", XXL",RIGHT(TRIM(J637),5)=", 2XL"),O637,0)) -> 0 | AE637: {=IFERROR(_xlfn.XLOOKUP(H637,Sheet1!$G:$G,Sheet1!$F:$F),IFERROR(_xlfn.XLOOKUP(1,(--($X$2:$X$1074=X637))*(--ISNUMBER(MATCH($H$2:$H$1074,Sheet1!$G:$G,0))),_xlfn.XLOOKUP($H$2:$H$1074,Sheet1!$G:$G,Sheet1!$F:$F,"")),"NOT FOUND"))} -> YETKRTSCUT5008 | AF637: =IFERROR(IF(ISNUMBER(SEARCH("(RP)",J637)),TRIM(SUBSTITUTE(MID(J637,10,LEN(J637)),"(RP)","")),TRIM(MID(J637,FIND(",",J637)+1,FIND(",",J637,FIND(",",J637)+1)-FIND(",",J637)-1))),"") -> RUST | AG637: =IF(A637="SZAF","Bangalore",IF(A637="SAEX","JHAJJAR",IF(A637="S0EU","HARIPAL",""))) -> Bangalore | AH637: =IF(OR(J637="",AE637="",AE637="NOT FOUND"),"",IF(Y637="RP",IFERROR(LEFT(_xlfn.XLOOKUP(AE637,Sheet1!$F:$F,Sheet1!$W:$W),FIND("-",_xlfn.XLOOKUP(AE637,Sheet1!$F:$F,Sheet1!$W:$W),FIND("-",_xlfn.XLOOKUP(AE637,Sheet1!$F:$F,Sheet1!$W:$W))+1))&AE637,"NOT FOUND"),LEFT(J637,FIND("-",J637,FIND("-",J637)+1))&AE637)) -> KRTS-APSU26-YETKRTSCUT5008
A638: SZAF | B638: 5112963768 | C638: 30.01.2026 | D638: 30.06.2026 | E638: 10337044 | F638: UNITED TEXTILE MILLS PRIVATE LIMITE | G638: 1 | H638: 8909103992590 | I638: 494758188 | J638: 441857089 OFF WHITE(RP) | L638: EA | M638: 1 | N638: 566 | O638: 566 | Q638: 1221.5 | R638: 1221.5 | S638: 34568.45 | T638: 691369 | U638: 5 | V638: INR | X638: =IF(ISNUMBER(VALUE(LEFT(J638,1))),LEFT(J638,MIN(IFERROR(FIND("A",UPPER(J638)),LEN(J638)+1),IFERROR(FIND("B",UPPER(J638)),LEN(J638)+1),IFERROR(FIND("C",UPPER(J638)),LEN(J638)+1),IFERROR(FIND("D",UPPER(J638)),LEN(J638)+1),IFERROR(FIND("E",UPPER(J638)),LEN(J638)+1),IFERROR(FIND("F",UPPER(J638)),LEN(J638)+1),IFERROR(FIND("G",UPPER(J638)),LEN(J638)+1),IFERROR(FIND("H",UPPER(J638)),LEN(J638)+1),IFERROR(FIND("I",UPPER(J638)),LEN(J638)+1),IFERROR(FIND("J",UPPER(J638)),LEN(J638)+1),IFERROR(FIND("K",UPPER(J638)),LEN(J638)+1),IFERROR(FIND("L",UPPER(J638)),LEN(J638)+1),IFERROR(FIND("M",UPPER(J638)),LEN(J638)+1),IFERROR(FIND("N",UPPER(J638)),LEN(J638)+1),IFERROR(FIND("O",UPPER(J638)),LEN(J638)+1),IFERROR(FIND("P",UPPER(J638)),LEN(J638)+1),IFERROR(FIND("Q",UPPER(J638)),LEN(J638)+1),IFERROR(FIND("R",UPPER(J638)),LEN(J638)+1),IFERROR(FIND("S",UPPER(J638)),LEN(J638)+1),IFERROR(FIND("T",UPPER(J638)),LEN(J638)+1),IFERROR(FIND("U",UPPER(J638)),LEN(J638)+1),IFERROR(FIND("V",UPPER(J638)),LEN(J638)+1),IFERROR(FIND("W",UPPER(J638)),LEN(J638)+1),IFERROR(FIND("X",UPPER(J638)),LEN(J638)+1),IFERROR(FIND("Y",UPPER(J638)),LEN(J638)+1),IFERROR(FIND("Z",UPPER(J638)),LEN(J638)+1))-1),LEFT(TEXT(I638,"0"),LEN(TEXT(I638,"0"))-3)) -> 441857089 | Y638: =IF(ISNUMBER(SEARCH("(RP)",J638)),"RP","DC") -> RP | Z638: =IF(ISNUMBER(SEARCH("(RP)",J638)),O638,IF(RIGHT(TRIM(J638),3)=", S",O638,0)) -> 566 | AA638: =IF(ISNUMBER(SEARCH("(RP)",J638)),O638,IF(RIGHT(TRIM(J638),3)=", M",O638,0)) -> 566 | AB638: =IF(ISNUMBER(SEARCH("(RP)",J638)),O638,IF(RIGHT(TRIM(J638),3)=", L",O638,0)) -> 566 | AC638: =IF(ISNUMBER(SEARCH("(RP)",J638)),O638,IF(RIGHT(TRIM(J638),4)=", XL",O638,0)) -> 566 | AD638: =IF(ISNUMBER(SEARCH("(RP)",J638)),O638,IF(OR(RIGHT(TRIM(J638),5)=", XXL",RIGHT(TRIM(J638),5)=", 2XL"),O638,0)) -> 566 | AE638: {=IFERROR(_xlfn.XLOOKUP(H638,Sheet1!$G:$G,Sheet1!$F:$F),IFERROR(_xlfn.XLOOKUP(1,(--($X$2:$X$1074=X638))*(--ISNUMBER(MATCH($H$2:$H$1074,Sheet1!$G:$G,0))),_xlfn.XLOOKUP($H$2:$H$1074,Sheet1!$G:$G,Sheet1!$F:$F,"")),"NOT FOUND"))} -> YETKRTSCUT5008 | AF638: =IFERROR(IF(ISNUMBER(SEARCH("(RP)",J638)),TRIM(SUBSTITUTE(MID(J638,10,LEN(J638)),"(RP)","")),TRIM(MID(J638,FIND(",",J638)+1,FIND(",",J638,FIND(",",J638)+1)-FIND(",",J638)-1))),"") -> OFF WHITE | AG638: =IF(A638="SZAF","Bangalore",IF(A638="SAEX","JHAJJAR",IF(A638="S0EU","HARIPAL",""))) -> Bangalore | AH638: =IF(OR(J638="",AE638="",AE638="NOT FOUND"),"",IF(Y638="RP",IFERROR(LEFT(_xlfn.XLOOKUP(AE638,Sheet1!$F:$F,Sheet1!$W:$W),FIND("-",_xlfn.XLOOKUP(AE638,Sheet1!$F:$F,Sheet1!$W:$W),FIND("-",_xlfn.XLOOKUP(AE638,Sheet1!$F:$F,Sheet1!$W:$W))+1))&AE638,"NOT FOUND"),LEFT(J638,FIND("-",J638,FIND("-",J638)+1))&AE638)) -> KRTS-APSU26-YETKRTSCUT5008
A639: SZAF | B639: 5112963768 | C639: 30.01.2026 | D639: 30.06.2026 | E639: 10337044 | F639: UNITED TEXTILE MILLS PRIVATE LIMITE | G639: 2 | H639: 8909103992460 | I639: 441857089016 | J639: KRTS-APSU26-YETKRTSCUT50, OFF WHITE, 2XL | L639: EA | M639: 1 | N639: 566 | O639: 566 | Q639: 0 | R639: 0 | S639: 0 | T639: 0 | U639: 0 | V639: INR | X639: =IF(ISNUMBER(VALUE(LEFT(J639,1))),LEFT(J639,MIN(IFERROR(FIND("A",UPPER(J639)),LEN(J639)+1),IFERROR(FIND("B",UPPER(J639)),LEN(J639)+1),IFERROR(FIND("C",UPPER(J639)),LEN(J639)+1),IFERROR(FIND("D",UPPER(J639)),LEN(J639)+1),IFERROR(FIND("E",UPPER(J639)),LEN(J639)+1),IFERROR(FIND("F",UPPER(J639)),LEN(J639)+1),IFERROR(FIND("G",UPPER(J639)),LEN(J639)+1),IFERROR(FIND("H",UPPER(J639)),LEN(J639)+1),IFERROR(FIND("I",UPPER(J639)),LEN(J639)+1),IFERROR(FIND("J",UPPER(J639)),LEN(J639)+1),IFERROR(FIND("K",UPPER(J639)),LEN(J639)+1),IFERROR(FIND("L",UPPER(J639)),LEN(J639)+1),IFERROR(FIND("M",UPPER(J639)),LEN(J639)+1),IFERROR(FIND("N",UPPER(J639)),LEN(J639)+1),IFERROR(FIND("O",UPPER(J639)),LEN(J639)+1),IFERROR(FIND("P",UPPER(J639)),LEN(J639)+1),IFERROR(FIND("Q",UPPER(J639)),LEN(J639)+1),IFERROR(FIND("R",UPPER(J639)),LEN(J639)+1),IFERROR(FIND("S",UPPER(J639)),LEN(J639)+1),IFERROR(FIND("T",UPPER(J639)),LEN(J639)+1),IFERROR(FIND("U",UPPER(J639)),LEN(J639)+1),IFERROR(FIND("V",UPPER(J639)),LEN(J639)+1),IFERROR(FIND("W",UPPER(J639)),LEN(J639)+1),IFERROR(FIND("X",UPPER(J639)),LEN(J639)+1),IFERROR(FIND("Y",UPPER(J639)),LEN(J639)+1),IFERROR(FIND("Z",UPPER(J639)),LEN(J639)+1))-1),LEFT(TEXT(I639,"0"),LEN(TEXT(I639,"0"))-3)) -> 441857089 | Y639: =IF(ISNUMBER(SEARCH("(RP)",J639)),"RP","DC") -> DC | Z639: =IF(ISNUMBER(SEARCH("(RP)",J639)),O639,IF(RIGHT(TRIM(J639),3)=", S",O639,0)) -> 0 | AA639: =IF(ISNUMBER(SEARCH("(RP)",J639)),O639,IF(RIGHT(TRIM(J639),3)=", M",O639,0)) -> 0 | AB639: =IF(ISNUMBER(SEARCH("(RP)",J639)),O639,IF(RIGHT(TRIM(J639),3)=", L",O639,0)) -> 0 | AC639: =IF(ISNUMBER(SEARCH("(RP)",J639)),O639,IF(RIGHT(TRIM(J639),4)=", XL",O639,0)) -> 0 | AD639: =IF(ISNUMBER(SEARCH("(RP)",J639)),O639,IF(OR(RIGHT(TRIM(J639),5)=", XXL",RIGHT(TRIM(J639),5)=", 2XL"),O639,0)) -> 566 | AE639: {=IFERROR(_xlfn.XLOOKUP(H639,Sheet1!$G:$G,Sheet1!$F:$F),IFERROR(_xlfn.XLOOKUP(1,(--($X$2:$X$1074=X639))*(--ISNUMBER(MATCH($H$2:$H$1074,Sheet1!$G:$G,0))),_xlfn.XLOOKUP($H$2:$H$1074,Sheet1!$G:$G,Sheet1!$F:$F,"")),"NOT FOUND"))} -> YETKRTSCUT5008 | AF639: =IFERROR(IF(ISNUMBER(SEARCH("(RP)",J639)),TRIM(SUBSTITUTE(MID(J639,10,LEN(J639)),"(RP)","")),TRIM(MID(J639,FIND(",",J639)+1,FIND(",",J639,FIND(",",J639)+1)-FIND(",",J639)-1))),"") -> OFF WHITE | AG639: =IF(A639="SZAF","Bangalore",IF(A639="SAEX","JHAJJAR",IF(A639="S0EU","HARIPAL",""))) -> Bangalore | AH639: =IF(OR(J639="",AE639="",AE639="NOT FOUND"),"",IF(Y639="RP",IFERROR(LEFT(_xlfn.XLOOKUP(AE639,Sheet1!$F:$F,Sheet1!$W:$W),FIND("-",_xlfn.XLOOKUP(AE639,Sheet1!$F:$F,Sheet1!$W:$W),FIND("-",_xlfn.XLOOKUP(AE639,Sheet1!$F:$F,Sheet1!$W:$W))+1))&AE639,"NOT FOUND"),LEFT(J639,FIND("-",J639,FIND("-",J639)+1))&AE639)) -> KRTS-APSU26-YETKRTSCUT5008
A640: SZAF | B640: 5112963768 | C640: 30.01.2026 | D640: 30.06.2026 | E640: 10337044 | F640: UNITED TEXTILE MILLS PRIVATE LIMITE | G640: 3 | H640: 8909103992453 | I640: 441857089017 | J640: KRTS-APSU26-YETKRTSCUT500, OFF WHITE, XL | L640: EA | M640: 1 | N640: 566 | O640: 566 | Q640: 0 | R640: 0 | S640: 0 | T640: 0 | U640: 0 | V640: INR | X640: =IF(ISNUMBER(VALUE(LEFT(J640,1))),LEFT(J640,MIN(IFERROR(FIND("A",UPPER(J640)),LEN(J640)+1),IFERROR(FIND("B",UPPER(J640)),LEN(J640)+1),IFERROR(FIND("C",UPPER(J640)),LEN(J640)+1),IFERROR(FIND("D",UPPER(J640)),LEN(J640)+1),IFERROR(FIND("E",UPPER(J640)),LEN(J640)+1),IFERROR(FIND("F",UPPER(J640)),LEN(J640)+1),IFERROR(FIND("G",UPPER(J640)),LEN(J640)+1),IFERROR(FIND("H",UPPER(J640)),LEN(J640)+1),IFERROR(FIND("I",UPPER(J640)),LEN(J640)+1),IFERROR(FIND("J",UPPER(J640)),LEN(J640)+1),IFERROR(FIND("K",UPPER(J640)),LEN(J640)+1),IFERROR(FIND("L",UPPER(J640)),LEN(J640)+1),IFERROR(FIND("M",UPPER(J640)),LEN(J640)+1),IFERROR(FIND("N",UPPER(J640)),LEN(J640)+1),IFERROR(FIND("O",UPPER(J640)),LEN(J640)+1),IFERROR(FIND("P",UPPER(J640)),LEN(J640)+1),IFERROR(FIND("Q",UPPER(J640)),LEN(J640)+1),IFERROR(FIND("R",UPPER(J640)),LEN(J640)+1),IFERROR(FIND("S",UPPER(J640)),LEN(J640)+1),IFERROR(FIND("T",UPPER(J640)),LEN(J640)+1),IFERROR(FIND("U",UPPER(J640)),LEN(J640)+1),IFERROR(FIND("V",UPPER(J640)),LEN(J640)+1),IFERROR(FIND("W",UPPER(J640)),LEN(J640)+1),IFERROR(FIND("X",UPPER(J640)),LEN(J640)+1),IFERROR(FIND("Y",UPPER(J640)),LEN(J640)+1),IFERROR(FIND("Z",UPPER(J640)),LEN(J640)+1))-1),LEFT(TEXT(I640,"0"),LEN(TEXT(I640,"0"))-3)) -> 441857089 | Y640: =IF(ISNUMBER(SEARCH("(RP)",J640)),"RP","DC") -> DC | Z640: =IF(ISNUMBER(SEARCH("(RP)",J640)),O640,IF(RIGHT(TRIM(J640),3)=", S",O640,0)) -> 0 | AA640: =IF(ISNUMBER(SEARCH("(RP)",J640)),O640,IF(RIGHT(TRIM(J640),3)=", M",O640,0)) -> 0 | AB640: =IF(ISNUMBER(SEARCH("(RP)",J640)),O640,IF(RIGHT(TRIM(J640),3)=", L",O640,0)) -> 0 | AC640: =IF(ISNUMBER(SEARCH("(RP)",J640)),O640,IF(RIGHT(TRIM(J640),4)=", XL",O640,0)) -> 566 | AD640: =IF(ISNUMBER(SEARCH("(RP)",J640)),O640,IF(OR(RIGHT(TRIM(J640),5)=", XXL",RIGHT(TRIM(J640),5)=", 2XL"),O640,0)) -> 0 | AE640: {=IFERROR(_xlfn.XLOOKUP(H640,Sheet1!$G:$G,Sheet1!$F:$F),IFERROR(_xlfn.XLOOKUP(1,(--($X$2:$X$1074=X640))*(--ISNUMBER(MATCH($H$2:$H$1074,Sheet1!$G:$G,0))),_xlfn.XLOOKUP($H$2:$H$1074,Sheet1!$G:$G,Sheet1!$F:$F,"")),"NOT FOUND"))} -> YETKRTSCUT5008 | AF640: =IFERROR(IF(ISNUMBER(SEARCH("(RP)",J640)),TRIM(SUBSTITUTE(MID(J640,10,LEN(J640)),"(RP)","")),TRIM(MID(J640,FIND(",",J640)+1,FIND(",",J640,FIND(",",J640)+1)-FIND(",",J640)-1))),"") -> OFF WHITE | AG640: =IF(A640="SZAF","Bangalore",IF(A640="SAEX","JHAJJAR",IF(A640="S0EU","HARIPAL",""))) -> Bangalore | AH640: =IF(OR(J640="",AE640="",AE640="NOT FOUND"),"",IF(Y640="RP",IFERROR(LEFT(_xlfn.XLOOKUP(AE640,Sheet1!$F:$F,Sheet1!$W:$W),FIND("-",_xlfn.XLOOKUP(AE640,Sheet1!$F:$F,Sheet1!$W:$W),FIND("-",_xlfn.XLOOKUP(AE640,Sheet1!$F:$F,Sheet1!$W:$W))+1))&AE640,"NOT FOUND"),LEFT(J640,FIND("-",J640,FIND("-",J640)+1))&AE640)) -> KRTS-APSU26-YETKRTSCUT5008
A641: SZAF | B641: 5112963768 | C641: 30.01.2026 | D641: 30.06.2026 | E641: 10337044 | F641: UNITED TEXTILE MILLS PRIVATE LIMITE | G641: 4 | H641: 8909103992446 | I641: 441857089018 | J641: KRTS-APSU26-YETKRTSCUT5008, OFF WHITE, L | L641: EA | M641: 1 | N641: 566 | O641: 566 | Q641: 0 | R641: 0 | S641: 0 | T641: 0 | U641: 0 | V641: INR | X641: =IF(ISNUMBER(VALUE(LEFT(J641,1))),LEFT(J641,MIN(IFERROR(FIND("A",UPPER(J641)),LEN(J641)+1),IFERROR(FIND("B",UPPER(J641)),LEN(J641)+1),IFERROR(FIND("C",UPPER(J641)),LEN(J641)+1),IFERROR(FIND("D",UPPER(J641)),LEN(J641)+1),IFERROR(FIND("E",UPPER(J641)),LEN(J641)+1),IFERROR(FIND("F",UPPER(J641)),LEN(J641)+1),IFERROR(FIND("G",UPPER(J641)),LEN(J641)+1),IFERROR(FIND("H",UPPER(J641)),LEN(J641)+1),IFERROR(FIND("I",UPPER(J641)),LEN(J641)+1),IFERROR(FIND("J",UPPER(J641)),LEN(J641)+1),IFERROR(FIND("K",UPPER(J641)),LEN(J641)+1),IFERROR(FIND("L",UPPER(J641)),LEN(J641)+1),IFERROR(FIND("M",UPPER(J641)),LEN(J641)+1),IFERROR(FIND("N",UPPER(J641)),LEN(J641)+1),IFERROR(FIND("O",UPPER(J641)),LEN(J641)+1),IFERROR(FIND("P",UPPER(J641)),LEN(J641)+1),IFERROR(FIND("Q",UPPER(J641)),LEN(J641)+1),IFERROR(FIND("R",UPPER(J641)),LEN(J641)+1),IFERROR(FIND("S",UPPER(J641)),LEN(J641)+1),IFERROR(FIND("T",UPPER(J641)),LEN(J641)+1),IFERROR(FIND("U",UPPER(J641)),LEN(J641)+1),IFERROR(FIND("V",UPPER(J641)),LEN(J641)+1),IFERROR(FIND("W",UPPER(J641)),LEN(J641)+1),IFERROR(FIND("X",UPPER(J641)),LEN(J641)+1),IFERROR(FIND("Y",UPPER(J641)),LEN(J641)+1),IFERROR(FIND("Z",UPPER(J641)),LEN(J641)+1))-1),LEFT(TEXT(I641,"0"),LEN(TEXT(I641,"0"))-3)) -> 441857089 | Y641: =IF(ISNUMBER(SEARCH("(RP)",J641)),"RP","DC") -> DC | Z641: =IF(ISNUMBER(SEARCH("(RP)",J641)),O641,IF(RIGHT(TRIM(J641),3)=", S",O641,0)) -> 0 | AA641: =IF(ISNUMBER(SEARCH("(RP)",J641)),O641,IF(RIGHT(TRIM(J641),3)=", M",O641,0)) -> 0 | AB641: =IF(ISNUMBER(SEARCH("(RP)",J641)),O641,IF(RIGHT(TRIM(J641),3)=", L",O641,0)) -> 566 | AC641: =IF(ISNUMBER(SEARCH("(RP)",J641)),O641,IF(RIGHT(TRIM(J641),4)=", XL",O641,0)) -> 0 | AD641: =IF(ISNUMBER(SEARCH("(RP)",J641)),O641,IF(OR(RIGHT(TRIM(J641),5)=", XXL",RIGHT(TRIM(J641),5)=", 2XL"),O641,0)) -> 0 | AE641: {=IFERROR(_xlfn.XLOOKUP(H641,Sheet1!$G:$G,Sheet1!$F:$F),IFERROR(_xlfn.XLOOKUP(1,(--($X$2:$X$1074=X641))*(--ISNUMBER(MATCH($H$2:$H$1074,Sheet1!$G:$G,0))),_xlfn.XLOOKUP($H$2:$H$1074,Sheet1!$G:$G,Sheet1!$F:$F,"")),"NOT FOUND"))} -> YETKRTSCUT5008 | AF641: =IFERROR(IF(ISNUMBER(SEARCH("(RP)",J641)),TRIM(SUBSTITUTE(MID(J641,10,LEN(J641)),"(RP)","")),TRIM(MID(J641,FIND(",",J641)+1,FIND(",",J641,FIND(",",J641)+1)-FIND(",",J641)-1))),"") -> OFF WHITE | AG641: =IF(A641="SZAF","Bangalore",IF(A641="SAEX","JHAJJAR",IF(A641="S0EU","HARIPAL",""))) -> Bangalore | AH641: =IF(OR(J641="",AE641="",AE641="NOT FOUND"),"",IF(Y641="RP",IFERROR(LEFT(_xlfn.XLOOKUP(AE641,Sheet1!$F:$F,Sheet1!$W:$W),FIND("-",_xlfn.XLOOKUP(AE641,Sheet1!$F:$F,Sheet1!$W:$W),FIND("-",_xlfn.XLOOKUP(AE641,Sheet1!$F:$F,Sheet1!$W:$W))+1))&AE641,"NOT FOUND"),LEFT(J641,FIND("-",J641,FIND("-",J641)+1))&AE641)) -> KRTS-APSU26-YETKRTSCUT5008
A642: SZAF | B642: 5112963768 | C642: 30.01.2026 | D642: 30.06.2026 | E642: 10337044 | F642: UNITED TEXTILE MILLS PRIVATE LIMITE | G642: 5 | H642: 8909103992439 | I642: 441857089019 | J642: KRTS-APSU26-YETKRTSCUT5008, OFF WHITE, M | L642: EA | M642: 1 | N642: 566 | O642: 566 | Q642: 0 | R642: 0 | S642: 0 | T642: 0 | U642: 0 | V642: INR | X642: =IF(ISNUMBER(VALUE(LEFT(J642,1))),LEFT(J642,MIN(IFERROR(FIND("A",UPPER(J642)),LEN(J642)+1),IFERROR(FIND("B",UPPER(J642)),LEN(J642)+1),IFERROR(FIND("C",UPPER(J642)),LEN(J642)+1),IFERROR(FIND("D",UPPER(J642)),LEN(J642)+1),IFERROR(FIND("E",UPPER(J642)),LEN(J642)+1),IFERROR(FIND("F",UPPER(J642)),LEN(J642)+1),IFERROR(FIND("G",UPPER(J642)),LEN(J642)+1),IFERROR(FIND("H",UPPER(J642)),LEN(J642)+1),IFERROR(FIND("I",UPPER(J642)),LEN(J642)+1),IFERROR(FIND("J",UPPER(J642)),LEN(J642)+1),IFERROR(FIND("K",UPPER(J642)),LEN(J642)+1),IFERROR(FIND("L",UPPER(J642)),LEN(J642)+1),IFERROR(FIND("M",UPPER(J642)),LEN(J642)+1),IFERROR(FIND("N",UPPER(J642)),LEN(J642)+1),IFERROR(FIND("O",UPPER(J642)),LEN(J642)+1),IFERROR(FIND("P",UPPER(J642)),LEN(J642)+1),IFERROR(FIND("Q",UPPER(J642)),LEN(J642)+1),IFERROR(FIND("R",UPPER(J642)),LEN(J642)+1),IFERROR(FIND("S",UPPER(J642)),LEN(J642)+1),IFERROR(FIND("T",UPPER(J642)),LEN(J642)+1),IFERROR(FIND("U",UPPER(J642)),LEN(J642)+1),IFERROR(FIND("V",UPPER(J642)),LEN(J642)+1),IFERROR(FIND("W",UPPER(J642)),LEN(J642)+1),IFERROR(FIND("X",UPPER(J642)),LEN(J642)+1),IFERROR(FIND("Y",UPPER(J642)),LEN(J642)+1),IFERROR(FIND("Z",UPPER(J642)),LEN(J642)+1))-1),LEFT(TEXT(I642,"0"),LEN(TEXT(I642,"0"))-3)) -> 441857089 | Y642: =IF(ISNUMBER(SEARCH("(RP)",J642)),"RP","DC") -> DC | Z642: =IF(ISNUMBER(SEARCH("(RP)",J642)),O642,IF(RIGHT(TRIM(J642),3)=", S",O642,0)) -> 0 | AA642: =IF(ISNUMBER(SEARCH("(RP)",J642)),O642,IF(RIGHT(TRIM(J642),3)=", M",O642,0)) -> 566 | AB642: =IF(ISNUMBER(SEARCH("(RP)",J642)),O642,IF(RIGHT(TRIM(J642),3)=", L",O642,0)) -> 0 | AC642: =IF(ISNUMBER(SEARCH("(RP)",J642)),O642,IF(RIGHT(TRIM(J642),4)=", XL",O642,0)) -> 0 | AD642: =IF(ISNUMBER(SEARCH("(RP)",J642)),O642,IF(OR(RIGHT(TRIM(J642),5)=", XXL",RIGHT(TRIM(J642),5)=", 2XL"),O642,0)) -> 0 | AE642: {=IFERROR(_xlfn.XLOOKUP(H642,Sheet1!$G:$G,Sheet1!$F:$F),IFERROR(_xlfn.XLOOKUP(1,(--($X$2:$X$1074=X642))*(--ISNUMBER(MATCH($H$2:$H$1074,Sheet1!$G:$G,0))),_xlfn.XLOOKUP($H$2:$H$1074,Sheet1!$G:$G,Sheet1!$F:$F,"")),"NOT FOUND"))} -> YETKRTSCUT5008 | AF642: =IFERROR(IF(ISNUMBER(SEARCH("(RP)",J642)),TRIM(SUBSTITUTE(MID(J642,10,LEN(J642)),"(RP)","")),TRIM(MID(J642,FIND(",",J642)+1,FIND(",",J642,FIND(",",J642)+1)-FIND(",",J642)-1))),"") -> OFF WHITE | AG642: =IF(A642="SZAF","Bangalore",IF(A642="SAEX","JHAJJAR",IF(A642="S0EU","HARIPAL",""))) -> Bangalore | AH642: =IF(OR(J642="",AE642="",AE642="NOT FOUND"),"",IF(Y642="RP",IFERROR(LEFT(_xlfn.XLOOKUP(AE642,Sheet1!$F:$F,Sheet1!$W:$W),FIND("-",_xlfn.XLOOKUP(AE642,Sheet1!$F:$F,Sheet1!$W:$W),FIND("-",_xlfn.XLOOKUP(AE642,Sheet1!$F:$F,Sheet1!$W:$W))+1))&AE642,"NOT FOUND"),LEFT(J642,FIND("-",J642,FIND("-",J642)+1))&AE642)) -> KRTS-APSU26-YETKRTSCUT5008
A643: SZAF | B643: 5112963768 | C643: 30.01.2026 | D643: 30.06.2026 | E643: 10337044 | F643: UNITED TEXTILE MILLS PRIVATE LIMITE | G643: 6 | H643: 8909103992422 | I643: 441857089020 | J643: KRTS-APSU26-YETKRTSCUT5008, OFF WHITE, S | L643: EA | M643: 1 | N643: 566 | O643: 566 | Q643: 0 | R643: 0 | S643: 0 | T643: 0 | U643: 0 | X643: =IF(ISNUMBER(VALUE(LEFT(J643,1))),LEFT(J643,MIN(IFERROR(FIND("A",UPPER(J643)),LEN(J643)+1),IFERROR(FIND("B",UPPER(J643)),LEN(J643)+1),IFERROR(FIND("C",UPPER(J643)),LEN(J643)+1),IFERROR(FIND("D",UPPER(J643)),LEN(J643)+1),IFERROR(FIND("E",UPPER(J643)),LEN(J643)+1),IFERROR(FIND("F",UPPER(J643)),LEN(J643)+1),IFERROR(FIND("G",UPPER(J643)),LEN(J643)+1),IFERROR(FIND("H",UPPER(J643)),LEN(J643)+1),IFERROR(FIND("I",UPPER(J643)),LEN(J643)+1),IFERROR(FIND("J",UPPER(J643)),LEN(J643)+1),IFERROR(FIND("K",UPPER(J643)),LEN(J643)+1),IFERROR(FIND("L",UPPER(J643)),LEN(J643)+1),IFERROR(FIND("M",UPPER(J643)),LEN(J643)+1),IFERROR(FIND("N",UPPER(J643)),LEN(J643)+1),IFERROR(FIND("O",UPPER(J643)),LEN(J643)+1),IFERROR(FIND("P",UPPER(J643)),LEN(J643)+1),IFERROR(FIND("Q",UPPER(J643)),LEN(J643)+1),IFERROR(FIND("R",UPPER(J643)),LEN(J643)+1),IFERROR(FIND("S",UPPER(J643)),LEN(J643)+1),IFERROR(FIND("T",UPPER(J643)),LEN(J643)+1),IFERROR(FIND("U",UPPER(J643)),LEN(J643)+1),IFERROR(FIND("V",UPPER(J643)),LEN(J643)+1),IFERROR(FIND("W",UPPER(J643)),LEN(J643)+1),IFERROR(FIND("X",UPPER(J643)),LEN(J643)+1),IFERROR(FIND("Y",UPPER(J643)),LEN(J643)+1),IFERROR(FIND("Z",UPPER(J643)),LEN(J643)+1))-1),LEFT(TEXT(I643,"0"),LEN(TEXT(I643,"0"))-3)) -> 441857089 | Y643: =IF(ISNUMBER(SEARCH("(RP)",J643)),"RP","DC") -> DC | Z643: =IF(ISNUMBER(SEARCH("(RP)",J643)),O643,IF(RIGHT(TRIM(J643),3)=", S",O643,0)) -> 566 | AA643: =IF(ISNUMBER(SEARCH("(RP)",J643)),O643,IF(RIGHT(TRIM(J643),3)=", M",O643,0)) -> 0 | AB643: =IF(ISNUMBER(SEARCH("(RP)",J643)),O643,IF(RIGHT(TRIM(J643),3)=", L",O643,0)) -> 0 | AC643: =IF(ISNUMBER(SEARCH("(RP)",J643)),O643,IF(RIGHT(TRIM(J643),4)=", XL",O643,0)) -> 0 | AD643: =IF(ISNUMBER(SEARCH("(RP)",J643)),O643,IF(OR(RIGHT(TRIM(J643),5)=", XXL",RIGHT(TRIM(J643),5)=", 2XL"),O643,0)) -> 0 | AE643: {=IFERROR(_xlfn.XLOOKUP(H643,Sheet1!$G:$G,Sheet1!$F:$F),IFERROR(_xlfn.XLOOKUP(1,(--($X$2:$X$1074=X643))*(--ISNUMBER(MATCH($H$2:$H$1074,Sheet1!$G:$G,0))),_xlfn.XLOOKUP($H$2:$H$1074,Sheet1!$G:$G,Sheet1!$F:$F,"")),"NOT FOUND"))} -> YETKRTSCUT5008 | AF643: =IFERROR(IF(ISNUMBER(SEARCH("(RP)",J643)),TRIM(SUBSTITUTE(MID(J643,10,LEN(J643)),"(RP)","")),TRIM(MID(J643,FIND(",",J643)+1,FIND(",",J643,FIND(",",J643)+1)-FIND(",",J643)-1))),"") -> OFF WHITE | AG643: =IF(A643="SZAF","Bangalore",IF(A643="SAEX","JHAJJAR",IF(A643="S0EU","HARIPAL",""))) -> Bangalore | AH643: =IF(OR(J643="",AE643="",AE643="NOT FOUND"),"",IF(Y643="RP",IFERROR(LEFT(_xlfn.XLOOKUP(AE643,Sheet1!$F:$F,Sheet1!$W:$W),FIND("-",_xlfn.XLOOKUP(AE643,Sheet1!$F:$F,Sheet1!$W:$W),FIND("-",_xlfn.XLOOKUP(AE643,Sheet1!$F:$F,Sheet1!$W:$W))+1))&AE643,"NOT FOUND"),LEFT(J643,FIND("-",J643,FIND("-",J643)+1))&AE643)) -> KRTS-APSU26-YETKRTSCUT5008
A644: SZAF | B644: 5112963767 | C644: 30.01.2026 | D644: 20.05.2026 | E644: 10337044 | F644: UNITED TEXTILE MILLS PRIVATE LIMITE | G644: 1 | H644: 8909103992583 | I644: 494758187 | J644: 441857089 MUSTARD(RP) | L644: EA | M644: 1 | N644: 531 | O644: 531 | Q644: 1221.5 | R644: 1221.5 | S644: 32430.83 | T644: 648616.5 | U644: 5 | V644: INR | X644: =IF(ISNUMBER(VALUE(LEFT(J644,1))),LEFT(J644,MIN(IFERROR(FIND("A",UPPER(J644)),LEN(J644)+1),IFERROR(FIND("B",UPPER(J644)),LEN(J644)+1),IFERROR(FIND("C",UPPER(J644)),LEN(J644)+1),IFERROR(FIND("D",UPPER(J644)),LEN(J644)+1),IFERROR(FIND("E",UPPER(J644)),LEN(J644)+1),IFERROR(FIND("F",UPPER(J644)),LEN(J644)+1),IFERROR(FIND("G",UPPER(J644)),LEN(J644)+1),IFERROR(FIND("H",UPPER(J644)),LEN(J644)+1),IFERROR(FIND("I",UPPER(J644)),LEN(J644)+1),IFERROR(FIND("J",UPPER(J644)),LEN(J644)+1),IFERROR(FIND("K",UPPER(J644)),LEN(J644)+1),IFERROR(FIND("L",UPPER(J644)),LEN(J644)+1),IFERROR(FIND("M",UPPER(J644)),LEN(J644)+1),IFERROR(FIND("N",UPPER(J644)),LEN(J644)+1),IFERROR(FIND("O",UPPER(J644)),LEN(J644)+1),IFERROR(FIND("P",UPPER(J644)),LEN(J644)+1),IFERROR(FIND("Q",UPPER(J644)),LEN(J644)+1),IFERROR(FIND("R",UPPER(J644)),LEN(J644)+1),IFERROR(FIND("S",UPPER(J644)),LEN(J644)+1),IFERROR(FIND("T",UPPER(J644)),LEN(J644)+1),IFERROR(FIND("U",UPPER(J644)),LEN(J644)+1),IFERROR(FIND("V",UPPER(J644)),LEN(J644)+1),IFERROR(FIND("W",UPPER(J644)),LEN(J644)+1),IFERROR(FIND("X",UPPER(J644)),LEN(J644)+1),IFERROR(FIND("Y",UPPER(J644)),LEN(J644)+1),IFERROR(FIND("Z",UPPER(J644)),LEN(J644)+1))-1),LEFT(TEXT(I644,"0"),LEN(TEXT(I644,"0"))-3)) -> 441857089 | Y644: =IF(ISNUMBER(SEARCH("(RP)",J644)),"RP","DC") -> RP | Z644: =IF(ISNUMBER(SEARCH("(RP)",J644)),O644,IF(RIGHT(TRIM(J644),3)=", S",O644,0)) -> 531 | AA644: =IF(ISNUMBER(SEARCH("(RP)",J644)),O644,IF(RIGHT(TRIM(J644),3)=", M",O644,0)) -> 531 | AB644: =IF(ISNUMBER(SEARCH("(RP)",J644)),O644,IF(RIGHT(TRIM(J644),3)=", L",O644,0)) -> 531 | AC644: =IF(ISNUMBER(SEARCH("(RP)",J644)),O644,IF(RIGHT(TRIM(J644),4)=", XL",O644,0)) -> 531 | AD644: =IF(ISNUMBER(SEARCH("(RP)",J644)),O644,IF(OR(RIGHT(TRIM(J644),5)=", XXL",RIGHT(TRIM(J644),5)=", 2XL"),O644,0)) -> 531 | AE644: {=IFERROR(_xlfn.XLOOKUP(H644,Sheet1!$G:$G,Sheet1!$F:$F),IFERROR(_xlfn.XLOOKUP(1,(--($X$2:$X$1074=X644))*(--ISNUMBER(MATCH($H$2:$H$1074,Sheet1!$G:$G,0))),_xlfn.XLOOKUP($H$2:$H$1074,Sheet1!$G:$G,Sheet1!$F:$F,"")),"NOT FOUND"))} -> YETKRTSCUT5008 | AF644: =IFERROR(IF(ISNUMBER(SEARCH("(RP)",J644)),TRIM(SUBSTITUTE(MID(J644,10,LEN(J644)),"(RP)","")),TRIM(MID(J644,FIND(",",J644)+1,FIND(",",J644,FIND(",",J644)+1)-FIND(",",J644)-1))),"") -> MUSTARD | AG644: =IF(A644="SZAF","Bangalore",IF(A644="SAEX","JHAJJAR",IF(A644="S0EU","HARIPAL",""))) -> Bangalore | AH644: =IF(OR(J644="",AE644="",AE644="NOT FOUND"),"",IF(Y644="RP",IFERROR(LEFT(_xlfn.XLOOKUP(AE644,Sheet1!$F:$F,Sheet1!$W:$W),FIND("-",_xlfn.XLOOKUP(AE644,Sheet1!$F:$F,Sheet1!$W:$W),FIND("-",_xlfn.XLOOKUP(AE644,Sheet1!$F:$F,Sheet1!$W:$W))+1))&AE644,"NOT FOUND"),LEFT(J644,FIND("-",J644,FIND("-",J644)+1))&AE644)) -> KRTS-APSU26-YETKRTSCUT5008
A645: SZAF | B645: 5112963766 | C645: 30.01.2026 | D645: 20.05.2026 | E645: 10337044 | F645: UNITED TEXTILE MILLS PRIVATE LIMITE | G645: 1 | H645: 8909103992576 | I645: 494758186 | J645: 441857089 FUCHSIA(RP) | L645: EA | M645: 1 | N645: 495 | O645: 495 | Q645: 1221.5 | R645: 1221.5 | S645: 30232.13 | T645: 604642.5 | U645: 5 | V645: INR | X645: =IF(ISNUMBER(VALUE(LEFT(J645,1))),LEFT(J645,MIN(IFERROR(FIND("A",UPPER(J645)),LEN(J645)+1),IFERROR(FIND("B",UPPER(J645)),LEN(J645)+1),IFERROR(FIND("C",UPPER(J645)),LEN(J645)+1),IFERROR(FIND("D",UPPER(J645)),LEN(J645)+1),IFERROR(FIND("E",UPPER(J645)),LEN(J645)+1),IFERROR(FIND("F",UPPER(J645)),LEN(J645)+1),IFERROR(FIND("G",UPPER(J645)),LEN(J645)+1),IFERROR(FIND("H",UPPER(J645)),LEN(J645)+1),IFERROR(FIND("I",UPPER(J645)),LEN(J645)+1),IFERROR(FIND("J",UPPER(J645)),LEN(J645)+1),IFERROR(FIND("K",UPPER(J645)),LEN(J645)+1),IFERROR(FIND("L",UPPER(J645)),LEN(J645)+1),IFERROR(FIND("M",UPPER(J645)),LEN(J645)+1),IFERROR(FIND("N",UPPER(J645)),LEN(J645)+1),IFERROR(FIND("O",UPPER(J645)),LEN(J645)+1),IFERROR(FIND("P",UPPER(J645)),LEN(J645)+1),IFERROR(FIND("Q",UPPER(J645)),LEN(J645)+1),IFERROR(FIND("R",UPPER(J645)),LEN(J645)+1),IFERROR(FIND("S",UPPER(J645)),LEN(J645)+1),IFERROR(FIND("T",UPPER(J645)),LEN(J645)+1),IFERROR(FIND("U",UPPER(J645)),LEN(J645)+1),IFERROR(FIND("V",UPPER(J645)),LEN(J645)+1),IFERROR(FIND("W",UPPER(J645)),LEN(J645)+1),IFERROR(FIND("X",UPPER(J645)),LEN(J645)+1),IFERROR(FIND("Y",UPPER(J645)),LEN(J645)+1),IFERROR(FIND("Z",UPPER(J645)),LEN(J645)+1))-1),LEFT(TEXT(I645,"0"),LEN(TEXT(I645,"0"))-3)) -> 441857089 | Y645: =IF(ISNUMBER(SEARCH("(RP)",J645)),"RP","DC") -> RP | Z645: =IF(ISNUMBER(SEARCH("(RP)",J645)),O645,IF(RIGHT(TRIM(J645),3)=", S",O645,0)) -> 495 | AA645: =IF(ISNUMBER(SEARCH("(RP)",J645)),O645,IF(RIGHT(TRIM(J645),3)=", M",O645,0)) -> 495 | AB645: =IF(ISNUMBER(SEARCH("(RP)",J645)),O645,IF(RIGHT(TRIM(J645),3)=", L",O645,0)) -> 495 | AC645: =IF(ISNUMBER(SEARCH("(RP)",J645)),O645,IF(RIGHT(TRIM(J645),4)=", XL",O645,0)) -> 495 | AD645: =IF(ISNUMBER(SEARCH("(RP)",J645)),O645,IF(OR(RIGHT(TRIM(J645),5)=", XXL",RIGHT(TRIM(J645),5)=", 2XL"),O645,0)) -> 495 | AE645: {=IFERROR(_xlfn.XLOOKUP(H645,Sheet1!$G:$G,Sheet1!$F:$F),IFERROR(_xlfn.XLOOKUP(1,(--($X$2:$X$1074=X645))*(--ISNUMBER(MATCH($H$2:$H$1074,Sheet1!$G:$G,0))),_xlfn.XLOOKUP($H$2:$H$1074,Sheet1!$G:$G,Sheet1!$F:$F,"")),"NOT FOUND"))} -> YETKRTSCUT5008 | AF645: =IFERROR(IF(ISNUMBER(SEARCH("(RP)",J645)),TRIM(SUBSTITUTE(MID(J645,10,LEN(J645)),"(RP)","")),TRIM(MID(J645,FIND(",",J645)+1,FIND(",",J645,FIND(",",J645)+1)-FIND(",",J645)-1))),"") -> FUCHSIA | AG645: =IF(A645="SZAF","Bangalore",IF(A645="SAEX","JHAJJAR",IF(A645="S0EU","HARIPAL",""))) -> Bangalore | AH645: =IF(OR(J645="",AE645="",AE645="NOT FOUND"),"",IF(Y645="RP",IFERROR(LEFT(_xlfn.XLOOKUP(AE645,Sheet1!$F:$F,Sheet1!$W:$W),FIND("-",_xlfn.XLOOKUP(AE645,Sheet1!$F:$F,Sheet1!$W:$W),FIND("-",_xlfn.XLOOKUP(AE645,Sheet1!$F:$F,Sheet1!$W:$W))+1))&AE645,"NOT FOUND"),LEFT(J645,FIND("-",J645,FIND("-",J645)+1))&AE645)) -> KRTS-APSU26-YETKRTSCUT5008
A646: SAEX | B646: 5112963749 | C646: 30.01.2026 | D646: 20.05.2026 | E646: 10337044 | F646: UNITED TEXTILE MILLS PRIVATE LIMITE | G646: 1 | H646: 8909103992576 | I646: 494758186 | J646: 441857089 FUCHSIA(RP) | L646: EA | M646: 1 | N646: 249 | O646: 249 | Q646: 1221.5 | R646: 1221.5 | S646: 15207.68 | T646: 304153.5 | U646: 5 | V646: INR | X646: =IF(ISNUMBER(VALUE(LEFT(J646,1))),LEFT(J646,MIN(IFERROR(FIND("A",UPPER(J646)),LEN(J646)+1),IFERROR(FIND("B",UPPER(J646)),LEN(J646)+1),IFERROR(FIND("C",UPPER(J646)),LEN(J646)+1),IFERROR(FIND("D",UPPER(J646)),LEN(J646)+1),IFERROR(FIND("E",UPPER(J646)),LEN(J646)+1),IFERROR(FIND("F",UPPER(J646)),LEN(J646)+1),IFERROR(FIND("G",UPPER(J646)),LEN(J646)+1),IFERROR(FIND("H",UPPER(J646)),LEN(J646)+1),IFERROR(FIND("I",UPPER(J646)),LEN(J646)+1),IFERROR(FIND("J",UPPER(J646)),LEN(J646)+1),IFERROR(FIND("K",UPPER(J646)),LEN(J646)+1),IFERROR(FIND("L",UPPER(J646)),LEN(J646)+1),IFERROR(FIND("M",UPPER(J646)),LEN(J646)+1),IFERROR(FIND("N",UPPER(J646)),LEN(J646)+1),IFERROR(FIND("O",UPPER(J646)),LEN(J646)+1),IFERROR(FIND("P",UPPER(J646)),LEN(J646)+1),IFERROR(FIND("Q",UPPER(J646)),LEN(J646)+1),IFERROR(FIND("R",UPPER(J646)),LEN(J646)+1),IFERROR(FIND("S",UPPER(J646)),LEN(J646)+1),IFERROR(FIND("T",UPPER(J646)),LEN(J646)+1),IFERROR(FIND("U",UPPER(J646)),LEN(J646)+1),IFERROR(FIND("V",UPPER(J646)),LEN(J646)+1),IFERROR(FIND("W",UPPER(J646)),LEN(J646)+1),IFERROR(FIND("X",UPPER(J646)),LEN(J646)+1),IFERROR(FIND("Y",UPPER(J646)),LEN(J646)+1),IFERROR(FIND("Z",UPPER(J646)),LEN(J646)+1))-1),LEFT(TEXT(I646,"0"),LEN(TEXT(I646,"0"))-3)) -> 441857089 | Y646: =IF(ISNUMBER(SEARCH("(RP)",J646)),"RP","DC") -> RP | Z646: =IF(ISNUMBER(SEARCH("(RP)",J646)),O646,IF(RIGHT(TRIM(J646),3)=", S",O646,0)) -> 249 | AA646: =IF(ISNUMBER(SEARCH("(RP)",J646)),O646,IF(RIGHT(TRIM(J646),3)=", M",O646,0)) -> 249 | AB646: =IF(ISNUMBER(SEARCH("(RP)",J646)),O646,IF(RIGHT(TRIM(J646),3)=", L",O646,0)) -> 249 | AC646: =IF(ISNUMBER(SEARCH("(RP)",J646)),O646,IF(RIGHT(TRIM(J646),4)=", XL",O646,0)) -> 249 | AD646: =IF(ISNUMBER(SEARCH("(RP)",J646)),O646,IF(OR(RIGHT(TRIM(J646),5)=", XXL",RIGHT(TRIM(J646),5)=", 2XL"),O646,0)) -> 249 | AE646: {=IFERROR(_xlfn.XLOOKUP(H646,Sheet1!$G:$G,Sheet1!$F:$F),IFERROR(_xlfn.XLOOKUP(1,(--($X$2:$X$1074=X646))*(--ISNUMBER(MATCH($H$2:$H$1074,Sheet1!$G:$G,0))),_xlfn.XLOOKUP($H$2:$H$1074,Sheet1!$G:$G,Sheet1!$F:$F,"")),"NOT FOUND"))} -> YETKRTSCUT5008 | AF646: =IFERROR(IF(ISNUMBER(SEARCH("(RP)",J646)),TRIM(SUBSTITUTE(MID(J646,10,LEN(J646)),"(RP)","")),TRIM(MID(J646,FIND(",",J646)+1,FIND(",",J646,FIND(",",J646)+1)-FIND(",",J646)-1))),"") -> FUCHSIA | AG646: =IF(A646="SZAF","Bangalore",IF(A646="SAEX","JHAJJAR",IF(A646="S0EU","HARIPAL",""))) -> JHAJJAR | AH646: =IF(OR(J646="",AE646="",AE646="NOT FOUND"),"",IF(Y646="RP",IFERROR(LEFT(_xlfn.XLOOKUP(AE646,Sheet1!$F:$F,Sheet1!$W:$W),FIND("-",_xlfn.XLOOKUP(AE646,Sheet1!$F:$F,Sheet1!$W:$W),FIND("-",_xlfn.XLOOKUP(AE646,Sheet1!$F:$F,Sheet1!$W:$W))+1))&AE646,"NOT FOUND"),LEFT(J646,FIND("-",J646,FIND("-",J646)+1))&AE646)) -> KRTS-APSU26-YETKRTSCUT5008
A647: SAEX | B647: 5112963748 | C647: 30.01.2026 | D647: 20.05.2026 | E647: 10337044 | F647: UNITED TEXTILE MILLS PRIVATE LIMITE | G647: 1 | H647: 8909103992583 | I647: 494758187 | J647: 441857089 MUSTARD(RP) | L647: EA | M647: 1 | N647: 267 | O647: 267 | Q647: 1221.5 | R647: 1221.5 | S647: 16307.03 | T647: 326140.5 | U647: 5 | V647: INR | X647: =IF(ISNUMBER(VALUE(LEFT(J647,1))),LEFT(J647,MIN(IFERROR(FIND("A",UPPER(J647)),LEN(J647)+1),IFERROR(FIND("B",UPPER(J647)),LEN(J647)+1),IFERROR(FIND("C",UPPER(J647)),LEN(J647)+1),IFERROR(FIND("D",UPPER(J647)),LEN(J647)+1),IFERROR(FIND("E",UPPER(J647)),LEN(J647)+1),IFERROR(FIND("F",UPPER(J647)),LEN(J647)+1),IFERROR(FIND("G",UPPER(J647)),LEN(J647)+1),IFERROR(FIND("H",UPPER(J647)),LEN(J647)+1),IFERROR(FIND("I",UPPER(J647)),LEN(J647)+1),IFERROR(FIND("J",UPPER(J647)),LEN(J647)+1),IFERROR(FIND("K",UPPER(J647)),LEN(J647)+1),IFERROR(FIND("L",UPPER(J647)),LEN(J647)+1),IFERROR(FIND("M",UPPER(J647)),LEN(J647)+1),IFERROR(FIND("N",UPPER(J647)),LEN(J647)+1),IFERROR(FIND("O",UPPER(J647)),LEN(J647)+1),IFERROR(FIND("P",UPPER(J647)),LEN(J647)+1),IFERROR(FIND("Q",UPPER(J647)),LEN(J647)+1),IFERROR(FIND("R",UPPER(J647)),LEN(J647)+1),IFERROR(FIND("S",UPPER(J647)),LEN(J647)+1),IFERROR(FIND("T",UPPER(J647)),LEN(J647)+1),IFERROR(FIND("U",UPPER(J647)),LEN(J647)+1),IFERROR(FIND("V",UPPER(J647)),LEN(J647)+1),IFERROR(FIND("W",UPPER(J647)),LEN(J647)+1),IFERROR(FIND("X",UPPER(J647)),LEN(J647)+1),IFERROR(FIND("Y",UPPER(J647)),LEN(J647)+1),IFERROR(FIND("Z",UPPER(J647)),LEN(J647)+1))-1),LEFT(TEXT(I647,"0"),LEN(TEXT(I647,"0"))-3)) -> 441857089 | Y647: =IF(ISNUMBER(SEARCH("(RP)",J647)),"RP","DC") -> RP | Z647: =IF(ISNUMBER(SEARCH("(RP)",J647)),O647,IF(RIGHT(TRIM(J647),3)=", S",O647,0)) -> 267 | AA647: =IF(ISNUMBER(SEARCH("(RP)",J647)),O647,IF(RIGHT(TRIM(J647),3)=", M",O647,0)) -> 267 | AB647: =IF(ISNUMBER(SEARCH("(RP)",J647)),O647,IF(RIGHT(TRIM(J647),3)=", L",O647,0)) -> 267 | AC647: =IF(ISNUMBER(SEARCH("(RP)",J647)),O647,IF(RIGHT(TRIM(J647),4)=", XL",O647,0)) -> 267 | AD647: =IF(ISNUMBER(SEARCH("(RP)",J647)),O647,IF(OR(RIGHT(TRIM(J647),5)=", XXL",RIGHT(TRIM(J647),5)=", 2XL"),O647,0)) -> 267 | AE647: {=IFERROR(_xlfn.XLOOKUP(H647,Sheet1!$G:$G,Sheet1!$F:$F),IFERROR(_xlfn.XLOOKUP(1,(--($X$2:$X$1074=X647))*(--ISNUMBER(MATCH($H$2:$H$1074,Sheet1!$G:$G,0))),_xlfn.XLOOKUP($H$2:$H$1074,Sheet1!$G:$G,Sheet1!$F:$F,"")),"NOT FOUND"))} -> YETKRTSCUT5008 | AF647: =IFERROR(IF(ISNUMBER(SEARCH("(RP)",J647)),TRIM(SUBSTITUTE(MID(J647,10,LEN(J647)),"(RP)","")),TRIM(MID(J647,FIND(",",J647)+1,FIND(",",J647,FIND(",",J647)+1)-FIND(",",J647)-1))),"") -> MUSTARD | AG647: =IF(A647="SZAF","Bangalore",IF(A647="SAEX","JHAJJAR",IF(A647="S0EU","HARIPAL",""))) -> JHAJJAR | AH647: =IF(OR(J647="",AE647="",AE647="NOT FOUND"),"",IF(Y647="RP",IFERROR(LEFT(_xlfn.XLOOKUP(AE647,Sheet1!$F:$F,Sheet1!$W:$W),FIND("-",_xlfn.XLOOKUP(AE647,Sheet1!$F:$F,Sheet1!$W:$W),FIND("-",_xlfn.XLOOKUP(AE647,Sheet1!$F:$F,Sheet1!$W:$W))+1))&AE647,"NOT FOUND"),LEFT(J647,FIND("-",J647,FIND("-",J647)+1))&AE647)) -> KRTS-APSU26-YETKRTSCUT5008
A648: SAEX | B648: 5112963747 | C648: 30.01.2026 | D648: 30.06.2026 | E648: 10337044 | F648: UNITED TEXTILE MILLS PRIVATE LIMITE | G648: 1 | H648: 8909103992590 | I648: 494758188 | J648: 441857089 OFF WHITE(RP) | L648: EA | M648: 1 | N648: 284 | O648: 284 | Q648: 1221.5 | R648: 1221.5 | S648: 17345.3 | T648: 346906 | U648: 5 | V648: INR | X648: =IF(ISNUMBER(VALUE(LEFT(J648,1))),LEFT(J648,MIN(IFERROR(FIND("A",UPPER(J648)),LEN(J648)+1),IFERROR(FIND("B",UPPER(J648)),LEN(J648)+1),IFERROR(FIND("C",UPPER(J648)),LEN(J648)+1),IFERROR(FIND("D",UPPER(J648)),LEN(J648)+1),IFERROR(FIND("E",UPPER(J648)),LEN(J648)+1),IFERROR(FIND("F",UPPER(J648)),LEN(J648)+1),IFERROR(FIND("G",UPPER(J648)),LEN(J648)+1),IFERROR(FIND("H",UPPER(J648)),LEN(J648)+1),IFERROR(FIND("I",UPPER(J648)),LEN(J648)+1),IFERROR(FIND("J",UPPER(J648)),LEN(J648)+1),IFERROR(FIND("K",UPPER(J648)),LEN(J648)+1),IFERROR(FIND("L",UPPER(J648)),LEN(J648)+1),IFERROR(FIND("M",UPPER(J648)),LEN(J648)+1),IFERROR(FIND("N",UPPER(J648)),LEN(J648)+1),IFERROR(FIND("O",UPPER(J648)),LEN(J648)+1),IFERROR(FIND("P",UPPER(J648)),LEN(J648)+1),IFERROR(FIND("Q",UPPER(J648)),LEN(J648)+1),IFERROR(FIND("R",UPPER(J648)),LEN(J648)+1),IFERROR(FIND("S",UPPER(J648)),LEN(J648)+1),IFERROR(FIND("T",UPPER(J648)),LEN(J648)+1),IFERROR(FIND("U",UPPER(J648)),LEN(J648)+1),IFERROR(FIND("V",UPPER(J648)),LEN(J648)+1),IFERROR(FIND("W",UPPER(J648)),LEN(J648)+1),IFERROR(FIND("X",UPPER(J648)),LEN(J648)+1),IFERROR(FIND("Y",UPPER(J648)),LEN(J648)+1),IFERROR(FIND("Z",UPPER(J648)),LEN(J648)+1))-1),LEFT(TEXT(I648,"0"),LEN(TEXT(I648,"0"))-3)) -> 441857089 | Y648: =IF(ISNUMBER(SEARCH("(RP)",J648)),"RP","DC") -> RP | Z648: =IF(ISNUMBER(SEARCH("(RP)",J648)),O648,IF(RIGHT(TRIM(J648),3)=", S",O648,0)) -> 284 | AA648: =IF(ISNUMBER(SEARCH("(RP)",J648)),O648,IF(RIGHT(TRIM(J648),3)=", M",O648,0)) -> 284 | AB648: =IF(ISNUMBER(SEARCH("(RP)",J648)),O648,IF(RIGHT(TRIM(J648),3)=", L",O648,0)) -> 284 | AC648: =IF(ISNUMBER(SEARCH("(RP)",J648)),O648,IF(RIGHT(TRIM(J648),4)=", XL",O648,0)) -> 284 | AD648: =IF(ISNUMBER(SEARCH("(RP)",J648)),O648,IF(OR(RIGHT(TRIM(J648),5)=", XXL",RIGHT(TRIM(J648),5)=", 2XL"),O648,0)) -> 284 | AE648: {=IFERROR(_xlfn.XLOOKUP(H648,Sheet1!$G:$G,Sheet1!$F:$F),IFERROR(_xlfn.XLOOKUP(1,(--($X$2:$X$1074=X648))*(--ISNUMBER(MATCH($H$2:$H$1074,Sheet1!$G:$G,0))),_xlfn.XLOOKUP($H$2:$H$1074,Sheet1!$G:$G,Sheet1!$F:$F,"")),"NOT FOUND"))} -> YETKRTSCUT5008 | AF648: =IFERROR(IF(ISNUMBER(SEARCH("(RP)",J648)),TRIM(SUBSTITUTE(MID(J648,10,LEN(J648)),"(RP)","")),TRIM(MID(J648,FIND(",",J648)+1,FIND(",",J648,FIND(",",J648)+1)-FIND(",",J648)-1))),"") -> OFF WHITE | AG648: =IF(A648="SZAF","Bangalore",IF(A648="SAEX","JHAJJAR",IF(A648="S0EU","HARIPAL",""))) -> JHAJJAR | AH648: =IF(OR(J648="",AE648="",AE648="NOT FOUND"),"",IF(Y648="RP",IFERROR(LEFT(_xlfn.XLOOKUP(AE648,Sheet1!$F:$F,Sheet1!$W:$W),FIND("-",_xlfn.XLOOKUP(AE648,Sheet1!$F:$F,Sheet1!$W:$W),FIND("-",_xlfn.XLOOKUP(AE648,Sheet1!$F:$F,Sheet1!$W:$W))+1))&AE648,"NOT FOUND"),LEFT(J648,FIND("-",J648,FIND("-",J648)+1))&AE648)) -> KRTS-APSU26-YETKRTSCUT5008
A649: SAEX | B649: 5112963747 | C649: 30.01.2026 | D649: 30.06.2026 | E649: 10337044 | F649: UNITED TEXTILE MILLS PRIVATE LIMITE | G649: 2 | H649: 8909103992460 | I649: 441857089016 | J649: KRTS-APSU26-YETKRTSCUT50, OFF WHITE, 2XL | L649: EA | M649: 1 | N649: 284 | O649: 284 | Q649: 0 | R649: 0 | S649: 0 | T649: 0 | U649: 0 | V649: INR | X649: =IF(ISNUMBER(VALUE(LEFT(J649,1))),LEFT(J649,MIN(IFERROR(FIND("A",UPPER(J649)),LEN(J649)+1),IFERROR(FIND("B",UPPER(J649)),LEN(J649)+1),IFERROR(FIND("C",UPPER(J649)),LEN(J649)+1),IFERROR(FIND("D",UPPER(J649)),LEN(J649)+1),IFERROR(FIND("E",UPPER(J649)),LEN(J649)+1),IFERROR(FIND("F",UPPER(J649)),LEN(J649)+1),IFERROR(FIND("G",UPPER(J649)),LEN(J649)+1),IFERROR(FIND("H",UPPER(J649)),LEN(J649)+1),IFERROR(FIND("I",UPPER(J649)),LEN(J649)+1),IFERROR(FIND("J",UPPER(J649)),LEN(J649)+1),IFERROR(FIND("K",UPPER(J649)),LEN(J649)+1),IFERROR(FIND("L",UPPER(J649)),LEN(J649)+1),IFERROR(FIND("M",UPPER(J649)),LEN(J649)+1),IFERROR(FIND("N",UPPER(J649)),LEN(J649)+1),IFERROR(FIND("O",UPPER(J649)),LEN(J649)+1),IFERROR(FIND("P",UPPER(J649)),LEN(J649)+1),IFERROR(FIND("Q",UPPER(J649)),LEN(J649)+1),IFERROR(FIND("R",UPPER(J649)),LEN(J649)+1),IFERROR(FIND("S",UPPER(J649)),LEN(J649)+1),IFERROR(FIND("T",UPPER(J649)),LEN(J649)+1),IFERROR(FIND("U",UPPER(J649)),LEN(J649)+1),IFERROR(FIND("V",UPPER(J649)),LEN(J649)+1),IFERROR(FIND("W",UPPER(J649)),LEN(J649)+1),IFERROR(FIND("X",UPPER(J649)),LEN(J649)+1),IFERROR(FIND("Y",UPPER(J649)),LEN(J649)+1),IFERROR(FIND("Z",UPPER(J649)),LEN(J649)+1))-1),LEFT(TEXT(I649,"0"),LEN(TEXT(I649,"0"))-3)) -> 441857089 | Y649: =IF(ISNUMBER(SEARCH("(RP)",J649)),"RP","DC") -> DC | Z649: =IF(ISNUMBER(SEARCH("(RP)",J649)),O649,IF(RIGHT(TRIM(J649),3)=", S",O649,0)) -> 0 | AA649: =IF(ISNUMBER(SEARCH("(RP)",J649)),O649,IF(RIGHT(TRIM(J649),3)=", M",O649,0)) -> 0 | AB649: =IF(ISNUMBER(SEARCH("(RP)",J649)),O649,IF(RIGHT(TRIM(J649),3)=", L",O649,0)) -> 0 | AC649: =IF(ISNUMBER(SEARCH("(RP)",J649)),O649,IF(RIGHT(TRIM(J649),4)=", XL",O649,0)) -> 0 | AD649: =IF(ISNUMBER(SEARCH("(RP)",J649)),O649,IF(OR(RIGHT(TRIM(J649),5)=", XXL",RIGHT(TRIM(J649),5)=", 2XL"),O649,0)) -> 284 | AE649: {=IFERROR(_xlfn.XLOOKUP(H649,Sheet1!$G:$G,Sheet1!$F:$F),IFERROR(_xlfn.XLOOKUP(1,(--($X$2:$X$1074=X649))*(--ISNUMBER(MATCH($H$2:$H$1074,Sheet1!$G:$G,0))),_xlfn.XLOOKUP($H$2:$H$1074,Sheet1!$G:$G,Sheet1!$F:$F,"")),"NOT FOUND"))} -> YETKRTSCUT5008 | AF649: =IFERROR(IF(ISNUMBER(SEARCH("(RP)",J649)),TRIM(SUBSTITUTE(MID(J649,10,LEN(J649)),"(RP)","")),TRIM(MID(J649,FIND(",",J649)+1,FIND(",",J649,FIND(",",J649)+1)-FIND(",",J649)-1))),"") -> OFF WHITE | AG649: =IF(A649="SZAF","Bangalore",IF(A649="SAEX","JHAJJAR",IF(A649="S0EU","HARIPAL",""))) -> JHAJJAR | AH649: =IF(OR(J649="",AE649="",AE649="NOT FOUND"),"",IF(Y649="RP",IFERROR(LEFT(_xlfn.XLOOKUP(AE649,Sheet1!$F:$F,Sheet1!$W:$W),FIND("-",_xlfn.XLOOKUP(AE649,Sheet1!$F:$F,Sheet1!$W:$W),FIND("-",_xlfn.XLOOKUP(AE649,Sheet1!$F:$F,Sheet1!$W:$W))+1))&AE649,"NOT FOUND"),LEFT(J649,FIND("-",J649,FIND("-",J649)+1))&AE649)) -> KRTS-APSU26-YETKRTSCUT5008
A650: SAEX | B650: 5112963747 | C650: 30.01.2026 | D650: 30.06.2026 | E650: 10337044 | F650: UNITED TEXTILE MILLS PRIVATE LIMITE | G650: 3 | H650: 8909103992453 | I650: 441857089017 | J650: KRTS-APSU26-YETKRTSCUT500, OFF WHITE, XL | L650: EA | M650: 1 | N650: 284 | O650: 284 | Q650: 0 | R650: 0 | S650: 0 | T650: 0 | U650: 0 | V650: INR | X650: =IF(ISNUMBER(VALUE(LEFT(J650,1))),LEFT(J650,MIN(IFERROR(FIND("A",UPPER(J650)),LEN(J650)+1),IFERROR(FIND("B",UPPER(J650)),LEN(J650)+1),IFERROR(FIND("C",UPPER(J650)),LEN(J650)+1),IFERROR(FIND("D",UPPER(J650)),LEN(J650)+1),IFERROR(FIND("E",UPPER(J650)),LEN(J650)+1),IFERROR(FIND("F",UPPER(J650)),LEN(J650)+1),IFERROR(FIND("G",UPPER(J650)),LEN(J650)+1),IFERROR(FIND("H",UPPER(J650)),LEN(J650)+1),IFERROR(FIND("I",UPPER(J650)),LEN(J650)+1),IFERROR(FIND("J",UPPER(J650)),LEN(J650)+1),IFERROR(FIND("K",UPPER(J650)),LEN(J650)+1),IFERROR(FIND("L",UPPER(J650)),LEN(J650)+1),IFERROR(FIND("M",UPPER(J650)),LEN(J650)+1),IFERROR(FIND("N",UPPER(J650)),LEN(J650)+1),IFERROR(FIND("O",UPPER(J650)),LEN(J650)+1),IFERROR(FIND("P",UPPER(J650)),LEN(J650)+1),IFERROR(FIND("Q",UPPER(J650)),LEN(J650)+1),IFERROR(FIND("R",UPPER(J650)),LEN(J650)+1),IFERROR(FIND("S",UPPER(J650)),LEN(J650)+1),IFERROR(FIND("T",UPPER(J650)),LEN(J650)+1),IFERROR(FIND("U",UPPER(J650)),LEN(J650)+1),IFERROR(FIND("V",UPPER(J650)),LEN(J650)+1),IFERROR(FIND("W",UPPER(J650)),LEN(J650)+1),IFERROR(FIND("X",UPPER(J650)),LEN(J650)+1),IFERROR(FIND("Y",UPPER(J650)),LEN(J650)+1),IFERROR(FIND("Z",UPPER(J650)),LEN(J650)+1))-1),LEFT(TEXT(I650,"0"),LEN(TEXT(I650,"0"))-3)) -> 441857089 | Y650: =IF(ISNUMBER(SEARCH("(RP)",J650)),"RP","DC") -> DC | Z650: =IF(ISNUMBER(SEARCH("(RP)",J650)),O650,IF(RIGHT(TRIM(J650),3)=", S",O650,0)) -> 0 | AA650: =IF(ISNUMBER(SEARCH("(RP)",J650)),O650,IF(RIGHT(TRIM(J650),3)=", M",O650,0)) -> 0 | AB650: =IF(ISNUMBER(SEARCH("(RP)",J650)),O650,IF(RIGHT(TRIM(J650),3)=", L",O650,0)) -> 0 | AC650: =IF(ISNUMBER(SEARCH("(RP)",J650)),O650,IF(RIGHT(TRIM(J650),4)=", XL",O650,0)) -> 284 | AD650: =IF(ISNUMBER(SEARCH("(RP)",J650)),O650,IF(OR(RIGHT(TRIM(J650),5)=", XXL",RIGHT(TRIM(J650),5)=", 2XL"),O650,0)) -> 0 | AE650: {=IFERROR(_xlfn.XLOOKUP(H650,Sheet1!$G:$G,Sheet1!$F:$F),IFERROR(_xlfn.XLOOKUP(1,(--($X$2:$X$1074=X650))*(--ISNUMBER(MATCH($H$2:$H$1074,Sheet1!$G:$G,0))),_xlfn.XLOOKUP($H$2:$H$1074,Sheet1!$G:$G,Sheet1!$F:$F,"")),"NOT FOUND"))} -> YETKRTSCUT5008 | AF650: =IFERROR(IF(ISNUMBER(SEARCH("(RP)",J650)),TRIM(SUBSTITUTE(MID(J650,10,LEN(J650)),"(RP)","")),TRIM(MID(J650,FIND(",",J650)+1,FIND(",",J650,FIND(",",J650)+1)-FIND(",",J650)-1))),"") -> OFF WHITE | AG650: =IF(A650="SZAF","Bangalore",IF(A650="SAEX","JHAJJAR",IF(A650="S0EU","HARIPAL",""))) -> JHAJJAR | AH650: =IF(OR(J650="",AE650="",AE650="NOT FOUND"),"",IF(Y650="RP",IFERROR(LEFT(_xlfn.XLOOKUP(AE650,Sheet1!$F:$F,Sheet1!$W:$W),FIND("-",_xlfn.XLOOKUP(AE650,Sheet1!$F:$F,Sheet1!$W:$W),FIND("-",_xlfn.XLOOKUP(AE650,Sheet1!$F:$F,Sheet1!$W:$W))+1))&AE650,"NOT FOUND"),LEFT(J650,FIND("-",J650,FIND("-",J650)+1))&AE650)) -> KRTS-APSU26-YETKRTSCUT5008
A651: SAEX | B651: 5112963747 | C651: 30.01.2026 | D651: 30.06.2026 | E651: 10337044 | F651: UNITED TEXTILE MILLS PRIVATE LIMITE | G651: 4 | H651: 8909103992446 | I651: 441857089018 | J651: KRTS-APSU26-YETKRTSCUT5008, OFF WHITE, L | L651: EA | M651: 1 | N651: 284 | O651: 284 | Q651: 0 | R651: 0 | S651: 0 | T651: 0 | U651: 0 | V651: INR | X651: =IF(ISNUMBER(VALUE(LEFT(J651,1))),LEFT(J651,MIN(IFERROR(FIND("A",UPPER(J651)),LEN(J651)+1),IFERROR(FIND("B",UPPER(J651)),LEN(J651)+1),IFERROR(FIND("C",UPPER(J651)),LEN(J651)+1),IFERROR(FIND("D",UPPER(J651)),LEN(J651)+1),IFERROR(FIND("E",UPPER(J651)),LEN(J651)+1),IFERROR(FIND("F",UPPER(J651)),LEN(J651)+1),IFERROR(FIND("G",UPPER(J651)),LEN(J651)+1),IFERROR(FIND("H",UPPER(J651)),LEN(J651)+1),IFERROR(FIND("I",UPPER(J651)),LEN(J651)+1),IFERROR(FIND("J",UPPER(J651)),LEN(J651)+1),IFERROR(FIND("K",UPPER(J651)),LEN(J651)+1),IFERROR(FIND("L",UPPER(J651)),LEN(J651)+1),IFERROR(FIND("M",UPPER(J651)),LEN(J651)+1),IFERROR(FIND("N",UPPER(J651)),LEN(J651)+1),IFERROR(FIND("O",UPPER(J651)),LEN(J651)+1),IFERROR(FIND("P",UPPER(J651)),LEN(J651)+1),IFERROR(FIND("Q",UPPER(J651)),LEN(J651)+1),IFERROR(FIND("R",UPPER(J651)),LEN(J651)+1),IFERROR(FIND("S",UPPER(J651)),LEN(J651)+1),IFERROR(FIND("T",UPPER(J651)),LEN(J651)+1),IFERROR(FIND("U",UPPER(J651)),LEN(J651)+1),IFERROR(FIND("V",UPPER(J651)),LEN(J651)+1),IFERROR(FIND("W",UPPER(J651)),LEN(J651)+1),IFERROR(FIND("X",UPPER(J651)),LEN(J651)+1),IFERROR(FIND("Y",UPPER(J651)),LEN(J651)+1),IFERROR(FIND("Z",UPPER(J651)),LEN(J651)+1))-1),LEFT(TEXT(I651,"0"),LEN(TEXT(I651,"0"))-3)) -> 441857089 | Y651: =IF(ISNUMBER(SEARCH("(RP)",J651)),"RP","DC") -> DC | Z651: =IF(ISNUMBER(SEARCH("(RP)",J651)),O651,IF(RIGHT(TRIM(J651),3)=", S",O651,0)) -> 0 | AA651: =IF(ISNUMBER(SEARCH("(RP)",J651)),O651,IF(RIGHT(TRIM(J651),3)=", M",O651,0)) -> 0 | AB651: =IF(ISNUMBER(SEARCH("(RP)",J651)),O651,IF(RIGHT(TRIM(J651),3)=", L",O651,0)) -> 284 | AC651: =IF(ISNUMBER(SEARCH("(RP)",J651)),O651,IF(RIGHT(TRIM(J651),4)=", XL",O651,0)) -> 0 | AD651: =IF(ISNUMBER(SEARCH("(RP)",J651)),O651,IF(OR(RIGHT(TRIM(J651),5)=", XXL",RIGHT(TRIM(J651),5)=", 2XL"),O651,0)) -> 0 | AE651: {=IFERROR(_xlfn.XLOOKUP(H651,Sheet1!$G:$G,Sheet1!$F:$F),IFERROR(_xlfn.XLOOKUP(1,(--($X$2:$X$1074=X651))*(--ISNUMBER(MATCH($H$2:$H$1074,Sheet1!$G:$G,0))),_xlfn.XLOOKUP($H$2:$H$1074,Sheet1!$G:$G,Sheet1!$F:$F,"")),"NOT FOUND"))} -> YETKRTSCUT5008 | AF651: =IFERROR(IF(ISNUMBER(SEARCH("(RP)",J651)),TRIM(SUBSTITUTE(MID(J651,10,LEN(J651)),"(RP)","")),TRIM(MID(J651,FIND(",",J651)+1,FIND(",",J651,FIND(",",J651)+1)-FIND(",",J651)-1))),"") -> OFF WHITE | AG651: =IF(A651="SZAF","Bangalore",IF(A651="SAEX","JHAJJAR",IF(A651="S0EU","HARIPAL",""))) -> JHAJJAR | AH651: =IF(OR(J651="",AE651="",AE651="NOT FOUND"),"",IF(Y651="RP",IFERROR(LEFT(_xlfn.XLOOKUP(AE651,Sheet1!$F:$F,Sheet1!$W:$W),FIND("-",_xlfn.XLOOKUP(AE651,Sheet1!$F:$F,Sheet1!$W:$W),FIND("-",_xlfn.XLOOKUP(AE651,Sheet1!$F:$F,Sheet1!$W:$W))+1))&AE651,"NOT FOUND"),LEFT(J651,FIND("-",J651,FIND("-",J651)+1))&AE651)) -> KRTS-APSU26-YETKRTSCUT5008
A652: SAEX | B652: 5112963747 | C652: 30.01.2026 | D652: 30.06.2026 | E652: 10337044 | F652: UNITED TEXTILE MILLS PRIVATE LIMITE | G652: 5 | H652: 8909103992439 | I652: 441857089019 | J652: KRTS-APSU26-YETKRTSCUT5008, OFF WHITE, M | L652: EA | M652: 1 | N652: 284 | O652: 284 | Q652: 0 | R652: 0 | S652: 0 | T652: 0 | U652: 0 | V652: INR | X652: =IF(ISNUMBER(VALUE(LEFT(J652,1))),LEFT(J652,MIN(IFERROR(FIND("A",UPPER(J652)),LEN(J652)+1),IFERROR(FIND("B",UPPER(J652)),LEN(J652)+1),IFERROR(FIND("C",UPPER(J652)),LEN(J652)+1),IFERROR(FIND("D",UPPER(J652)),LEN(J652)+1),IFERROR(FIND("E",UPPER(J652)),LEN(J652)+1),IFERROR(FIND("F",UPPER(J652)),LEN(J652)+1),IFERROR(FIND("G",UPPER(J652)),LEN(J652)+1),IFERROR(FIND("H",UPPER(J652)),LEN(J652)+1),IFERROR(FIND("I",UPPER(J652)),LEN(J652)+1),IFERROR(FIND("J",UPPER(J652)),LEN(J652)+1),IFERROR(FIND("K",UPPER(J652)),LEN(J652)+1),IFERROR(FIND("L",UPPER(J652)),LEN(J652)+1),IFERROR(FIND("M",UPPER(J652)),LEN(J652)+1),IFERROR(FIND("N",UPPER(J652)),LEN(J652)+1),IFERROR(FIND("O",UPPER(J652)),LEN(J652)+1),IFERROR(FIND("P",UPPER(J652)),LEN(J652)+1),IFERROR(FIND("Q",UPPER(J652)),LEN(J652)+1),IFERROR(FIND("R",UPPER(J652)),LEN(J652)+1),IFERROR(FIND("S",UPPER(J652)),LEN(J652)+1),IFERROR(FIND("T",UPPER(J652)),LEN(J652)+1),IFERROR(FIND("U",UPPER(J652)),LEN(J652)+1),IFERROR(FIND("V",UPPER(J652)),LEN(J652)+1),IFERROR(FIND("W",UPPER(J652)),LEN(J652)+1),IFERROR(FIND("X",UPPER(J652)),LEN(J652)+1),IFERROR(FIND("Y",UPPER(J652)),LEN(J652)+1),IFERROR(FIND("Z",UPPER(J652)),LEN(J652)+1))-1),LEFT(TEXT(I652,"0"),LEN(TEXT(I652,"0"))-3)) -> 441857089 | Y652: =IF(ISNUMBER(SEARCH("(RP)",J652)),"RP","DC") -> DC | Z652: =IF(ISNUMBER(SEARCH("(RP)",J652)),O652,IF(RIGHT(TRIM(J652),3)=", S",O652,0)) -> 0 | AA652: =IF(ISNUMBER(SEARCH("(RP)",J652)),O652,IF(RIGHT(TRIM(J652),3)=", M",O652,0)) -> 284 | AB652: =IF(ISNUMBER(SEARCH("(RP)",J652)),O652,IF(RIGHT(TRIM(J652),3)=", L",O652,0)) -> 0 | AC652: =IF(ISNUMBER(SEARCH("(RP)",J652)),O652,IF(RIGHT(TRIM(J652),4)=", XL",O652,0)) -> 0 | AD652: =IF(ISNUMBER(SEARCH("(RP)",J652)),O652,IF(OR(RIGHT(TRIM(J652),5)=", XXL",RIGHT(TRIM(J652),5)=", 2XL"),O652,0)) -> 0 | AE652: {=IFERROR(_xlfn.XLOOKUP(H652,Sheet1!$G:$G,Sheet1!$F:$F),IFERROR(_xlfn.XLOOKUP(1,(--($X$2:$X$1074=X652))*(--ISNUMBER(MATCH($H$2:$H$1074,Sheet1!$G:$G,0))),_xlfn.XLOOKUP($H$2:$H$1074,Sheet1!$G:$G,Sheet1!$F:$F,"")),"NOT FOUND"))} -> YETKRTSCUT5008 | AF652: =IFERROR(IF(ISNUMBER(SEARCH("(RP)",J652)),TRIM(SUBSTITUTE(MID(J652,10,LEN(J652)),"(RP)","")),TRIM(MID(J652,FIND(",",J652)+1,FIND(",",J652,FIND(",",J652)+1)-FIND(",",J652)-1))),"") -> OFF WHITE | AG652: =IF(A652="SZAF","Bangalore",IF(A652="SAEX","JHAJJAR",IF(A652="S0EU","HARIPAL",""))) -> JHAJJAR | AH652: =IF(OR(J652="",AE652="",AE652="NOT FOUND"),"",IF(Y652="RP",IFERROR(LEFT(_xlfn.XLOOKUP(AE652,Sheet1!$F:$F,Sheet1!$W:$W),FIND("-",_xlfn.XLOOKUP(AE652,Sheet1!$F:$F,Sheet1!$W:$W),FIND("-",_xlfn.XLOOKUP(AE652,Sheet1!$F:$F,Sheet1!$W:$W))+1))&AE652,"NOT FOUND"),LEFT(J652,FIND("-",J652,FIND("-",J652)+1))&AE652)) -> KRTS-APSU26-YETKRTSCUT5008
A653: SAEX | B653: 5112963747 | C653: 30.01.2026 | D653: 30.06.2026 | E653: 10337044 | F653: UNITED TEXTILE MILLS PRIVATE LIMITE | G653: 6 | H653: 8909103992422 | I653: 441857089020 | J653: KRTS-APSU26-YETKRTSCUT5008, OFF WHITE, S | L653: EA | M653: 1 | N653: 284 | O653: 284 | Q653: 0 | R653: 0 | S653: 0 | T653: 0 | U653: 0 | X653: =IF(ISNUMBER(VALUE(LEFT(J653,1))),LEFT(J653,MIN(IFERROR(FIND("A",UPPER(J653)),LEN(J653)+1),IFERROR(FIND("B",UPPER(J653)),LEN(J653)+1),IFERROR(FIND("C",UPPER(J653)),LEN(J653)+1),IFERROR(FIND("D",UPPER(J653)),LEN(J653)+1),IFERROR(FIND("E",UPPER(J653)),LEN(J653)+1),IFERROR(FIND("F",UPPER(J653)),LEN(J653)+1),IFERROR(FIND("G",UPPER(J653)),LEN(J653)+1),IFERROR(FIND("H",UPPER(J653)),LEN(J653)+1),IFERROR(FIND("I",UPPER(J653)),LEN(J653)+1),IFERROR(FIND("J",UPPER(J653)),LEN(J653)+1),IFERROR(FIND("K",UPPER(J653)),LEN(J653)+1),IFERROR(FIND("L",UPPER(J653)),LEN(J653)+1),IFERROR(FIND("M",UPPER(J653)),LEN(J653)+1),IFERROR(FIND("N",UPPER(J653)),LEN(J653)+1),IFERROR(FIND("O",UPPER(J653)),LEN(J653)+1),IFERROR(FIND("P",UPPER(J653)),LEN(J653)+1),IFERROR(FIND("Q",UPPER(J653)),LEN(J653)+1),IFERROR(FIND("R",UPPER(J653)),LEN(J653)+1),IFERROR(FIND("S",UPPER(J653)),LEN(J653)+1),IFERROR(FIND("T",UPPER(J653)),LEN(J653)+1),IFERROR(FIND("U",UPPER(J653)),LEN(J653)+1),IFERROR(FIND("V",UPPER(J653)),LEN(J653)+1),IFERROR(FIND("W",UPPER(J653)),LEN(J653)+1),IFERROR(FIND("X",UPPER(J653)),LEN(J653)+1),IFERROR(FIND("Y",UPPER(J653)),LEN(J653)+1),IFERROR(FIND("Z",UPPER(J653)),LEN(J653)+1))-1),LEFT(TEXT(I653,"0"),LEN(TEXT(I653,"0"))-3)) -> 441857089 | Y653: =IF(ISNUMBER(SEARCH("(RP)",J653)),"RP","DC") -> DC | Z653: =IF(ISNUMBER(SEARCH("(RP)",J653)),O653,IF(RIGHT(TRIM(J653),3)=", S",O653,0)) -> 284 | AA653: =IF(ISNUMBER(SEARCH("(RP)",J653)),O653,IF(RIGHT(TRIM(J653),3)=", M",O653,0)) -> 0 | AB653: =IF(ISNUMBER(SEARCH("(RP)",J653)),O653,IF(RIGHT(TRIM(J653),3)=", L",O653,0)) -> 0 | AC653: =IF(ISNUMBER(SEARCH("(RP)",J653)),O653,IF(RIGHT(TRIM(J653),4)=", XL",O653,0)) -> 0 | AD653: =IF(ISNUMBER(SEARCH("(RP)",J653)),O653,IF(OR(RIGHT(TRIM(J653),5)=", XXL",RIGHT(TRIM(J653),5)=", 2XL"),O653,0)) -> 0 | AE653: {=IFERROR(_xlfn.XLOOKUP(H653,Sheet1!$G:$G,Sheet1!$F:$F),IFERROR(_xlfn.XLOOKUP(1,(--($X$2:$X$1074=X653))*(--ISNUMBER(MATCH($H$2:$H$1074,Sheet1!$G:$G,0))),_xlfn.XLOOKUP($H$2:$H$1074,Sheet1!$G:$G,Sheet1!$F:$F,"")),"NOT FOUND"))} -> YETKRTSCUT5008 | AF653: =IFERROR(IF(ISNUMBER(SEARCH("(RP)",J653)),TRIM(SUBSTITUTE(MID(J653,10,LEN(J653)),"(RP)","")),TRIM(MID(J653,FIND(",",J653)+1,FIND(",",J653,FIND(",",J653)+1)-FIND(",",J653)-1))),"") -> OFF WHITE | AG653: =IF(A653="SZAF","Bangalore",IF(A653="SAEX","JHAJJAR",IF(A653="S0EU","HARIPAL",""))) -> JHAJJAR | AH653: =IF(OR(J653="",AE653="",AE653="NOT FOUND"),"",IF(Y653="RP",IFERROR(LEFT(_xlfn.XLOOKUP(AE653,Sheet1!$F:$F,Sheet1!$W:$W),FIND("-",_xlfn.XLOOKUP(AE653,Sheet1!$F:$F,Sheet1!$W:$W),FIND("-",_xlfn.XLOOKUP(AE653,Sheet1!$F:$F,Sheet1!$W:$W))+1))&AE653,"NOT FOUND"),LEFT(J653,FIND("-",J653,FIND("-",J653)+1))&AE653)) -> KRTS-APSU26-YETKRTSCUT5008
A654: SAEX | B654: 5112963746 | C654: 30.01.2026 | D654: 30.06.2026 | E654: 10337044 | F654: UNITED TEXTILE MILLS PRIVATE LIMITE | G654: 1 | H654: 8909103992606 | I654: 494758189 | J654: 441857089 RUST(RP) | L654: EA | M654: 1 | N654: 284 | O654: 284 | Q654: 1221.5 | R654: 1221.5 | S654: 17345.3 | T654: 346906 | U654: 5 | V654: INR | X654: =IF(ISNUMBER(VALUE(LEFT(J654,1))),LEFT(J654,MIN(IFERROR(FIND("A",UPPER(J654)),LEN(J654)+1),IFERROR(FIND("B",UPPER(J654)),LEN(J654)+1),IFERROR(FIND("C",UPPER(J654)),LEN(J654)+1),IFERROR(FIND("D",UPPER(J654)),LEN(J654)+1),IFERROR(FIND("E",UPPER(J654)),LEN(J654)+1),IFERROR(FIND("F",UPPER(J654)),LEN(J654)+1),IFERROR(FIND("G",UPPER(J654)),LEN(J654)+1),IFERROR(FIND("H",UPPER(J654)),LEN(J654)+1),IFERROR(FIND("I",UPPER(J654)),LEN(J654)+1),IFERROR(FIND("J",UPPER(J654)),LEN(J654)+1),IFERROR(FIND("K",UPPER(J654)),LEN(J654)+1),IFERROR(FIND("L",UPPER(J654)),LEN(J654)+1),IFERROR(FIND("M",UPPER(J654)),LEN(J654)+1),IFERROR(FIND("N",UPPER(J654)),LEN(J654)+1),IFERROR(FIND("O",UPPER(J654)),LEN(J654)+1),IFERROR(FIND("P",UPPER(J654)),LEN(J654)+1),IFERROR(FIND("Q",UPPER(J654)),LEN(J654)+1),IFERROR(FIND("R",UPPER(J654)),LEN(J654)+1),IFERROR(FIND("S",UPPER(J654)),LEN(J654)+1),IFERROR(FIND("T",UPPER(J654)),LEN(J654)+1),IFERROR(FIND("U",UPPER(J654)),LEN(J654)+1),IFERROR(FIND("V",UPPER(J654)),LEN(J654)+1),IFERROR(FIND("W",UPPER(J654)),LEN(J654)+1),IFERROR(FIND("X",UPPER(J654)),LEN(J654)+1),IFERROR(FIND("Y",UPPER(J654)),LEN(J654)+1),IFERROR(FIND("Z",UPPER(J654)),LEN(J654)+1))-1),LEFT(TEXT(I654,"0"),LEN(TEXT(I654,"0"))-3)) -> 441857089 | Y654: =IF(ISNUMBER(SEARCH("(RP)",J654)),"RP","DC") -> RP | Z654: =IF(ISNUMBER(SEARCH("(RP)",J654)),O654,IF(RIGHT(TRIM(J654),3)=", S",O654,0)) -> 284 | AA654: =IF(ISNUMBER(SEARCH("(RP)",J654)),O654,IF(RIGHT(TRIM(J654),3)=", M",O654,0)) -> 284 | AB654: =IF(ISNUMBER(SEARCH("(RP)",J654)),O654,IF(RIGHT(TRIM(J654),3)=", L",O654,0)) -> 284 | AC654: =IF(ISNUMBER(SEARCH("(RP)",J654)),O654,IF(RIGHT(TRIM(J654),4)=", XL",O654,0)) -> 284 | AD654: =IF(ISNUMBER(SEARCH("(RP)",J654)),O654,IF(OR(RIGHT(TRIM(J654),5)=", XXL",RIGHT(TRIM(J654),5)=", 2XL"),O654,0)) -> 284 | AE654: {=IFERROR(_xlfn.XLOOKUP(H654,Sheet1!$G:$G,Sheet1!$F:$F),IFERROR(_xlfn.XLOOKUP(1,(--($X$2:$X$1074=X654))*(--ISNUMBER(MATCH($H$2:$H$1074,Sheet1!$G:$G,0))),_xlfn.XLOOKUP($H$2:$H$1074,Sheet1!$G:$G,Sheet1!$F:$F,"")),"NOT FOUND"))} -> YETKRTSCUT5008 | AF654: =IFERROR(IF(ISNUMBER(SEARCH("(RP)",J654)),TRIM(SUBSTITUTE(MID(J654,10,LEN(J654)),"(RP)","")),TRIM(MID(J654,FIND(",",J654)+1,FIND(",",J654,FIND(",",J654)+1)-FIND(",",J654)-1))),"") -> RUST | AG654: =IF(A654="SZAF","Bangalore",IF(A654="SAEX","JHAJJAR",IF(A654="S0EU","HARIPAL",""))) -> JHAJJAR | AH654: =IF(OR(J654="",AE654="",AE654="NOT FOUND"),"",IF(Y654="RP",IFERROR(LEFT(_xlfn.XLOOKUP(AE654,Sheet1!$F:$F,Sheet1!$W:$W),FIND("-",_xlfn.XLOOKUP(AE654,Sheet1!$F:$F,Sheet1!$W:$W),FIND("-",_xlfn.XLOOKUP(AE654,Sheet1!$F:$F,Sheet1!$W:$W))+1))&AE654,"NOT FOUND"),LEFT(J654,FIND("-",J654,FIND("-",J654)+1))&AE654)) -> KRTS-APSU26-YETKRTSCUT5008
A655: SAEX | B655: 5112963746 | C655: 30.01.2026 | D655: 30.06.2026 | E655: 10337044 | F655: UNITED TEXTILE MILLS PRIVATE LIMITE | G655: 2 | H655: 8909103992514 | I655: 441857089011 | J655: KRTS-APSU26-YETKRTSCUT5008, RUST, 2XL | L655: EA | M655: 1 | N655: 284 | O655: 284 | Q655: 0 | R655: 0 | S655: 0 | T655: 0 | U655: 0 | V655: INR | X655: =IF(ISNUMBER(VALUE(LEFT(J655,1))),LEFT(J655,MIN(IFERROR(FIND("A",UPPER(J655)),LEN(J655)+1),IFERROR(FIND("B",UPPER(J655)),LEN(J655)+1),IFERROR(FIND("C",UPPER(J655)),LEN(J655)+1),IFERROR(FIND("D",UPPER(J655)),LEN(J655)+1),IFERROR(FIND("E",UPPER(J655)),LEN(J655)+1),IFERROR(FIND("F",UPPER(J655)),LEN(J655)+1),IFERROR(FIND("G",UPPER(J655)),LEN(J655)+1),IFERROR(FIND("H",UPPER(J655)),LEN(J655)+1),IFERROR(FIND("I",UPPER(J655)),LEN(J655)+1),IFERROR(FIND("J",UPPER(J655)),LEN(J655)+1),IFERROR(FIND("K",UPPER(J655)),LEN(J655)+1),IFERROR(FIND("L",UPPER(J655)),LEN(J655)+1),IFERROR(FIND("M",UPPER(J655)),LEN(J655)+1),IFERROR(FIND("N",UPPER(J655)),LEN(J655)+1),IFERROR(FIND("O",UPPER(J655)),LEN(J655)+1),IFERROR(FIND("P",UPPER(J655)),LEN(J655)+1),IFERROR(FIND("Q",UPPER(J655)),LEN(J655)+1),IFERROR(FIND("R",UPPER(J655)),LEN(J655)+1),IFERROR(FIND("S",UPPER(J655)),LEN(J655)+1),IFERROR(FIND("T",UPPER(J655)),LEN(J655)+1),IFERROR(FIND("U",UPPER(J655)),LEN(J655)+1),IFERROR(FIND("V",UPPER(J655)),LEN(J655)+1),IFERROR(FIND("W",UPPER(J655)),LEN(J655)+1),IFERROR(FIND("X",UPPER(J655)),LEN(J655)+1),IFERROR(FIND("Y",UPPER(J655)),LEN(J655)+1),IFERROR(FIND("Z",UPPER(J655)),LEN(J655)+1))-1),LEFT(TEXT(I655,"0"),LEN(TEXT(I655,"0"))-3)) -> 441857089 | Y655: =IF(ISNUMBER(SEARCH("(RP)",J655)),"RP","DC") -> DC | Z655: =IF(ISNUMBER(SEARCH("(RP)",J655)),O655,IF(RIGHT(TRIM(J655),3)=", S",O655,0)) -> 0 | AA655: =IF(ISNUMBER(SEARCH("(RP)",J655)),O655,IF(RIGHT(TRIM(J655),3)=", M",O655,0)) -> 0 | AB655: =IF(ISNUMBER(SEARCH("(RP)",J655)),O655,IF(RIGHT(TRIM(J655),3)=", L",O655,0)) -> 0 | AC655: =IF(ISNUMBER(SEARCH("(RP)",J655)),O655,IF(RIGHT(TRIM(J655),4)=", XL",O655,0)) -> 0 | AD655: =IF(ISNUMBER(SEARCH("(RP)",J655)),O655,IF(OR(RIGHT(TRIM(J655),5)=", XXL",RIGHT(TRIM(J655),5)=", 2XL"),O655,0)) -> 284 | AE655: {=IFERROR(_xlfn.XLOOKUP(H655,Sheet1!$G:$G,Sheet1!$F:$F),IFERROR(_xlfn.XLOOKUP(1,(--($X$2:$X$1074=X655))*(--ISNUMBER(MATCH($H$2:$H$1074,Sheet1!$G:$G,0))),_xlfn.XLOOKUP($H$2:$H$1074,Sheet1!$G:$G,Sheet1!$F:$F,"")),"NOT FOUND"))} -> YETKRTSCUT5008 | AF655: =IFERROR(IF(ISNUMBER(SEARCH("(RP)",J655)),TRIM(SUBSTITUTE(MID(J655,10,LEN(J655)),"(RP)","")),TRIM(MID(J655,FIND(",",J655)+1,FIND(",",J655,FIND(",",J655)+1)-FIND(",",J655)-1))),"") -> RUST | AG655: =IF(A655="SZAF","Bangalore",IF(A655="SAEX","JHAJJAR",IF(A655="S0EU","HARIPAL",""))) -> JHAJJAR | AH655: =IF(OR(J655="",AE655="",AE655="NOT FOUND"),"",IF(Y655="RP",IFERROR(LEFT(_xlfn.XLOOKUP(AE655,Sheet1!$F:$F,Sheet1!$W:$W),FIND("-",_xlfn.XLOOKUP(AE655,Sheet1!$F:$F,Sheet1!$W:$W),FIND("-",_xlfn.XLOOKUP(AE655,Sheet1!$F:$F,Sheet1!$W:$W))+1))&AE655,"NOT FOUND"),LEFT(J655,FIND("-",J655,FIND("-",J655)+1))&AE655)) -> KRTS-APSU26-YETKRTSCUT5008
A656: SAEX | B656: 5112963746 | C656: 30.01.2026 | D656: 30.06.2026 | E656: 10337044 | F656: UNITED TEXTILE MILLS PRIVATE LIMITE | G656: 3 | H656: 8909103992507 | I656: 441857089012 | J656: KRTS-APSU26-YETKRTSCUT5008, RUST, XL | L656: EA | M656: 1 | N656: 284 | O656: 284 | Q656: 0 | R656: 0 | S656: 0 | T656: 0 | U656: 0 | V656: INR | X656: =IF(ISNUMBER(VALUE(LEFT(J656,1))),LEFT(J656,MIN(IFERROR(FIND("A",UPPER(J656)),LEN(J656)+1),IFERROR(FIND("B",UPPER(J656)),LEN(J656)+1),IFERROR(FIND("C",UPPER(J656)),LEN(J656)+1),IFERROR(FIND("D",UPPER(J656)),LEN(J656)+1),IFERROR(FIND("E",UPPER(J656)),LEN(J656)+1),IFERROR(FIND("F",UPPER(J656)),LEN(J656)+1),IFERROR(FIND("G",UPPER(J656)),LEN(J656)+1),IFERROR(FIND("H",UPPER(J656)),LEN(J656)+1),IFERROR(FIND("I",UPPER(J656)),LEN(J656)+1),IFERROR(FIND("J",UPPER(J656)),LEN(J656)+1),IFERROR(FIND("K",UPPER(J656)),LEN(J656)+1),IFERROR(FIND("L",UPPER(J656)),LEN(J656)+1),IFERROR(FIND("M",UPPER(J656)),LEN(J656)+1),IFERROR(FIND("N",UPPER(J656)),LEN(J656)+1),IFERROR(FIND("O",UPPER(J656)),LEN(J656)+1),IFERROR(FIND("P",UPPER(J656)),LEN(J656)+1),IFERROR(FIND("Q",UPPER(J656)),LEN(J656)+1),IFERROR(FIND("R",UPPER(J656)),LEN(J656)+1),IFERROR(FIND("S",UPPER(J656)),LEN(J656)+1),IFERROR(FIND("T",UPPER(J656)),LEN(J656)+1),IFERROR(FIND("U",UPPER(J656)),LEN(J656)+1),IFERROR(FIND("V",UPPER(J656)),LEN(J656)+1),IFERROR(FIND("W",UPPER(J656)),LEN(J656)+1),IFERROR(FIND("X",UPPER(J656)),LEN(J656)+1),IFERROR(FIND("Y",UPPER(J656)),LEN(J656)+1),IFERROR(FIND("Z",UPPER(J656)),LEN(J656)+1))-1),LEFT(TEXT(I656,"0"),LEN(TEXT(I656,"0"))-3)) -> 441857089 | Y656: =IF(ISNUMBER(SEARCH("(RP)",J656)),"RP","DC") -> DC | Z656: =IF(ISNUMBER(SEARCH("(RP)",J656)),O656,IF(RIGHT(TRIM(J656),3)=", S",O656,0)) -> 0 | AA656: =IF(ISNUMBER(SEARCH("(RP)",J656)),O656,IF(RIGHT(TRIM(J656),3)=", M",O656,0)) -> 0 | AB656: =IF(ISNUMBER(SEARCH("(RP)",J656)),O656,IF(RIGHT(TRIM(J656),3)=", L",O656,0)) -> 0 | AC656: =IF(ISNUMBER(SEARCH("(RP)",J656)),O656,IF(RIGHT(TRIM(J656),4)=", XL",O656,0)) -> 284 | AD656: =IF(ISNUMBER(SEARCH("(RP)",J656)),O656,IF(OR(RIGHT(TRIM(J656),5)=", XXL",RIGHT(TRIM(J656),5)=", 2XL"),O656,0)) -> 0 | AE656: {=IFERROR(_xlfn.XLOOKUP(H656,Sheet1!$G:$G,Sheet1!$F:$F),IFERROR(_xlfn.XLOOKUP(1,(--($X$2:$X$1074=X656))*(--ISNUMBER(MATCH($H$2:$H$1074,Sheet1!$G:$G,0))),_xlfn.XLOOKUP($H$2:$H$1074,Sheet1!$G:$G,Sheet1!$F:$F,"")),"NOT FOUND"))} -> YETKRTSCUT5008 | AF656: =IFERROR(IF(ISNUMBER(SEARCH("(RP)",J656)),TRIM(SUBSTITUTE(MID(J656,10,LEN(J656)),"(RP)","")),TRIM(MID(J656,FIND(",",J656)+1,FIND(",",J656,FIND(",",J656)+1)-FIND(",",J656)-1))),"") -> RUST | AG656: =IF(A656="SZAF","Bangalore",IF(A656="SAEX","JHAJJAR",IF(A656="S0EU","HARIPAL",""))) -> JHAJJAR | AH656: =IF(OR(J656="",AE656="",AE656="NOT FOUND"),"",IF(Y656="RP",IFERROR(LEFT(_xlfn.XLOOKUP(AE656,Sheet1!$F:$F,Sheet1!$W:$W),FIND("-",_xlfn.XLOOKUP(AE656,Sheet1!$F:$F,Sheet1!$W:$W),FIND("-",_xlfn.XLOOKUP(AE656,Sheet1!$F:$F,Sheet1!$W:$W))+1))&AE656,"NOT FOUND"),LEFT(J656,FIND("-",J656,FIND("-",J656)+1))&AE656)) -> KRTS-APSU26-YETKRTSCUT5008
A657: SAEX | B657: 5112963746 | C657: 30.01.2026 | D657: 30.06.2026 | E657: 10337044 | F657: UNITED TEXTILE MILLS PRIVATE LIMITE | G657: 4 | H657: 8909103992491 | I657: 441857089013 | J657: KRTS-APSU26-YETKRTSCUT5008, RUST, L | L657: EA | M657: 1 | N657: 284 | O657: 284 | Q657: 0 | R657: 0 | S657: 0 | T657: 0 | U657: 0 | V657: INR | X657: =IF(ISNUMBER(VALUE(LEFT(J657,1))),LEFT(J657,MIN(IFERROR(FIND("A",UPPER(J657)),LEN(J657)+1),IFERROR(FIND("B",UPPER(J657)),LEN(J657)+1),IFERROR(FIND("C",UPPER(J657)),LEN(J657)+1),IFERROR(FIND("D",UPPER(J657)),LEN(J657)+1),IFERROR(FIND("E",UPPER(J657)),LEN(J657)+1),IFERROR(FIND("F",UPPER(J657)),LEN(J657)+1),IFERROR(FIND("G",UPPER(J657)),LEN(J657)+1),IFERROR(FIND("H",UPPER(J657)),LEN(J657)+1),IFERROR(FIND("I",UPPER(J657)),LEN(J657)+1),IFERROR(FIND("J",UPPER(J657)),LEN(J657)+1),IFERROR(FIND("K",UPPER(J657)),LEN(J657)+1),IFERROR(FIND("L",UPPER(J657)),LEN(J657)+1),IFERROR(FIND("M",UPPER(J657)),LEN(J657)+1),IFERROR(FIND("N",UPPER(J657)),LEN(J657)+1),IFERROR(FIND("O",UPPER(J657)),LEN(J657)+1),IFERROR(FIND("P",UPPER(J657)),LEN(J657)+1),IFERROR(FIND("Q",UPPER(J657)),LEN(J657)+1),IFERROR(FIND("R",UPPER(J657)),LEN(J657)+1),IFERROR(FIND("S",UPPER(J657)),LEN(J657)+1),IFERROR(FIND("T",UPPER(J657)),LEN(J657)+1),IFERROR(FIND("U",UPPER(J657)),LEN(J657)+1),IFERROR(FIND("V",UPPER(J657)),LEN(J657)+1),IFERROR(FIND("W",UPPER(J657)),LEN(J657)+1),IFERROR(FIND("X",UPPER(J657)),LEN(J657)+1),IFERROR(FIND("Y",UPPER(J657)),LEN(J657)+1),IFERROR(FIND("Z",UPPER(J657)),LEN(J657)+1))-1),LEFT(TEXT(I657,"0"),LEN(TEXT(I657,"0"))-3)) -> 441857089 | Y657: =IF(ISNUMBER(SEARCH("(RP)",J657)),"RP","DC") -> DC | Z657: =IF(ISNUMBER(SEARCH("(RP)",J657)),O657,IF(RIGHT(TRIM(J657),3)=", S",O657,0)) -> 0 | AA657: =IF(ISNUMBER(SEARCH("(RP)",J657)),O657,IF(RIGHT(TRIM(J657),3)=", M",O657,0)) -> 0 | AB657: =IF(ISNUMBER(SEARCH("(RP)",J657)),O657,IF(RIGHT(TRIM(J657),3)=", L",O657,0)) -> 284 | AC657: =IF(ISNUMBER(SEARCH("(RP)",J657)),O657,IF(RIGHT(TRIM(J657),4)=", XL",O657,0)) -> 0 | AD657: =IF(ISNUMBER(SEARCH("(RP)",J657)),O657,IF(OR(RIGHT(TRIM(J657),5)=", XXL",RIGHT(TRIM(J657),5)=", 2XL"),O657,0)) -> 0 | AE657: {=IFERROR(_xlfn.XLOOKUP(H657,Sheet1!$G:$G,Sheet1!$F:$F),IFERROR(_xlfn.XLOOKUP(1,(--($X$2:$X$1074=X657))*(--ISNUMBER(MATCH($H$2:$H$1074,Sheet1!$G:$G,0))),_xlfn.XLOOKUP($H$2:$H$1074,Sheet1!$G:$G,Sheet1!$F:$F,"")),"NOT FOUND"))} -> YETKRTSCUT5008 | AF657: =IFERROR(IF(ISNUMBER(SEARCH("(RP)",J657)),TRIM(SUBSTITUTE(MID(J657,10,LEN(J657)),"(RP)","")),TRIM(MID(J657,FIND(",",J657)+1,FIND(",",J657,FIND(",",J657)+1)-FIND(",",J657)-1))),"") -> RUST | AG657: =IF(A657="SZAF","Bangalore",IF(A657="SAEX","JHAJJAR",IF(A657="S0EU","HARIPAL",""))) -> JHAJJAR | AH657: =IF(OR(J657="",AE657="",AE657="NOT FOUND"),"",IF(Y657="RP",IFERROR(LEFT(_xlfn.XLOOKUP(AE657,Sheet1!$F:$F,Sheet1!$W:$W),FIND("-",_xlfn.XLOOKUP(AE657,Sheet1!$F:$F,Sheet1!$W:$W),FIND("-",_xlfn.XLOOKUP(AE657,Sheet1!$F:$F,Sheet1!$W:$W))+1))&AE657,"NOT FOUND"),LEFT(J657,FIND("-",J657,FIND("-",J657)+1))&AE657)) -> KRTS-APSU26-YETKRTSCUT5008
A658: SAEX | B658: 5112963746 | C658: 30.01.2026 | D658: 30.06.2026 | E658: 10337044 | F658: UNITED TEXTILE MILLS PRIVATE LIMITE | G658: 5 | H658: 8909103992484 | I658: 441857089014 | J658: KRTS-APSU26-YETKRTSCUT5008, RUST, M | L658: EA | M658: 1 | N658: 284 | O658: 284 | Q658: 0 | R658: 0 | S658: 0 | T658: 0 | U658: 0 | V658: INR | X658: =IF(ISNUMBER(VALUE(LEFT(J658,1))),LEFT(J658,MIN(IFERROR(FIND("A",UPPER(J658)),LEN(J658)+1),IFERROR(FIND("B",UPPER(J658)),LEN(J658)+1),IFERROR(FIND("C",UPPER(J658)),LEN(J658)+1),IFERROR(FIND("D",UPPER(J658)),LEN(J658)+1),IFERROR(FIND("E",UPPER(J658)),LEN(J658)+1),IFERROR(FIND("F",UPPER(J658)),LEN(J658)+1),IFERROR(FIND("G",UPPER(J658)),LEN(J658)+1),IFERROR(FIND("H",UPPER(J658)),LEN(J658)+1),IFERROR(FIND("I",UPPER(J658)),LEN(J658)+1),IFERROR(FIND("J",UPPER(J658)),LEN(J658)+1),IFERROR(FIND("K",UPPER(J658)),LEN(J658)+1),IFERROR(FIND("L",UPPER(J658)),LEN(J658)+1),IFERROR(FIND("M",UPPER(J658)),LEN(J658)+1),IFERROR(FIND("N",UPPER(J658)),LEN(J658)+1),IFERROR(FIND("O",UPPER(J658)),LEN(J658)+1),IFERROR(FIND("P",UPPER(J658)),LEN(J658)+1),IFERROR(FIND("Q",UPPER(J658)),LEN(J658)+1),IFERROR(FIND("R",UPPER(J658)),LEN(J658)+1),IFERROR(FIND("S",UPPER(J658)),LEN(J658)+1),IFERROR(FIND("T",UPPER(J658)),LEN(J658)+1),IFERROR(FIND("U",UPPER(J658)),LEN(J658)+1),IFERROR(FIND("V",UPPER(J658)),LEN(J658)+1),IFERROR(FIND("W",UPPER(J658)),LEN(J658)+1),IFERROR(FIND("X",UPPER(J658)),LEN(J658)+1),IFERROR(FIND("Y",UPPER(J658)),LEN(J658)+1),IFERROR(FIND("Z",UPPER(J658)),LEN(J658)+1))-1),LEFT(TEXT(I658,"0"),LEN(TEXT(I658,"0"))-3)) -> 441857089 | Y658: =IF(ISNUMBER(SEARCH("(RP)",J658)),"RP","DC") -> DC | Z658: =IF(ISNUMBER(SEARCH("(RP)",J658)),O658,IF(RIGHT(TRIM(J658),3)=", S",O658,0)) -> 0 | AA658: =IF(ISNUMBER(SEARCH("(RP)",J658)),O658,IF(RIGHT(TRIM(J658),3)=", M",O658,0)) -> 284 | AB658: =IF(ISNUMBER(SEARCH("(RP)",J658)),O658,IF(RIGHT(TRIM(J658),3)=", L",O658,0)) -> 0 | AC658: =IF(ISNUMBER(SEARCH("(RP)",J658)),O658,IF(RIGHT(TRIM(J658),4)=", XL",O658,0)) -> 0 | AD658: =IF(ISNUMBER(SEARCH("(RP)",J658)),O658,IF(OR(RIGHT(TRIM(J658),5)=", XXL",RIGHT(TRIM(J658),5)=", 2XL"),O658,0)) -> 0 | AE658: {=IFERROR(_xlfn.XLOOKUP(H658,Sheet1!$G:$G,Sheet1!$F:$F),IFERROR(_xlfn.XLOOKUP(1,(--($X$2:$X$1074=X658))*(--ISNUMBER(MATCH($H$2:$H$1074,Sheet1!$G:$G,0))),_xlfn.XLOOKUP($H$2:$H$1074,Sheet1!$G:$G,Sheet1!$F:$F,"")),"NOT FOUND"))} -> YETKRTSCUT5008 | AF658: =IFERROR(IF(ISNUMBER(SEARCH("(RP)",J658)),TRIM(SUBSTITUTE(MID(J658,10,LEN(J658)),"(RP)","")),TRIM(MID(J658,FIND(",",J658)+1,FIND(",",J658,FIND(",",J658)+1)-FIND(",",J658)-1))),"") -> RUST | AG658: =IF(A658="SZAF","Bangalore",IF(A658="SAEX","JHAJJAR",IF(A658="S0EU","HARIPAL",""))) -> JHAJJAR | AH658: =IF(OR(J658="",AE658="",AE658="NOT FOUND"),"",IF(Y658="RP",IFERROR(LEFT(_xlfn.XLOOKUP(AE658,Sheet1!$F:$F,Sheet1!$W:$W),FIND("-",_xlfn.XLOOKUP(AE658,Sheet1!$F:$F,Sheet1!$W:$W),FIND("-",_xlfn.XLOOKUP(AE658,Sheet1!$F:$F,Sheet1!$W:$W))+1))&AE658,"NOT FOUND"),LEFT(J658,FIND("-",J658,FIND("-",J658)+1))&AE658)) -> KRTS-APSU26-YETKRTSCUT5008
A659: SAEX | B659: 5112963746 | C659: 30.01.2026 | D659: 30.06.2026 | E659: 10337044 | F659: UNITED TEXTILE MILLS PRIVATE LIMITE | G659: 6 | H659: 8909103992477 | I659: 441857089015 | J659: KRTS-APSU26-YETKRTSCUT5008, RUST, S | L659: EA | M659: 1 | N659: 284 | O659: 284 | Q659: 0 | R659: 0 | S659: 0 | T659: 0 | U659: 0 | X659: =IF(ISNUMBER(VALUE(LEFT(J659,1))),LEFT(J659,MIN(IFERROR(FIND("A",UPPER(J659)),LEN(J659)+1),IFERROR(FIND("B",UPPER(J659)),LEN(J659)+1),IFERROR(FIND("C",UPPER(J659)),LEN(J659)+1),IFERROR(FIND("D",UPPER(J659)),LEN(J659)+1),IFERROR(FIND("E",UPPER(J659)),LEN(J659)+1),IFERROR(FIND("F",UPPER(J659)),LEN(J659)+1),IFERROR(FIND("G",UPPER(J659)),LEN(J659)+1),IFERROR(FIND("H",UPPER(J659)),LEN(J659)+1),IFERROR(FIND("I",UPPER(J659)),LEN(J659)+1),IFERROR(FIND("J",UPPER(J659)),LEN(J659)+1),IFERROR(FIND("K",UPPER(J659)),LEN(J659)+1),IFERROR(FIND("L",UPPER(J659)),LEN(J659)+1),IFERROR(FIND("M",UPPER(J659)),LEN(J659)+1),IFERROR(FIND("N",UPPER(J659)),LEN(J659)+1),IFERROR(FIND("O",UPPER(J659)),LEN(J659)+1),IFERROR(FIND("P",UPPER(J659)),LEN(J659)+1),IFERROR(FIND("Q",UPPER(J659)),LEN(J659)+1),IFERROR(FIND("R",UPPER(J659)),LEN(J659)+1),IFERROR(FIND("S",UPPER(J659)),LEN(J659)+1),IFERROR(FIND("T",UPPER(J659)),LEN(J659)+1),IFERROR(FIND("U",UPPER(J659)),LEN(J659)+1),IFERROR(FIND("V",UPPER(J659)),LEN(J659)+1),IFERROR(FIND("W",UPPER(J659)),LEN(J659)+1),IFERROR(FIND("X",UPPER(J659)),LEN(J659)+1),IFERROR(FIND("Y",UPPER(J659)),LEN(J659)+1),IFERROR(FIND("Z",UPPER(J659)),LEN(J659)+1))-1),LEFT(TEXT(I659,"0"),LEN(TEXT(I659,"0"))-3)) -> 441857089 | Y659: =IF(ISNUMBER(SEARCH("(RP)",J659)),"RP","DC") -> DC | Z659: =IF(ISNUMBER(SEARCH("(RP)",J659)),O659,IF(RIGHT(TRIM(J659),3)=", S",O659,0)) -> 284 | AA659: =IF(ISNUMBER(SEARCH("(RP)",J659)),O659,IF(RIGHT(TRIM(J659),3)=", M",O659,0)) -> 0 | AB659: =IF(ISNUMBER(SEARCH("(RP)",J659)),O659,IF(RIGHT(TRIM(J659),3)=", L",O659,0)) -> 0 | AC659: =IF(ISNUMBER(SEARCH("(RP)",J659)),O659,IF(RIGHT(TRIM(J659),4)=", XL",O659,0)) -> 0 | AD659: =IF(ISNUMBER(SEARCH("(RP)",J659)),O659,IF(OR(RIGHT(TRIM(J659),5)=", XXL",RIGHT(TRIM(J659),5)=", 2XL"),O659,0)) -> 0 | AE659: {=IFERROR(_xlfn.XLOOKUP(H659,Sheet1!$G:$G,Sheet1!$F:$F),IFERROR(_xlfn.XLOOKUP(1,(--($X$2:$X$1074=X659))*(--ISNUMBER(MATCH($H$2:$H$1074,Sheet1!$G:$G,0))),_xlfn.XLOOKUP($H$2:$H$1074,Sheet1!$G:$G,Sheet1!$F:$F,"")),"NOT FOUND"))} -> YETKRTSCUT5008 | AF659: =IFERROR(IF(ISNUMBER(SEARCH("(RP)",J659)),TRIM(SUBSTITUTE(MID(J659,10,LEN(J659)),"(RP)","")),TRIM(MID(J659,FIND(",",J659)+1,FIND(",",J659,FIND(",",J659)+1)-FIND(",",J659)-1))),"") -> RUST | AG659: =IF(A659="SZAF","Bangalore",IF(A659="SAEX","JHAJJAR",IF(A659="S0EU","HARIPAL",""))) -> JHAJJAR | AH659: =IF(OR(J659="",AE659="",AE659="NOT FOUND"),"",IF(Y659="RP",IFERROR(LEFT(_xlfn.XLOOKUP(AE659,Sheet1!$F:$F,Sheet1!$W:$W),FIND("-",_xlfn.XLOOKUP(AE659,Sheet1!$F:$F,Sheet1!$W:$W),FIND("-",_xlfn.XLOOKUP(AE659,Sheet1!$F:$F,Sheet1!$W:$W))+1))&AE659,"NOT FOUND"),LEFT(J659,FIND("-",J659,FIND("-",J659)+1))&AE659)) -> KRTS-APSU26-YETKRTSCUT5008
A660: S0EU | B660: 5112963728 | C660: 30.01.2026 | D660: 20.05.2026 | E660: 10337044 | F660: UNITED TEXTILE MILLS PRIVATE LIMITE | G660: 1 | H660: 8909103992583 | I660: 494758187 | J660: 441857089 MUSTARD(RP) | L660: EA | M660: 1 | N660: 253 | O660: 253 | Q660: 1221.5 | R660: 1221.5 | S660: 15451.98 | T660: 309039.5 | U660: 5 | V660: INR | X660: =IF(ISNUMBER(VALUE(LEFT(J660,1))),LEFT(J660,MIN(IFERROR(FIND("A",UPPER(J660)),LEN(J660)+1),IFERROR(FIND("B",UPPER(J660)),LEN(J660)+1),IFERROR(FIND("C",UPPER(J660)),LEN(J660)+1),IFERROR(FIND("D",UPPER(J660)),LEN(J660)+1),IFERROR(FIND("E",UPPER(J660)),LEN(J660)+1),IFERROR(FIND("F",UPPER(J660)),LEN(J660)+1),IFERROR(FIND("G",UPPER(J660)),LEN(J660)+1),IFERROR(FIND("H",UPPER(J660)),LEN(J660)+1),IFERROR(FIND("I",UPPER(J660)),LEN(J660)+1),IFERROR(FIND("J",UPPER(J660)),LEN(J660)+1),IFERROR(FIND("K",UPPER(J660)),LEN(J660)+1),IFERROR(FIND("L",UPPER(J660)),LEN(J660)+1),IFERROR(FIND("M",UPPER(J660)),LEN(J660)+1),IFERROR(FIND("N",UPPER(J660)),LEN(J660)+1),IFERROR(FIND("O",UPPER(J660)),LEN(J660)+1),IFERROR(FIND("P",UPPER(J660)),LEN(J660)+1),IFERROR(FIND("Q",UPPER(J660)),LEN(J660)+1),IFERROR(FIND("R",UPPER(J660)),LEN(J660)+1),IFERROR(FIND("S",UPPER(J660)),LEN(J660)+1),IFERROR(FIND("T",UPPER(J660)),LEN(J660)+1),IFERROR(FIND("U",UPPER(J660)),LEN(J660)+1),IFERROR(FIND("V",UPPER(J660)),LEN(J660)+1),IFERROR(FIND("W",UPPER(J660)),LEN(J660)+1),IFERROR(FIND("X",UPPER(J660)),LEN(J660)+1),IFERROR(FIND("Y",UPPER(J660)),LEN(J660)+1),IFERROR(FIND("Z",UPPER(J660)),LEN(J660)+1))-1),LEFT(TEXT(I660,"0"),LEN(TEXT(I660,"0"))-3)) -> 441857089 | Y660: =IF(ISNUMBER(SEARCH("(RP)",J660)),"RP","DC") -> RP | Z660: =IF(ISNUMBER(SEARCH("(RP)",J660)),O660,IF(RIGHT(TRIM(J660),3)=", S",O660,0)) -> 253 | AA660: =IF(ISNUMBER(SEARCH("(RP)",J660)),O660,IF(RIGHT(TRIM(J660),3)=", M",O660,0)) -> 253 | AB660: =IF(ISNUMBER(SEARCH("(RP)",J660)),O660,IF(RIGHT(TRIM(J660),3)=", L",O660,0)) -> 253 | AC660: =IF(ISNUMBER(SEARCH("(RP)",J660)),O660,IF(RIGHT(TRIM(J660),4)=", XL",O660,0)) -> 253 | AD660: =IF(ISNUMBER(SEARCH("(RP)",J660)),O660,IF(OR(RIGHT(TRIM(J660),5)=", XXL",RIGHT(TRIM(J660),5)=", 2XL"),O660,0)) -> 253 | AE660: {=IFERROR(_xlfn.XLOOKUP(H660,Sheet1!$G:$G,Sheet1!$F:$F),IFERROR(_xlfn.XLOOKUP(1,(--($X$2:$X$1074=X660))*(--ISNUMBER(MATCH($H$2:$H$1074,Sheet1!$G:$G,0))),_xlfn.XLOOKUP($H$2:$H$1074,Sheet1!$G:$G,Sheet1!$F:$F,"")),"NOT FOUND"))} -> YETKRTSCUT5008 | AF660: =IFERROR(IF(ISNUMBER(SEARCH("(RP)",J660)),TRIM(SUBSTITUTE(MID(J660,10,LEN(J660)),"(RP)","")),TRIM(MID(J660,FIND(",",J660)+1,FIND(",",J660,FIND(",",J660)+1)-FIND(",",J660)-1))),"") -> MUSTARD | AG660: =IF(A660="SZAF","Bangalore",IF(A660="SAEX","JHAJJAR",IF(A660="S0EU","HARIPAL",""))) -> HARIPAL | AH660: =IF(OR(J660="",AE660="",AE660="NOT FOUND"),"",IF(Y660="RP",IFERROR(LEFT(_xlfn.XLOOKUP(AE660,Sheet1!$F:$F,Sheet1!$W:$W),FIND("-",_xlfn.XLOOKUP(AE660,Sheet1!$F:$F,Sheet1!$W:$W),FIND("-",_xlfn.XLOOKUP(AE660,Sheet1!$F:$F,Sheet1!$W:$W))+1))&AE660,"NOT FOUND"),LEFT(J660,FIND("-",J660,FIND("-",J660)+1))&AE660)) -> KRTS-APSU26-YETKRTSCUT5008
A661: S0EU | B661: 5112963727 | C661: 30.01.2026 | D661: 20.05.2026 | E661: 10337044 | F661: UNITED TEXTILE MILLS PRIVATE LIMITE | G661: 1 | H661: 8909103992576 | I661: 494758186 | J661: 441857089 FUCHSIA(RP) | L661: EA | M661: 1 | N661: 236 | O661: 236 | Q661: 1221.5 | R661: 1221.5 | S661: 14413.7 | T661: 288274 | U661: 5 | V661: INR | X661: =IF(ISNUMBER(VALUE(LEFT(J661,1))),LEFT(J661,MIN(IFERROR(FIND("A",UPPER(J661)),LEN(J661)+1),IFERROR(FIND("B",UPPER(J661)),LEN(J661)+1),IFERROR(FIND("C",UPPER(J661)),LEN(J661)+1),IFERROR(FIND("D",UPPER(J661)),LEN(J661)+1),IFERROR(FIND("E",UPPER(J661)),LEN(J661)+1),IFERROR(FIND("F",UPPER(J661)),LEN(J661)+1),IFERROR(FIND("G",UPPER(J661)),LEN(J661)+1),IFERROR(FIND("H",UPPER(J661)),LEN(J661)+1),IFERROR(FIND("I",UPPER(J661)),LEN(J661)+1),IFERROR(FIND("J",UPPER(J661)),LEN(J661)+1),IFERROR(FIND("K",UPPER(J661)),LEN(J661)+1),IFERROR(FIND("L",UPPER(J661)),LEN(J661)+1),IFERROR(FIND("M",UPPER(J661)),LEN(J661)+1),IFERROR(FIND("N",UPPER(J661)),LEN(J661)+1),IFERROR(FIND("O",UPPER(J661)),LEN(J661)+1),IFERROR(FIND("P",UPPER(J661)),LEN(J661)+1),IFERROR(FIND("Q",UPPER(J661)),LEN(J661)+1),IFERROR(FIND("R",UPPER(J661)),LEN(J661)+1),IFERROR(FIND("S",UPPER(J661)),LEN(J661)+1),IFERROR(FIND("T",UPPER(J661)),LEN(J661)+1),IFERROR(FIND("U",UPPER(J661)),LEN(J661)+1),IFERROR(FIND("V",UPPER(J661)),LEN(J661)+1),IFERROR(FIND("W",UPPER(J661)),LEN(J661)+1),IFERROR(FIND("X",UPPER(J661)),LEN(J661)+1),IFERROR(FIND("Y",UPPER(J661)),LEN(J661)+1),IFERROR(FIND("Z",UPPER(J661)),LEN(J661)+1))-1),LEFT(TEXT(I661,"0"),LEN(TEXT(I661,"0"))-3)) -> 441857089 | Y661: =IF(ISNUMBER(SEARCH("(RP)",J661)),"RP","DC") -> RP | Z661: =IF(ISNUMBER(SEARCH("(RP)",J661)),O661,IF(RIGHT(TRIM(J661),3)=", S",O661,0)) -> 236 | AA661: =IF(ISNUMBER(SEARCH("(RP)",J661)),O661,IF(RIGHT(TRIM(J661),3)=", M",O661,0)) -> 236 | AB661: =IF(ISNUMBER(SEARCH("(RP)",J661)),O661,IF(RIGHT(TRIM(J661),3)=", L",O661,0)) -> 236 | AC661: =IF(ISNUMBER(SEARCH("(RP)",J661)),O661,IF(RIGHT(TRIM(J661),4)=", XL",O661,0)) -> 236 | AD661: =IF(ISNUMBER(SEARCH("(RP)",J661)),O661,IF(OR(RIGHT(TRIM(J661),5)=", XXL",RIGHT(TRIM(J661),5)=", 2XL"),O661,0)) -> 236 | AE661: {=IFERROR(_xlfn.XLOOKUP(H661,Sheet1!$G:$G,Sheet1!$F:$F),IFERROR(_xlfn.XLOOKUP(1,(--($X$2:$X$1074=X661))*(--ISNUMBER(MATCH($H$2:$H$1074,Sheet1!$G:$G,0))),_xlfn.XLOOKUP($H$2:$H$1074,Sheet1!$G:$G,Sheet1!$F:$F,"")),"NOT FOUND"))} -> YETKRTSCUT5008 | AF661: =IFERROR(IF(ISNUMBER(SEARCH("(RP)",J661)),TRIM(SUBSTITUTE(MID(J661,10,LEN(J661)),"(RP)","")),TRIM(MID(J661,FIND(",",J661)+1,FIND(",",J661,FIND(",",J661)+1)-FIND(",",J661)-1))),"") -> FUCHSIA | AG661: =IF(A661="SZAF","Bangalore",IF(A661="SAEX","JHAJJAR",IF(A661="S0EU","HARIPAL",""))) -> HARIPAL | AH661: =IF(OR(J661="",AE661="",AE661="NOT FOUND"),"",IF(Y661="RP",IFERROR(LEFT(_xlfn.XLOOKUP(AE661,Sheet1!$F:$F,Sheet1!$W:$W),FIND("-",_xlfn.XLOOKUP(AE661,Sheet1!$F:$F,Sheet1!$W:$W),FIND("-",_xlfn.XLOOKUP(AE661,Sheet1!$F:$F,Sheet1!$W:$W))+1))&AE661,"NOT FOUND"),LEFT(J661,FIND("-",J661,FIND("-",J661)+1))&AE661)) -> KRTS-APSU26-YETKRTSCUT5008
A662: S0EU | B662: 5112963726 | C662: 30.01.2026 | D662: 20.05.2026 | E662: 10337044 | F662: UNITED TEXTILE MILLS PRIVATE LIMITE | G662: 1 | H662: 8909103992613 | I662: 494758190 | J662: 441857089 SAGE GREEN(RP) | L662: EA | M662: 1 | N662: 236 | O662: 236 | Q662: 1221.5 | R662: 1221.5 | S662: 14413.7 | T662: 288274 | U662: 5 | V662: INR | X662: =IF(ISNUMBER(VALUE(LEFT(J662,1))),LEFT(J662,MIN(IFERROR(FIND("A",UPPER(J662)),LEN(J662)+1),IFERROR(FIND("B",UPPER(J662)),LEN(J662)+1),IFERROR(FIND("C",UPPER(J662)),LEN(J662)+1),IFERROR(FIND("D",UPPER(J662)),LEN(J662)+1),IFERROR(FIND("E",UPPER(J662)),LEN(J662)+1),IFERROR(FIND("F",UPPER(J662)),LEN(J662)+1),IFERROR(FIND("G",UPPER(J662)),LEN(J662)+1),IFERROR(FIND("H",UPPER(J662)),LEN(J662)+1),IFERROR(FIND("I",UPPER(J662)),LEN(J662)+1),IFERROR(FIND("J",UPPER(J662)),LEN(J662)+1),IFERROR(FIND("K",UPPER(J662)),LEN(J662)+1),IFERROR(FIND("L",UPPER(J662)),LEN(J662)+1),IFERROR(FIND("M",UPPER(J662)),LEN(J662)+1),IFERROR(FIND("N",UPPER(J662)),LEN(J662)+1),IFERROR(FIND("O",UPPER(J662)),LEN(J662)+1),IFERROR(FIND("P",UPPER(J662)),LEN(J662)+1),IFERROR(FIND("Q",UPPER(J662)),LEN(J662)+1),IFERROR(FIND("R",UPPER(J662)),LEN(J662)+1),IFERROR(FIND("S",UPPER(J662)),LEN(J662)+1),IFERROR(FIND("T",UPPER(J662)),LEN(J662)+1),IFERROR(FIND("U",UPPER(J662)),LEN(J662)+1),IFERROR(FIND("V",UPPER(J662)),LEN(J662)+1),IFERROR(FIND("W",UPPER(J662)),LEN(J662)+1),IFERROR(FIND("X",UPPER(J662)),LEN(J662)+1),IFERROR(FIND("Y",UPPER(J662)),LEN(J662)+1),IFERROR(FIND("Z",UPPER(J662)),LEN(J662)+1))-1),LEFT(TEXT(I662,"0"),LEN(TEXT(I662,"0"))-3)) -> 441857089 | Y662: =IF(ISNUMBER(SEARCH("(RP)",J662)),"RP","DC") -> RP | Z662: =IF(ISNUMBER(SEARCH("(RP)",J662)),O662,IF(RIGHT(TRIM(J662),3)=", S",O662,0)) -> 236 | AA662: =IF(ISNUMBER(SEARCH("(RP)",J662)),O662,IF(RIGHT(TRIM(J662),3)=", M",O662,0)) -> 236 | AB662: =IF(ISNUMBER(SEARCH("(RP)",J662)),O662,IF(RIGHT(TRIM(J662),3)=", L",O662,0)) -> 236 | AC662: =IF(ISNUMBER(SEARCH("(RP)",J662)),O662,IF(RIGHT(TRIM(J662),4)=", XL",O662,0)) -> 236 | AD662: =IF(ISNUMBER(SEARCH("(RP)",J662)),O662,IF(OR(RIGHT(TRIM(J662),5)=", XXL",RIGHT(TRIM(J662),5)=", 2XL"),O662,0)) -> 236 | AE662: {=IFERROR(_xlfn.XLOOKUP(H662,Sheet1!$G:$G,Sheet1!$F:$F),IFERROR(_xlfn.XLOOKUP(1,(--($X$2:$X$1074=X662))*(--ISNUMBER(MATCH($H$2:$H$1074,Sheet1!$G:$G,0))),_xlfn.XLOOKUP($H$2:$H$1074,Sheet1!$G:$G,Sheet1!$F:$F,"")),"NOT FOUND"))} -> YETKRTSCUT5008 | AF662: =IFERROR(IF(ISNUMBER(SEARCH("(RP)",J662)),TRIM(SUBSTITUTE(MID(J662,10,LEN(J662)),"(RP)","")),TRIM(MID(J662,FIND(",",J662)+1,FIND(",",J662,FIND(",",J662)+1)-FIND(",",J662)-1))),"") -> SAGE GREEN | AG662: =IF(A662="SZAF","Bangalore",IF(A662="SAEX","JHAJJAR",IF(A662="S0EU","HARIPAL",""))) -> HARIPAL | AH662: =IF(OR(J662="",AE662="",AE662="NOT FOUND"),"",IF(Y662="RP",IFERROR(LEFT(_xlfn.XLOOKUP(AE662,Sheet1!$F:$F,Sheet1!$W:$W),FIND("-",_xlfn.XLOOKUP(AE662,Sheet1!$F:$F,Sheet1!$W:$W),FIND("-",_xlfn.XLOOKUP(AE662,Sheet1!$F:$F,Sheet1!$W:$W))+1))&AE662,"NOT FOUND"),LEFT(J662,FIND("-",J662,FIND("-",J662)+1))&AE662)) -> KRTS-APSU26-YETKRTSCUT5008
A663: S0EU | B663: 5112963725 | C663: 30.01.2026 | D663: 30.06.2026 | E663: 10337044 | F663: UNITED TEXTILE MILLS PRIVATE LIMITE | G663: 1 | H663: 8909103992590 | I663: 494758188 | J663: 441857089 OFF WHITE(RP) | L663: EA | M663: 1 | N663: 269 | O663: 269 | Q663: 1221.5 | R663: 1221.5 | S663: 16429.18 | T663: 328583.5 | U663: 5 | V663: INR | X663: =IF(ISNUMBER(VALUE(LEFT(J663,1))),LEFT(J663,MIN(IFERROR(FIND("A",UPPER(J663)),LEN(J663)+1),IFERROR(FIND("B",UPPER(J663)),LEN(J663)+1),IFERROR(FIND("C",UPPER(J663)),LEN(J663)+1),IFERROR(FIND("D",UPPER(J663)),LEN(J663)+1),IFERROR(FIND("E",UPPER(J663)),LEN(J663)+1),IFERROR(FIND("F",UPPER(J663)),LEN(J663)+1),IFERROR(FIND("G",UPPER(J663)),LEN(J663)+1),IFERROR(FIND("H",UPPER(J663)),LEN(J663)+1),IFERROR(FIND("I",UPPER(J663)),LEN(J663)+1),IFERROR(FIND("J",UPPER(J663)),LEN(J663)+1),IFERROR(FIND("K",UPPER(J663)),LEN(J663)+1),IFERROR(FIND("L",UPPER(J663)),LEN(J663)+1),IFERROR(FIND("M",UPPER(J663)),LEN(J663)+1),IFERROR(FIND("N",UPPER(J663)),LEN(J663)+1),IFERROR(FIND("O",UPPER(J663)),LEN(J663)+1),IFERROR(FIND("P",UPPER(J663)),LEN(J663)+1),IFERROR(FIND("Q",UPPER(J663)),LEN(J663)+1),IFERROR(FIND("R",UPPER(J663)),LEN(J663)+1),IFERROR(FIND("S",UPPER(J663)),LEN(J663)+1),IFERROR(FIND("T",UPPER(J663)),LEN(J663)+1),IFERROR(FIND("U",UPPER(J663)),LEN(J663)+1),IFERROR(FIND("V",UPPER(J663)),LEN(J663)+1),IFERROR(FIND("W",UPPER(J663)),LEN(J663)+1),IFERROR(FIND("X",UPPER(J663)),LEN(J663)+1),IFERROR(FIND("Y",UPPER(J663)),LEN(J663)+1),IFERROR(FIND("Z",UPPER(J663)),LEN(J663)+1))-1),LEFT(TEXT(I663,"0"),LEN(TEXT(I663,"0"))-3)) -> 441857089 | Y663: =IF(ISNUMBER(SEARCH("(RP)",J663)),"RP","DC") -> RP | Z663: =IF(ISNUMBER(SEARCH("(RP)",J663)),O663,IF(RIGHT(TRIM(J663),3)=", S",O663,0)) -> 269 | AA663: =IF(ISNUMBER(SEARCH("(RP)",J663)),O663,IF(RIGHT(TRIM(J663),3)=", M",O663,0)) -> 269 | AB663: =IF(ISNUMBER(SEARCH("(RP)",J663)),O663,IF(RIGHT(TRIM(J663),3)=", L",O663,0)) -> 269 | AC663: =IF(ISNUMBER(SEARCH("(RP)",J663)),O663,IF(RIGHT(TRIM(J663),4)=", XL",O663,0)) -> 269 | AD663: =IF(ISNUMBER(SEARCH("(RP)",J663)),O663,IF(OR(RIGHT(TRIM(J663),5)=", XXL",RIGHT(TRIM(J663),5)=", 2XL"),O663,0)) -> 269 | AE663: {=IFERROR(_xlfn.XLOOKUP(H663,Sheet1!$G:$G,Sheet1!$F:$F),IFERROR(_xlfn.XLOOKUP(1,(--($X$2:$X$1074=X663))*(--ISNUMBER(MATCH($H$2:$H$1074,Sheet1!$G:$G,0))),_xlfn.XLOOKUP($H$2:$H$1074,Sheet1!$G:$G,Sheet1!$F:$F,"")),"NOT FOUND"))} -> YETKRTSCUT5008 | AF663: =IFERROR(IF(ISNUMBER(SEARCH("(RP)",J663)),TRIM(SUBSTITUTE(MID(J663,10,LEN(J663)),"(RP)","")),TRIM(MID(J663,FIND(",",J663)+1,FIND(",",J663,FIND(",",J663)+1)-FIND(",",J663)-1))),"") -> OFF WHITE | AG663: =IF(A663="SZAF","Bangalore",IF(A663="SAEX","JHAJJAR",IF(A663="S0EU","HARIPAL",""))) -> HARIPAL | AH663: =IF(OR(J663="",AE663="",AE663="NOT FOUND"),"",IF(Y663="RP",IFERROR(LEFT(_xlfn.XLOOKUP(AE663,Sheet1!$F:$F,Sheet1!$W:$W),FIND("-",_xlfn.XLOOKUP(AE663,Sheet1!$F:$F,Sheet1!$W:$W),FIND("-",_xlfn.XLOOKUP(AE663,Sheet1!$F:$F,Sheet1!$W:$W))+1))&AE663,"NOT FOUND"),LEFT(J663,FIND("-",J663,FIND("-",J663)+1))&AE663)) -> KRTS-APSU26-YETKRTSCUT5008
A664: S0EU | B664: 5112963725 | C664: 30.01.2026 | D664: 30.06.2026 | E664: 10337044 | F664: UNITED TEXTILE MILLS PRIVATE LIMITE | G664: 2 | H664: 8909103992460 | I664: 441857089016 | J664: KRTS-APSU26-YETKRTSCUT50, OFF WHITE, 2XL | L664: EA | M664: 1 | N664: 269 | O664: 269 | Q664: 0 | R664: 0 | S664: 0 | T664: 0 | U664: 0 | V664: INR | X664: =IF(ISNUMBER(VALUE(LEFT(J664,1))),LEFT(J664,MIN(IFERROR(FIND("A",UPPER(J664)),LEN(J664)+1),IFERROR(FIND("B",UPPER(J664)),LEN(J664)+1),IFERROR(FIND("C",UPPER(J664)),LEN(J664)+1),IFERROR(FIND("D",UPPER(J664)),LEN(J664)+1),IFERROR(FIND("E",UPPER(J664)),LEN(J664)+1),IFERROR(FIND("F",UPPER(J664)),LEN(J664)+1),IFERROR(FIND("G",UPPER(J664)),LEN(J664)+1),IFERROR(FIND("H",UPPER(J664)),LEN(J664)+1),IFERROR(FIND("I",UPPER(J664)),LEN(J664)+1),IFERROR(FIND("J",UPPER(J664)),LEN(J664)+1),IFERROR(FIND("K",UPPER(J664)),LEN(J664)+1),IFERROR(FIND("L",UPPER(J664)),LEN(J664)+1),IFERROR(FIND("M",UPPER(J664)),LEN(J664)+1),IFERROR(FIND("N",UPPER(J664)),LEN(J664)+1),IFERROR(FIND("O",UPPER(J664)),LEN(J664)+1),IFERROR(FIND("P",UPPER(J664)),LEN(J664)+1),IFERROR(FIND("Q",UPPER(J664)),LEN(J664)+1),IFERROR(FIND("R",UPPER(J664)),LEN(J664)+1),IFERROR(FIND("S",UPPER(J664)),LEN(J664)+1),IFERROR(FIND("T",UPPER(J664)),LEN(J664)+1),IFERROR(FIND("U",UPPER(J664)),LEN(J664)+1),IFERROR(FIND("V",UPPER(J664)),LEN(J664)+1),IFERROR(FIND("W",UPPER(J664)),LEN(J664)+1),IFERROR(FIND("X",UPPER(J664)),LEN(J664)+1),IFERROR(FIND("Y",UPPER(J664)),LEN(J664)+1),IFERROR(FIND("Z",UPPER(J664)),LEN(J664)+1))-1),LEFT(TEXT(I664,"0"),LEN(TEXT(I664,"0"))-3)) -> 441857089 | Y664: =IF(ISNUMBER(SEARCH("(RP)",J664)),"RP","DC") -> DC | Z664: =IF(ISNUMBER(SEARCH("(RP)",J664)),O664,IF(RIGHT(TRIM(J664),3)=", S",O664,0)) -> 0 | AA664: =IF(ISNUMBER(SEARCH("(RP)",J664)),O664,IF(RIGHT(TRIM(J664),3)=", M",O664,0)) -> 0 | AB664: =IF(ISNUMBER(SEARCH("(RP)",J664)),O664,IF(RIGHT(TRIM(J664),3)=", L",O664,0)) -> 0 | AC664: =IF(ISNUMBER(SEARCH("(RP)",J664)),O664,IF(RIGHT(TRIM(J664),4)=", XL",O664,0)) -> 0 | AD664: =IF(ISNUMBER(SEARCH("(RP)",J664)),O664,IF(OR(RIGHT(TRIM(J664),5)=", XXL",RIGHT(TRIM(J664),5)=", 2XL"),O664,0)) -> 269 | AE664: {=IFERROR(_xlfn.XLOOKUP(H664,Sheet1!$G:$G,Sheet1!$F:$F),IFERROR(_xlfn.XLOOKUP(1,(--($X$2:$X$1074=X664))*(--ISNUMBER(MATCH($H$2:$H$1074,Sheet1!$G:$G,0))),_xlfn.XLOOKUP($H$2:$H$1074,Sheet1!$G:$G,Sheet1!$F:$F,"")),"NOT FOUND"))} -> YETKRTSCUT5008 | AF664: =IFERROR(IF(ISNUMBER(SEARCH("(RP)",J664)),TRIM(SUBSTITUTE(MID(J664,10,LEN(J664)),"(RP)","")),TRIM(MID(J664,FIND(",",J664)+1,FIND(",",J664,FIND(",",J664)+1)-FIND(",",J664)-1))),"") -> OFF WHITE | AG664: =IF(A664="SZAF","Bangalore",IF(A664="SAEX","JHAJJAR",IF(A664="S0EU","HARIPAL",""))) -> HARIPAL | AH664: =IF(OR(J664="",AE664="",AE664="NOT FOUND"),"",IF(Y664="RP",IFERROR(LEFT(_xlfn.XLOOKUP(AE664,Sheet1!$F:$F,Sheet1!$W:$W),FIND("-",_xlfn.XLOOKUP(AE664,Sheet1!$F:$F,Sheet1!$W:$W),FIND("-",_xlfn.XLOOKUP(AE664,Sheet1!$F:$F,Sheet1!$W:$W))+1))&AE664,"NOT FOUND"),LEFT(J664,FIND("-",J664,FIND("-",J664)+1))&AE664)) -> KRTS-APSU26-YETKRTSCUT5008
A665: S0EU | B665: 5112963725 | C665: 30.01.2026 | D665: 30.06.2026 | E665: 10337044 | F665: UNITED TEXTILE MILLS PRIVATE LIMITE | G665: 3 | H665: 8909103992453 | I665: 441857089017 | J665: KRTS-APSU26-YETKRTSCUT500, OFF WHITE, XL | L665: EA | M665: 1 | N665: 269 | O665: 269 | Q665: 0 | R665: 0 | S665: 0 | T665: 0 | U665: 0 | V665: INR | X665: =IF(ISNUMBER(VALUE(LEFT(J665,1))),LEFT(J665,MIN(IFERROR(FIND("A",UPPER(J665)),LEN(J665)+1),IFERROR(FIND("B",UPPER(J665)),LEN(J665)+1),IFERROR(FIND("C",UPPER(J665)),LEN(J665)+1),IFERROR(FIND("D",UPPER(J665)),LEN(J665)+1),IFERROR(FIND("E",UPPER(J665)),LEN(J665)+1),IFERROR(FIND("F",UPPER(J665)),LEN(J665)+1),IFERROR(FIND("G",UPPER(J665)),LEN(J665)+1),IFERROR(FIND("H",UPPER(J665)),LEN(J665)+1),IFERROR(FIND("I",UPPER(J665)),LEN(J665)+1),IFERROR(FIND("J",UPPER(J665)),LEN(J665)+1),IFERROR(FIND("K",UPPER(J665)),LEN(J665)+1),IFERROR(FIND("L",UPPER(J665)),LEN(J665)+1),IFERROR(FIND("M",UPPER(J665)),LEN(J665)+1),IFERROR(FIND("N",UPPER(J665)),LEN(J665)+1),IFERROR(FIND("O",UPPER(J665)),LEN(J665)+1),IFERROR(FIND("P",UPPER(J665)),LEN(J665)+1),IFERROR(FIND("Q",UPPER(J665)),LEN(J665)+1),IFERROR(FIND("R",UPPER(J665)),LEN(J665)+1),IFERROR(FIND("S",UPPER(J665)),LEN(J665)+1),IFERROR(FIND("T",UPPER(J665)),LEN(J665)+1),IFERROR(FIND("U",UPPER(J665)),LEN(J665)+1),IFERROR(FIND("V",UPPER(J665)),LEN(J665)+1),IFERROR(FIND("W",UPPER(J665)),LEN(J665)+1),IFERROR(FIND("X",UPPER(J665)),LEN(J665)+1),IFERROR(FIND("Y",UPPER(J665)),LEN(J665)+1),IFERROR(FIND("Z",UPPER(J665)),LEN(J665)+1))-1),LEFT(TEXT(I665,"0"),LEN(TEXT(I665,"0"))-3)) -> 441857089 | Y665: =IF(ISNUMBER(SEARCH("(RP)",J665)),"RP","DC") -> DC | Z665: =IF(ISNUMBER(SEARCH("(RP)",J665)),O665,IF(RIGHT(TRIM(J665),3)=", S",O665,0)) -> 0 | AA665: =IF(ISNUMBER(SEARCH("(RP)",J665)),O665,IF(RIGHT(TRIM(J665),3)=", M",O665,0)) -> 0 | AB665: =IF(ISNUMBER(SEARCH("(RP)",J665)),O665,IF(RIGHT(TRIM(J665),3)=", L",O665,0)) -> 0 | AC665: =IF(ISNUMBER(SEARCH("(RP)",J665)),O665,IF(RIGHT(TRIM(J665),4)=", XL",O665,0)) -> 269 | AD665: =IF(ISNUMBER(SEARCH("(RP)",J665)),O665,IF(OR(RIGHT(TRIM(J665),5)=", XXL",RIGHT(TRIM(J665),5)=", 2XL"),O665,0)) -> 0 | AE665: {=IFERROR(_xlfn.XLOOKUP(H665,Sheet1!$G:$G,Sheet1!$F:$F),IFERROR(_xlfn.XLOOKUP(1,(--($X$2:$X$1074=X665))*(--ISNUMBER(MATCH($H$2:$H$1074,Sheet1!$G:$G,0))),_xlfn.XLOOKUP($H$2:$H$1074,Sheet1!$G:$G,Sheet1!$F:$F,"")),"NOT FOUND"))} -> YETKRTSCUT5008 | AF665: =IFERROR(IF(ISNUMBER(SEARCH("(RP)",J665)),TRIM(SUBSTITUTE(MID(J665,10,LEN(J665)),"(RP)","")),TRIM(MID(J665,FIND(",",J665)+1,FIND(",",J665,FIND(",",J665)+1)-FIND(",",J665)-1))),"") -> OFF WHITE | AG665: =IF(A665="SZAF","Bangalore",IF(A665="SAEX","JHAJJAR",IF(A665="S0EU","HARIPAL",""))) -> HARIPAL | AH665: =IF(OR(J665="",AE665="",AE665="NOT FOUND"),"",IF(Y665="RP",IFERROR(LEFT(_xlfn.XLOOKUP(AE665,Sheet1!$F:$F,Sheet1!$W:$W),FIND("-",_xlfn.XLOOKUP(AE665,Sheet1!$F:$F,Sheet1!$W:$W),FIND("-",_xlfn.XLOOKUP(AE665,Sheet1!$F:$F,Sheet1!$W:$W))+1))&AE665,"NOT FOUND"),LEFT(J665,FIND("-",J665,FIND("-",J665)+1))&AE665)) -> KRTS-APSU26-YETKRTSCUT5008
A666: S0EU | B666: 5112963725 | C666: 30.01.2026 | D666: 30.06.2026 | E666: 10337044 | F666: UNITED TEXTILE MILLS PRIVATE LIMITE | G666: 4 | H666: 8909103992446 | I666: 441857089018 | J666: KRTS-APSU26-YETKRTSCUT5008, OFF WHITE, L | L666: EA | M666: 1 | N666: 269 | O666: 269 | Q666: 0 | R666: 0 | S666: 0 | T666: 0 | U666: 0 | V666: INR | X666: =IF(ISNUMBER(VALUE(LEFT(J666,1))),LEFT(J666,MIN(IFERROR(FIND("A",UPPER(J666)),LEN(J666)+1),IFERROR(FIND("B",UPPER(J666)),LEN(J666)+1),IFERROR(FIND("C",UPPER(J666)),LEN(J666)+1),IFERROR(FIND("D",UPPER(J666)),LEN(J666)+1),IFERROR(FIND("E",UPPER(J666)),LEN(J666)+1),IFERROR(FIND("F",UPPER(J666)),LEN(J666)+1),IFERROR(FIND("G",UPPER(J666)),LEN(J666)+1),IFERROR(FIND("H",UPPER(J666)),LEN(J666)+1),IFERROR(FIND("I",UPPER(J666)),LEN(J666)+1),IFERROR(FIND("J",UPPER(J666)),LEN(J666)+1),IFERROR(FIND("K",UPPER(J666)),LEN(J666)+1),IFERROR(FIND("L",UPPER(J666)),LEN(J666)+1),IFERROR(FIND("M",UPPER(J666)),LEN(J666)+1),IFERROR(FIND("N",UPPER(J666)),LEN(J666)+1),IFERROR(FIND("O",UPPER(J666)),LEN(J666)+1),IFERROR(FIND("P",UPPER(J666)),LEN(J666)+1),IFERROR(FIND("Q",UPPER(J666)),LEN(J666)+1),IFERROR(FIND("R",UPPER(J666)),LEN(J666)+1),IFERROR(FIND("S",UPPER(J666)),LEN(J666)+1),IFERROR(FIND("T",UPPER(J666)),LEN(J666)+1),IFERROR(FIND("U",UPPER(J666)),LEN(J666)+1),IFERROR(FIND("V",UPPER(J666)),LEN(J666)+1),IFERROR(FIND("W",UPPER(J666)),LEN(J666)+1),IFERROR(FIND("X",UPPER(J666)),LEN(J666)+1),IFERROR(FIND("Y",UPPER(J666)),LEN(J666)+1),IFERROR(FIND("Z",UPPER(J666)),LEN(J666)+1))-1),LEFT(TEXT(I666,"0"),LEN(TEXT(I666,"0"))-3)) -> 441857089 | Y666: =IF(ISNUMBER(SEARCH("(RP)",J666)),"RP","DC") -> DC | Z666: =IF(ISNUMBER(SEARCH("(RP)",J666)),O666,IF(RIGHT(TRIM(J666),3)=", S",O666,0)) -> 0 | AA666: =IF(ISNUMBER(SEARCH("(RP)",J666)),O666,IF(RIGHT(TRIM(J666),3)=", M",O666,0)) -> 0 | AB666: =IF(ISNUMBER(SEARCH("(RP)",J666)),O666,IF(RIGHT(TRIM(J666),3)=", L",O666,0)) -> 269 | AC666: =IF(ISNUMBER(SEARCH("(RP)",J666)),O666,IF(RIGHT(TRIM(J666),4)=", XL",O666,0)) -> 0 | AD666: =IF(ISNUMBER(SEARCH("(RP)",J666)),O666,IF(OR(RIGHT(TRIM(J666),5)=", XXL",RIGHT(TRIM(J666),5)=", 2XL"),O666,0)) -> 0 | AE666: {=IFERROR(_xlfn.XLOOKUP(H666,Sheet1!$G:$G,Sheet1!$F:$F),IFERROR(_xlfn.XLOOKUP(1,(--($X$2:$X$1074=X666))*(--ISNUMBER(MATCH($H$2:$H$1074,Sheet1!$G:$G,0))),_xlfn.XLOOKUP($H$2:$H$1074,Sheet1!$G:$G,Sheet1!$F:$F,"")),"NOT FOUND"))} -> YETKRTSCUT5008 | AF666: =IFERROR(IF(ISNUMBER(SEARCH("(RP)",J666)),TRIM(SUBSTITUTE(MID(J666,10,LEN(J666)),"(RP)","")),TRIM(MID(J666,FIND(",",J666)+1,FIND(",",J666,FIND(",",J666)+1)-FIND(",",J666)-1))),"") -> OFF WHITE | AG666: =IF(A666="SZAF","Bangalore",IF(A666="SAEX","JHAJJAR",IF(A666="S0EU","HARIPAL",""))) -> HARIPAL | AH666: =IF(OR(J666="",AE666="",AE666="NOT FOUND"),"",IF(Y666="RP",IFERROR(LEFT(_xlfn.XLOOKUP(AE666,Sheet1!$F:$F,Sheet1!$W:$W),FIND("-",_xlfn.XLOOKUP(AE666,Sheet1!$F:$F,Sheet1!$W:$W),FIND("-",_xlfn.XLOOKUP(AE666,Sheet1!$F:$F,Sheet1!$W:$W))+1))&AE666,"NOT FOUND"),LEFT(J666,FIND("-",J666,FIND("-",J666)+1))&AE666)) -> KRTS-APSU26-YETKRTSCUT5008
A667: S0EU | B667: 5112963725 | C667: 30.01.2026 | D667: 30.06.2026 | E667: 10337044 | F667: UNITED TEXTILE MILLS PRIVATE LIMITE | G667: 5 | H667: 8909103992439 | I667: 441857089019 | J667: KRTS-APSU26-YETKRTSCUT5008, OFF WHITE, M | L667: EA | M667: 1 | N667: 269 | O667: 269 | Q667: 0 | R667: 0 | S667: 0 | T667: 0 | U667: 0 | V667: INR | X667: =IF(ISNUMBER(VALUE(LEFT(J667,1))),LEFT(J667,MIN(IFERROR(FIND("A",UPPER(J667)),LEN(J667)+1),IFERROR(FIND("B",UPPER(J667)),LEN(J667)+1),IFERROR(FIND("C",UPPER(J667)),LEN(J667)+1),IFERROR(FIND("D",UPPER(J667)),LEN(J667)+1),IFERROR(FIND("E",UPPER(J667)),LEN(J667)+1),IFERROR(FIND("F",UPPER(J667)),LEN(J667)+1),IFERROR(FIND("G",UPPER(J667)),LEN(J667)+1),IFERROR(FIND("H",UPPER(J667)),LEN(J667)+1),IFERROR(FIND("I",UPPER(J667)),LEN(J667)+1),IFERROR(FIND("J",UPPER(J667)),LEN(J667)+1),IFERROR(FIND("K",UPPER(J667)),LEN(J667)+1),IFERROR(FIND("L",UPPER(J667)),LEN(J667)+1),IFERROR(FIND("M",UPPER(J667)),LEN(J667)+1),IFERROR(FIND("N",UPPER(J667)),LEN(J667)+1),IFERROR(FIND("O",UPPER(J667)),LEN(J667)+1),IFERROR(FIND("P",UPPER(J667)),LEN(J667)+1),IFERROR(FIND("Q",UPPER(J667)),LEN(J667)+1),IFERROR(FIND("R",UPPER(J667)),LEN(J667)+1),IFERROR(FIND("S",UPPER(J667)),LEN(J667)+1),IFERROR(FIND("T",UPPER(J667)),LEN(J667)+1),IFERROR(FIND("U",UPPER(J667)),LEN(J667)+1),IFERROR(FIND("V",UPPER(J667)),LEN(J667)+1),IFERROR(FIND("W",UPPER(J667)),LEN(J667)+1),IFERROR(FIND("X",UPPER(J667)),LEN(J667)+1),IFERROR(FIND("Y",UPPER(J667)),LEN(J667)+1),IFERROR(FIND("Z",UPPER(J667)),LEN(J667)+1))-1),LEFT(TEXT(I667,"0"),LEN(TEXT(I667,"0"))-3)) -> 441857089 | Y667: =IF(ISNUMBER(SEARCH("(RP)",J667)),"RP","DC") -> DC | Z667: =IF(ISNUMBER(SEARCH("(RP)",J667)),O667,IF(RIGHT(TRIM(J667),3)=", S",O667,0)) -> 0 | AA667: =IF(ISNUMBER(SEARCH("(RP)",J667)),O667,IF(RIGHT(TRIM(J667),3)=", M",O667,0)) -> 269 | AB667: =IF(ISNUMBER(SEARCH("(RP)",J667)),O667,IF(RIGHT(TRIM(J667),3)=", L",O667,0)) -> 0 | AC667: =IF(ISNUMBER(SEARCH("(RP)",J667)),O667,IF(RIGHT(TRIM(J667),4)=", XL",O667,0)) -> 0 | AD667: =IF(ISNUMBER(SEARCH("(RP)",J667)),O667,IF(OR(RIGHT(TRIM(J667),5)=", XXL",RIGHT(TRIM(J667),5)=", 2XL"),O667,0)) -> 0 | AE667: {=IFERROR(_xlfn.XLOOKUP(H667,Sheet1!$G:$G,Sheet1!$F:$F),IFERROR(_xlfn.XLOOKUP(1,(--($X$2:$X$1074=X667))*(--ISNUMBER(MATCH($H$2:$H$1074,Sheet1!$G:$G,0))),_xlfn.XLOOKUP($H$2:$H$1074,Sheet1!$G:$G,Sheet1!$F:$F,"")),"NOT FOUND"))} -> YETKRTSCUT5008 | AF667: =IFERROR(IF(ISNUMBER(SEARCH("(RP)",J667)),TRIM(SUBSTITUTE(MID(J667,10,LEN(J667)),"(RP)","")),TRIM(MID(J667,FIND(",",J667)+1,FIND(",",J667,FIND(",",J667)+1)-FIND(",",J667)-1))),"") -> OFF WHITE | AG667: =IF(A667="SZAF","Bangalore",IF(A667="SAEX","JHAJJAR",IF(A667="S0EU","HARIPAL",""))) -> HARIPAL | AH667: =IF(OR(J667="",AE667="",AE667="NOT FOUND"),"",IF(Y667="RP",IFERROR(LEFT(_xlfn.XLOOKUP(AE667,Sheet1!$F:$F,Sheet1!$W:$W),FIND("-",_xlfn.XLOOKUP(AE667,Sheet1!$F:$F,Sheet1!$W:$W),FIND("-",_xlfn.XLOOKUP(AE667,Sheet1!$F:$F,Sheet1!$W:$W))+1))&AE667,"NOT FOUND"),LEFT(J667,FIND("-",J667,FIND("-",J667)+1))&AE667)) -> KRTS-APSU26-YETKRTSCUT5008
A668: S0EU | B668: 5112963725 | C668: 30.01.2026 | D668: 30.06.2026 | E668: 10337044 | F668: UNITED TEXTILE MILLS PRIVATE LIMITE | G668: 6 | H668: 8909103992422 | I668: 441857089020 | J668: KRTS-APSU26-YETKRTSCUT5008, OFF WHITE, S | L668: EA | M668: 1 | N668: 269 | O668: 269 | Q668: 0 | R668: 0 | S668: 0 | T668: 0 | U668: 0 | X668: =IF(ISNUMBER(VALUE(LEFT(J668,1))),LEFT(J668,MIN(IFERROR(FIND("A",UPPER(J668)),LEN(J668)+1),IFERROR(FIND("B",UPPER(J668)),LEN(J668)+1),IFERROR(FIND("C",UPPER(J668)),LEN(J668)+1),IFERROR(FIND("D",UPPER(J668)),LEN(J668)+1),IFERROR(FIND("E",UPPER(J668)),LEN(J668)+1),IFERROR(FIND("F",UPPER(J668)),LEN(J668)+1),IFERROR(FIND("G",UPPER(J668)),LEN(J668)+1),IFERROR(FIND("H",UPPER(J668)),LEN(J668)+1),IFERROR(FIND("I",UPPER(J668)),LEN(J668)+1),IFERROR(FIND("J",UPPER(J668)),LEN(J668)+1),IFERROR(FIND("K",UPPER(J668)),LEN(J668)+1),IFERROR(FIND("L",UPPER(J668)),LEN(J668)+1),IFERROR(FIND("M",UPPER(J668)),LEN(J668)+1),IFERROR(FIND("N",UPPER(J668)),LEN(J668)+1),IFERROR(FIND("O",UPPER(J668)),LEN(J668)+1),IFERROR(FIND("P",UPPER(J668)),LEN(J668)+1),IFERROR(FIND("Q",UPPER(J668)),LEN(J668)+1),IFERROR(FIND("R",UPPER(J668)),LEN(J668)+1),IFERROR(FIND("S",UPPER(J668)),LEN(J668)+1),IFERROR(FIND("T",UPPER(J668)),LEN(J668)+1),IFERROR(FIND("U",UPPER(J668)),LEN(J668)+1),IFERROR(FIND("V",UPPER(J668)),LEN(J668)+1),IFERROR(FIND("W",UPPER(J668)),LEN(J668)+1),IFERROR(FIND("X",UPPER(J668)),LEN(J668)+1),IFERROR(FIND("Y",UPPER(J668)),LEN(J668)+1),IFERROR(FIND("Z",UPPER(J668)),LEN(J668)+1))-1),LEFT(TEXT(I668,"0"),LEN(TEXT(I668,"0"))-3)) -> 441857089 | Y668: =IF(ISNUMBER(SEARCH("(RP)",J668)),"RP","DC") -> DC | Z668: =IF(ISNUMBER(SEARCH("(RP)",J668)),O668,IF(RIGHT(TRIM(J668),3)=", S",O668,0)) -> 269 | AA668: =IF(ISNUMBER(SEARCH("(RP)",J668)),O668,IF(RIGHT(TRIM(J668),3)=", M",O668,0)) -> 0 | AB668: =IF(ISNUMBER(SEARCH("(RP)",J668)),O668,IF(RIGHT(TRIM(J668),3)=", L",O668,0)) -> 0 | AC668: =IF(ISNUMBER(SEARCH("(RP)",J668)),O668,IF(RIGHT(TRIM(J668),4)=", XL",O668,0)) -> 0 | AD668: =IF(ISNUMBER(SEARCH("(RP)",J668)),O668,IF(OR(RIGHT(TRIM(J668),5)=", XXL",RIGHT(TRIM(J668),5)=", 2XL"),O668,0)) -> 0 | AE668: {=IFERROR(_xlfn.XLOOKUP(H668,Sheet1!$G:$G,Sheet1!$F:$F),IFERROR(_xlfn.XLOOKUP(1,(--($X$2:$X$1074=X668))*(--ISNUMBER(MATCH($H$2:$H$1074,Sheet1!$G:$G,0))),_xlfn.XLOOKUP($H$2:$H$1074,Sheet1!$G:$G,Sheet1!$F:$F,"")),"NOT FOUND"))} -> YETKRTSCUT5008 | AF668: =IFERROR(IF(ISNUMBER(SEARCH("(RP)",J668)),TRIM(SUBSTITUTE(MID(J668,10,LEN(J668)),"(RP)","")),TRIM(MID(J668,FIND(",",J668)+1,FIND(",",J668,FIND(",",J668)+1)-FIND(",",J668)-1))),"") -> OFF WHITE | AG668: =IF(A668="SZAF","Bangalore",IF(A668="SAEX","JHAJJAR",IF(A668="S0EU","HARIPAL",""))) -> HARIPAL | AH668: =IF(OR(J668="",AE668="",AE668="NOT FOUND"),"",IF(Y668="RP",IFERROR(LEFT(_xlfn.XLOOKUP(AE668,Sheet1!$F:$F,Sheet1!$W:$W),FIND("-",_xlfn.XLOOKUP(AE668,Sheet1!$F:$F,Sheet1!$W:$W),FIND("-",_xlfn.XLOOKUP(AE668,Sheet1!$F:$F,Sheet1!$W:$W))+1))&AE668,"NOT FOUND"),LEFT(J668,FIND("-",J668,FIND("-",J668)+1))&AE668)) -> KRTS-APSU26-YETKRTSCUT5008
A669: S0EU | B669: 5112963724 | C669: 30.01.2026 | D669: 30.06.2026 | E669: 10337044 | F669: UNITED TEXTILE MILLS PRIVATE LIMITE | G669: 1 | H669: 8909103992606 | I669: 494758189 | J669: 441857089 RUST(RP) | L669: EA | M669: 1 | N669: 269 | O669: 269 | Q669: 1221.5 | R669: 1221.5 | S669: 16429.18 | T669: 328583.5 | U669: 5 | V669: INR | X669: =IF(ISNUMBER(VALUE(LEFT(J669,1))),LEFT(J669,MIN(IFERROR(FIND("A",UPPER(J669)),LEN(J669)+1),IFERROR(FIND("B",UPPER(J669)),LEN(J669)+1),IFERROR(FIND("C",UPPER(J669)),LEN(J669)+1),IFERROR(FIND("D",UPPER(J669)),LEN(J669)+1),IFERROR(FIND("E",UPPER(J669)),LEN(J669)+1),IFERROR(FIND("F",UPPER(J669)),LEN(J669)+1),IFERROR(FIND("G",UPPER(J669)),LEN(J669)+1),IFERROR(FIND("H",UPPER(J669)),LEN(J669)+1),IFERROR(FIND("I",UPPER(J669)),LEN(J669)+1),IFERROR(FIND("J",UPPER(J669)),LEN(J669)+1),IFERROR(FIND("K",UPPER(J669)),LEN(J669)+1),IFERROR(FIND("L",UPPER(J669)),LEN(J669)+1),IFERROR(FIND("M",UPPER(J669)),LEN(J669)+1),IFERROR(FIND("N",UPPER(J669)),LEN(J669)+1),IFERROR(FIND("O",UPPER(J669)),LEN(J669)+1),IFERROR(FIND("P",UPPER(J669)),LEN(J669)+1),IFERROR(FIND("Q",UPPER(J669)),LEN(J669)+1),IFERROR(FIND("R",UPPER(J669)),LEN(J669)+1),IFERROR(FIND("S",UPPER(J669)),LEN(J669)+1),IFERROR(FIND("T",UPPER(J669)),LEN(J669)+1),IFERROR(FIND("U",UPPER(J669)),LEN(J669)+1),IFERROR(FIND("V",UPPER(J669)),LEN(J669)+1),IFERROR(FIND("W",UPPER(J669)),LEN(J669)+1),IFERROR(FIND("X",UPPER(J669)),LEN(J669)+1),IFERROR(FIND("Y",UPPER(J669)),LEN(J669)+1),IFERROR(FIND("Z",UPPER(J669)),LEN(J669)+1))-1),LEFT(TEXT(I669,"0"),LEN(TEXT(I669,"0"))-3)) -> 441857089 | Y669: =IF(ISNUMBER(SEARCH("(RP)",J669)),"RP","DC") -> RP | Z669: =IF(ISNUMBER(SEARCH("(RP)",J669)),O669,IF(RIGHT(TRIM(J669),3)=", S",O669,0)) -> 269 | AA669: =IF(ISNUMBER(SEARCH("(RP)",J669)),O669,IF(RIGHT(TRIM(J669),3)=", M",O669,0)) -> 269 | AB669: =IF(ISNUMBER(SEARCH("(RP)",J669)),O669,IF(RIGHT(TRIM(J669),3)=", L",O669,0)) -> 269 | AC669: =IF(ISNUMBER(SEARCH("(RP)",J669)),O669,IF(RIGHT(TRIM(J669),4)=", XL",O669,0)) -> 269 | AD669: =IF(ISNUMBER(SEARCH("(RP)",J669)),O669,IF(OR(RIGHT(TRIM(J669),5)=", XXL",RIGHT(TRIM(J669),5)=", 2XL"),O669,0)) -> 269 | AE669: {=IFERROR(_xlfn.XLOOKUP(H669,Sheet1!$G:$G,Sheet1!$F:$F),IFERROR(_xlfn.XLOOKUP(1,(--($X$2:$X$1074=X669))*(--ISNUMBER(MATCH($H$2:$H$1074,Sheet1!$G:$G,0))),_xlfn.XLOOKUP($H$2:$H$1074,Sheet1!$G:$G,Sheet1!$F:$F,"")),"NOT FOUND"))} -> YETKRTSCUT5008 | AF669: =IFERROR(IF(ISNUMBER(SEARCH("(RP)",J669)),TRIM(SUBSTITUTE(MID(J669,10,LEN(J669)),"(RP)","")),TRIM(MID(J669,FIND(",",J669)+1,FIND(",",J669,FIND(",",J669)+1)-FIND(",",J669)-1))),"") -> RUST | AG669: =IF(A669="SZAF","Bangalore",IF(A669="SAEX","JHAJJAR",IF(A669="S0EU","HARIPAL",""))) -> HARIPAL | AH669: =IF(OR(J669="",AE669="",AE669="NOT FOUND"),"",IF(Y669="RP",IFERROR(LEFT(_xlfn.XLOOKUP(AE669,Sheet1!$F:$F,Sheet1!$W:$W),FIND("-",_xlfn.XLOOKUP(AE669,Sheet1!$F:$F,Sheet1!$W:$W),FIND("-",_xlfn.XLOOKUP(AE669,Sheet1!$F:$F,Sheet1!$W:$W))+1))&AE669,"NOT FOUND"),LEFT(J669,FIND("-",J669,FIND("-",J669)+1))&AE669)) -> KRTS-APSU26-YETKRTSCUT5008
A670: S0EU | B670: 5112963724 | C670: 30.01.2026 | D670: 30.06.2026 | E670: 10337044 | F670: UNITED TEXTILE MILLS PRIVATE LIMITE | G670: 2 | H670: 8909103992514 | I670: 441857089011 | J670: KRTS-APSU26-YETKRTSCUT5008, RUST, 2XL | L670: EA | M670: 1 | N670: 269 | O670: 269 | Q670: 0 | R670: 0 | S670: 0 | T670: 0 | U670: 0 | V670: INR | X670: =IF(ISNUMBER(VALUE(LEFT(J670,1))),LEFT(J670,MIN(IFERROR(FIND("A",UPPER(J670)),LEN(J670)+1),IFERROR(FIND("B",UPPER(J670)),LEN(J670)+1),IFERROR(FIND("C",UPPER(J670)),LEN(J670)+1),IFERROR(FIND("D",UPPER(J670)),LEN(J670)+1),IFERROR(FIND("E",UPPER(J670)),LEN(J670)+1),IFERROR(FIND("F",UPPER(J670)),LEN(J670)+1),IFERROR(FIND("G",UPPER(J670)),LEN(J670)+1),IFERROR(FIND("H",UPPER(J670)),LEN(J670)+1),IFERROR(FIND("I",UPPER(J670)),LEN(J670)+1),IFERROR(FIND("J",UPPER(J670)),LEN(J670)+1),IFERROR(FIND("K",UPPER(J670)),LEN(J670)+1),IFERROR(FIND("L",UPPER(J670)),LEN(J670)+1),IFERROR(FIND("M",UPPER(J670)),LEN(J670)+1),IFERROR(FIND("N",UPPER(J670)),LEN(J670)+1),IFERROR(FIND("O",UPPER(J670)),LEN(J670)+1),IFERROR(FIND("P",UPPER(J670)),LEN(J670)+1),IFERROR(FIND("Q",UPPER(J670)),LEN(J670)+1),IFERROR(FIND("R",UPPER(J670)),LEN(J670)+1),IFERROR(FIND("S",UPPER(J670)),LEN(J670)+1),IFERROR(FIND("T",UPPER(J670)),LEN(J670)+1),IFERROR(FIND("U",UPPER(J670)),LEN(J670)+1),IFERROR(FIND("V",UPPER(J670)),LEN(J670)+1),IFERROR(FIND("W",UPPER(J670)),LEN(J670)+1),IFERROR(FIND("X",UPPER(J670)),LEN(J670)+1),IFERROR(FIND("Y",UPPER(J670)),LEN(J670)+1),IFERROR(FIND("Z",UPPER(J670)),LEN(J670)+1))-1),LEFT(TEXT(I670,"0"),LEN(TEXT(I670,"0"))-3)) -> 441857089 | Y670: =IF(ISNUMBER(SEARCH("(RP)",J670)),"RP","DC") -> DC | Z670: =IF(ISNUMBER(SEARCH("(RP)",J670)),O670,IF(RIGHT(TRIM(J670),3)=", S",O670,0)) -> 0 | AA670: =IF(ISNUMBER(SEARCH("(RP)",J670)),O670,IF(RIGHT(TRIM(J670),3)=", M",O670,0)) -> 0 | AB670: =IF(ISNUMBER(SEARCH("(RP)",J670)),O670,IF(RIGHT(TRIM(J670),3)=", L",O670,0)) -> 0 | AC670: =IF(ISNUMBER(SEARCH("(RP)",J670)),O670,IF(RIGHT(TRIM(J670),4)=", XL",O670,0)) -> 0 | AD670: =IF(ISNUMBER(SEARCH("(RP)",J670)),O670,IF(OR(RIGHT(TRIM(J670),5)=", XXL",RIGHT(TRIM(J670),5)=", 2XL"),O670,0)) -> 269 | AE670: {=IFERROR(_xlfn.XLOOKUP(H670,Sheet1!$G:$G,Sheet1!$F:$F),IFERROR(_xlfn.XLOOKUP(1,(--($X$2:$X$1074=X670))*(--ISNUMBER(MATCH($H$2:$H$1074,Sheet1!$G:$G,0))),_xlfn.XLOOKUP($H$2:$H$1074,Sheet1!$G:$G,Sheet1!$F:$F,"")),"NOT FOUND"))} -> YETKRTSCUT5008 | AF670: =IFERROR(IF(ISNUMBER(SEARCH("(RP)",J670)),TRIM(SUBSTITUTE(MID(J670,10,LEN(J670)),"(RP)","")),TRIM(MID(J670,FIND(",",J670)+1,FIND(",",J670,FIND(",",J670)+1)-FIND(",",J670)-1))),"") -> RUST | AG670: =IF(A670="SZAF","Bangalore",IF(A670="SAEX","JHAJJAR",IF(A670="S0EU","HARIPAL",""))) -> HARIPAL | AH670: =IF(OR(J670="",AE670="",AE670="NOT FOUND"),"",IF(Y670="RP",IFERROR(LEFT(_xlfn.XLOOKUP(AE670,Sheet1!$F:$F,Sheet1!$W:$W),FIND("-",_xlfn.XLOOKUP(AE670,Sheet1!$F:$F,Sheet1!$W:$W),FIND("-",_xlfn.XLOOKUP(AE670,Sheet1!$F:$F,Sheet1!$W:$W))+1))&AE670,"NOT FOUND"),LEFT(J670,FIND("-",J670,FIND("-",J670)+1))&AE670)) -> KRTS-APSU26-YETKRTSCUT5008
A671: S0EU | B671: 5112963724 | C671: 30.01.2026 | D671: 30.06.2026 | E671: 10337044 | F671: UNITED TEXTILE MILLS PRIVATE LIMITE | G671: 3 | H671: 8909103992507 | I671: 441857089012 | J671: KRTS-APSU26-YETKRTSCUT5008, RUST, XL | L671: EA | M671: 1 | N671: 269 | O671: 269 | Q671: 0 | R671: 0 | S671: 0 | T671: 0 | U671: 0 | V671: INR | X671: =IF(ISNUMBER(VALUE(LEFT(J671,1))),LEFT(J671,MIN(IFERROR(FIND("A",UPPER(J671)),LEN(J671)+1),IFERROR(FIND("B",UPPER(J671)),LEN(J671)+1),IFERROR(FIND("C",UPPER(J671)),LEN(J671)+1),IFERROR(FIND("D",UPPER(J671)),LEN(J671)+1),IFERROR(FIND("E",UPPER(J671)),LEN(J671)+1),IFERROR(FIND("F",UPPER(J671)),LEN(J671)+1),IFERROR(FIND("G",UPPER(J671)),LEN(J671)+1),IFERROR(FIND("H",UPPER(J671)),LEN(J671)+1),IFERROR(FIND("I",UPPER(J671)),LEN(J671)+1),IFERROR(FIND("J",UPPER(J671)),LEN(J671)+1),IFERROR(FIND("K",UPPER(J671)),LEN(J671)+1),IFERROR(FIND("L",UPPER(J671)),LEN(J671)+1),IFERROR(FIND("M",UPPER(J671)),LEN(J671)+1),IFERROR(FIND("N",UPPER(J671)),LEN(J671)+1),IFERROR(FIND("O",UPPER(J671)),LEN(J671)+1),IFERROR(FIND("P",UPPER(J671)),LEN(J671)+1),IFERROR(FIND("Q",UPPER(J671)),LEN(J671)+1),IFERROR(FIND("R",UPPER(J671)),LEN(J671)+1),IFERROR(FIND("S",UPPER(J671)),LEN(J671)+1),IFERROR(FIND("T",UPPER(J671)),LEN(J671)+1),IFERROR(FIND("U",UPPER(J671)),LEN(J671)+1),IFERROR(FIND("V",UPPER(J671)),LEN(J671)+1),IFERROR(FIND("W",UPPER(J671)),LEN(J671)+1),IFERROR(FIND("X",UPPER(J671)),LEN(J671)+1),IFERROR(FIND("Y",UPPER(J671)),LEN(J671)+1),IFERROR(FIND("Z",UPPER(J671)),LEN(J671)+1))-1),LEFT(TEXT(I671,"0"),LEN(TEXT(I671,"0"))-3)) -> 441857089 | Y671: =IF(ISNUMBER(SEARCH("(RP)",J671)),"RP","DC") -> DC | Z671: =IF(ISNUMBER(SEARCH("(RP)",J671)),O671,IF(RIGHT(TRIM(J671),3)=", S",O671,0)) -> 0 | AA671: =IF(ISNUMBER(SEARCH("(RP)",J671)),O671,IF(RIGHT(TRIM(J671),3)=", M",O671,0)) -> 0 | AB671: =IF(ISNUMBER(SEARCH("(RP)",J671)),O671,IF(RIGHT(TRIM(J671),3)=", L",O671,0)) -> 0 | AC671: =IF(ISNUMBER(SEARCH("(RP)",J671)),O671,IF(RIGHT(TRIM(J671),4)=", XL",O671,0)) -> 269 | AD671: =IF(ISNUMBER(SEARCH("(RP)",J671)),O671,IF(OR(RIGHT(TRIM(J671),5)=", XXL",RIGHT(TRIM(J671),5)=", 2XL"),O671,0)) -> 0 | AE671: {=IFERROR(_xlfn.XLOOKUP(H671,Sheet1!$G:$G,Sheet1!$F:$F),IFERROR(_xlfn.XLOOKUP(1,(--($X$2:$X$1074=X671))*(--ISNUMBER(MATCH($H$2:$H$1074,Sheet1!$G:$G,0))),_xlfn.XLOOKUP($H$2:$H$1074,Sheet1!$G:$G,Sheet1!$F:$F,"")),"NOT FOUND"))} -> YETKRTSCUT5008 | AF671: =IFERROR(IF(ISNUMBER(SEARCH("(RP)",J671)),TRIM(SUBSTITUTE(MID(J671,10,LEN(J671)),"(RP)","")),TRIM(MID(J671,FIND(",",J671)+1,FIND(",",J671,FIND(",",J671)+1)-FIND(",",J671)-1))),"") -> RUST | AG671: =IF(A671="SZAF","Bangalore",IF(A671="SAEX","JHAJJAR",IF(A671="S0EU","HARIPAL",""))) -> HARIPAL | AH671: =IF(OR(J671="",AE671="",AE671="NOT FOUND"),"",IF(Y671="RP",IFERROR(LEFT(_xlfn.XLOOKUP(AE671,Sheet1!$F:$F,Sheet1!$W:$W),FIND("-",_xlfn.XLOOKUP(AE671,Sheet1!$F:$F,Sheet1!$W:$W),FIND("-",_xlfn.XLOOKUP(AE671,Sheet1!$F:$F,Sheet1!$W:$W))+1))&AE671,"NOT FOUND"),LEFT(J671,FIND("-",J671,FIND("-",J671)+1))&AE671)) -> KRTS-APSU26-YETKRTSCUT5008
A672: S0EU | B672: 5112963724 | C672: 30.01.2026 | D672: 30.06.2026 | E672: 10337044 | F672: UNITED TEXTILE MILLS PRIVATE LIMITE | G672: 4 | H672: 8909103992491 | I672: 441857089013 | J672: KRTS-APSU26-YETKRTSCUT5008, RUST, L | L672: EA | M672: 1 | N672: 269 | O672: 269 | Q672: 0 | R672: 0 | S672: 0 | T672: 0 | U672: 0 | V672: INR | X672: =IF(ISNUMBER(VALUE(LEFT(J672,1))),LEFT(J672,MIN(IFERROR(FIND("A",UPPER(J672)),LEN(J672)+1),IFERROR(FIND("B",UPPER(J672)),LEN(J672)+1),IFERROR(FIND("C",UPPER(J672)),LEN(J672)+1),IFERROR(FIND("D",UPPER(J672)),LEN(J672)+1),IFERROR(FIND("E",UPPER(J672)),LEN(J672)+1),IFERROR(FIND("F",UPPER(J672)),LEN(J672)+1),IFERROR(FIND("G",UPPER(J672)),LEN(J672)+1),IFERROR(FIND("H",UPPER(J672)),LEN(J672)+1),IFERROR(FIND("I",UPPER(J672)),LEN(J672)+1),IFERROR(FIND("J",UPPER(J672)),LEN(J672)+1),IFERROR(FIND("K",UPPER(J672)),LEN(J672)+1),IFERROR(FIND("L",UPPER(J672)),LEN(J672)+1),IFERROR(FIND("M",UPPER(J672)),LEN(J672)+1),IFERROR(FIND("N",UPPER(J672)),LEN(J672)+1),IFERROR(FIND("O",UPPER(J672)),LEN(J672)+1),IFERROR(FIND("P",UPPER(J672)),LEN(J672)+1),IFERROR(FIND("Q",UPPER(J672)),LEN(J672)+1),IFERROR(FIND("R",UPPER(J672)),LEN(J672)+1),IFERROR(FIND("S",UPPER(J672)),LEN(J672)+1),IFERROR(FIND("T",UPPER(J672)),LEN(J672)+1),IFERROR(FIND("U",UPPER(J672)),LEN(J672)+1),IFERROR(FIND("V",UPPER(J672)),LEN(J672)+1),IFERROR(FIND("W",UPPER(J672)),LEN(J672)+1),IFERROR(FIND("X",UPPER(J672)),LEN(J672)+1),IFERROR(FIND("Y",UPPER(J672)),LEN(J672)+1),IFERROR(FIND("Z",UPPER(J672)),LEN(J672)+1))-1),LEFT(TEXT(I672,"0"),LEN(TEXT(I672,"0"))-3)) -> 441857089 | Y672: =IF(ISNUMBER(SEARCH("(RP)",J672)),"RP","DC") -> DC | Z672: =IF(ISNUMBER(SEARCH("(RP)",J672)),O672,IF(RIGHT(TRIM(J672),3)=", S",O672,0)) -> 0 | AA672: =IF(ISNUMBER(SEARCH("(RP)",J672)),O672,IF(RIGHT(TRIM(J672),3)=", M",O672,0)) -> 0 | AB672: =IF(ISNUMBER(SEARCH("(RP)",J672)),O672,IF(RIGHT(TRIM(J672),3)=", L",O672,0)) -> 269 | AC672: =IF(ISNUMBER(SEARCH("(RP)",J672)),O672,IF(RIGHT(TRIM(J672),4)=", XL",O672,0)) -> 0 | AD672: =IF(ISNUMBER(SEARCH("(RP)",J672)),O672,IF(OR(RIGHT(TRIM(J672),5)=", XXL",RIGHT(TRIM(J672),5)=", 2XL"),O672,0)) -> 0 | AE672: {=IFERROR(_xlfn.XLOOKUP(H672,Sheet1!$G:$G,Sheet1!$F:$F),IFERROR(_xlfn.XLOOKUP(1,(--($X$2:$X$1074=X672))*(--ISNUMBER(MATCH($H$2:$H$1074,Sheet1!$G:$G,0))),_xlfn.XLOOKUP($H$2:$H$1074,Sheet1!$G:$G,Sheet1!$F:$F,"")),"NOT FOUND"))} -> YETKRTSCUT5008 | AF672: =IFERROR(IF(ISNUMBER(SEARCH("(RP)",J672)),TRIM(SUBSTITUTE(MID(J672,10,LEN(J672)),"(RP)","")),TRIM(MID(J672,FIND(",",J672)+1,FIND(",",J672,FIND(",",J672)+1)-FIND(",",J672)-1))),"") -> RUST | AG672: =IF(A672="SZAF","Bangalore",IF(A672="SAEX","JHAJJAR",IF(A672="S0EU","HARIPAL",""))) -> HARIPAL | AH672: =IF(OR(J672="",AE672="",AE672="NOT FOUND"),"",IF(Y672="RP",IFERROR(LEFT(_xlfn.XLOOKUP(AE672,Sheet1!$F:$F,Sheet1!$W:$W),FIND("-",_xlfn.XLOOKUP(AE672,Sheet1!$F:$F,Sheet1!$W:$W),FIND("-",_xlfn.XLOOKUP(AE672,Sheet1!$F:$F,Sheet1!$W:$W))+1))&AE672,"NOT FOUND"),LEFT(J672,FIND("-",J672,FIND("-",J672)+1))&AE672)) -> KRTS-APSU26-YETKRTSCUT5008
A673: S0EU | B673: 5112963724 | C673: 30.01.2026 | D673: 30.06.2026 | E673: 10337044 | F673: UNITED TEXTILE MILLS PRIVATE LIMITE | G673: 5 | H673: 8909103992484 | I673: 441857089014 | J673: KRTS-APSU26-YETKRTSCUT5008, RUST, M | L673: EA | M673: 1 | N673: 269 | O673: 269 | Q673: 0 | R673: 0 | S673: 0 | T673: 0 | U673: 0 | V673: INR | X673: =IF(ISNUMBER(VALUE(LEFT(J673,1))),LEFT(J673,MIN(IFERROR(FIND("A",UPPER(J673)),LEN(J673)+1),IFERROR(FIND("B",UPPER(J673)),LEN(J673)+1),IFERROR(FIND("C",UPPER(J673)),LEN(J673)+1),IFERROR(FIND("D",UPPER(J673)),LEN(J673)+1),IFERROR(FIND("E",UPPER(J673)),LEN(J673)+1),IFERROR(FIND("F",UPPER(J673)),LEN(J673)+1),IFERROR(FIND("G",UPPER(J673)),LEN(J673)+1),IFERROR(FIND("H",UPPER(J673)),LEN(J673)+1),IFERROR(FIND("I",UPPER(J673)),LEN(J673)+1),IFERROR(FIND("J",UPPER(J673)),LEN(J673)+1),IFERROR(FIND("K",UPPER(J673)),LEN(J673)+1),IFERROR(FIND("L",UPPER(J673)),LEN(J673)+1),IFERROR(FIND("M",UPPER(J673)),LEN(J673)+1),IFERROR(FIND("N",UPPER(J673)),LEN(J673)+1),IFERROR(FIND("O",UPPER(J673)),LEN(J673)+1),IFERROR(FIND("P",UPPER(J673)),LEN(J673)+1),IFERROR(FIND("Q",UPPER(J673)),LEN(J673)+1),IFERROR(FIND("R",UPPER(J673)),LEN(J673)+1),IFERROR(FIND("S",UPPER(J673)),LEN(J673)+1),IFERROR(FIND("T",UPPER(J673)),LEN(J673)+1),IFERROR(FIND("U",UPPER(J673)),LEN(J673)+1),IFERROR(FIND("V",UPPER(J673)),LEN(J673)+1),IFERROR(FIND("W",UPPER(J673)),LEN(J673)+1),IFERROR(FIND("X",UPPER(J673)),LEN(J673)+1),IFERROR(FIND("Y",UPPER(J673)),LEN(J673)+1),IFERROR(FIND("Z",UPPER(J673)),LEN(J673)+1))-1),LEFT(TEXT(I673,"0"),LEN(TEXT(I673,"0"))-3)) -> 441857089 | Y673: =IF(ISNUMBER(SEARCH("(RP)",J673)),"RP","DC") -> DC | Z673: =IF(ISNUMBER(SEARCH("(RP)",J673)),O673,IF(RIGHT(TRIM(J673),3)=", S",O673,0)) -> 0 | AA673: =IF(ISNUMBER(SEARCH("(RP)",J673)),O673,IF(RIGHT(TRIM(J673),3)=", M",O673,0)) -> 269 | AB673: =IF(ISNUMBER(SEARCH("(RP)",J673)),O673,IF(RIGHT(TRIM(J673),3)=", L",O673,0)) -> 0 | AC673: =IF(ISNUMBER(SEARCH("(RP)",J673)),O673,IF(RIGHT(TRIM(J673),4)=", XL",O673,0)) -> 0 | AD673: =IF(ISNUMBER(SEARCH("(RP)",J673)),O673,IF(OR(RIGHT(TRIM(J673),5)=", XXL",RIGHT(TRIM(J673),5)=", 2XL"),O673,0)) -> 0 | AE673: {=IFERROR(_xlfn.XLOOKUP(H673,Sheet1!$G:$G,Sheet1!$F:$F),IFERROR(_xlfn.XLOOKUP(1,(--($X$2:$X$1074=X673))*(--ISNUMBER(MATCH($H$2:$H$1074,Sheet1!$G:$G,0))),_xlfn.XLOOKUP($H$2:$H$1074,Sheet1!$G:$G,Sheet1!$F:$F,"")),"NOT FOUND"))} -> YETKRTSCUT5008 | AF673: =IFERROR(IF(ISNUMBER(SEARCH("(RP)",J673)),TRIM(SUBSTITUTE(MID(J673,10,LEN(J673)),"(RP)","")),TRIM(MID(J673,FIND(",",J673)+1,FIND(",",J673,FIND(",",J673)+1)-FIND(",",J673)-1))),"") -> RUST | AG673: =IF(A673="SZAF","Bangalore",IF(A673="SAEX","JHAJJAR",IF(A673="S0EU","HARIPAL",""))) -> HARIPAL | AH673: =IF(OR(J673="",AE673="",AE673="NOT FOUND"),"",IF(Y673="RP",IFERROR(LEFT(_xlfn.XLOOKUP(AE673,Sheet1!$F:$F,Sheet1!$W:$W),FIND("-",_xlfn.XLOOKUP(AE673,Sheet1!$F:$F,Sheet1!$W:$W),FIND("-",_xlfn.XLOOKUP(AE673,Sheet1!$F:$F,Sheet1!$W:$W))+1))&AE673,"NOT FOUND"),LEFT(J673,FIND("-",J673,FIND("-",J673)+1))&AE673)) -> KRTS-APSU26-YETKRTSCUT5008
A674: S0EU | B674: 5112963724 | C674: 30.01.2026 | D674: 30.06.2026 | E674: 10337044 | F674: UNITED TEXTILE MILLS PRIVATE LIMITE | G674: 6 | H674: 8909103992477 | I674: 441857089015 | J674: KRTS-APSU26-YETKRTSCUT5008, RUST, S | L674: EA | M674: 1 | N674: 269 | O674: 269 | Q674: 0 | R674: 0 | S674: 0 | T674: 0 | U674: 0 | X674: =IF(ISNUMBER(VALUE(LEFT(J674,1))),LEFT(J674,MIN(IFERROR(FIND("A",UPPER(J674)),LEN(J674)+1),IFERROR(FIND("B",UPPER(J674)),LEN(J674)+1),IFERROR(FIND("C",UPPER(J674)),LEN(J674)+1),IFERROR(FIND("D",UPPER(J674)),LEN(J674)+1),IFERROR(FIND("E",UPPER(J674)),LEN(J674)+1),IFERROR(FIND("F",UPPER(J674)),LEN(J674)+1),IFERROR(FIND("G",UPPER(J674)),LEN(J674)+1),IFERROR(FIND("H",UPPER(J674)),LEN(J674)+1),IFERROR(FIND("I",UPPER(J674)),LEN(J674)+1),IFERROR(FIND("J",UPPER(J674)),LEN(J674)+1),IFERROR(FIND("K",UPPER(J674)),LEN(J674)+1),IFERROR(FIND("L",UPPER(J674)),LEN(J674)+1),IFERROR(FIND("M",UPPER(J674)),LEN(J674)+1),IFERROR(FIND("N",UPPER(J674)),LEN(J674)+1),IFERROR(FIND("O",UPPER(J674)),LEN(J674)+1),IFERROR(FIND("P",UPPER(J674)),LEN(J674)+1),IFERROR(FIND("Q",UPPER(J674)),LEN(J674)+1),IFERROR(FIND("R",UPPER(J674)),LEN(J674)+1),IFERROR(FIND("S",UPPER(J674)),LEN(J674)+1),IFERROR(FIND("T",UPPER(J674)),LEN(J674)+1),IFERROR(FIND("U",UPPER(J674)),LEN(J674)+1),IFERROR(FIND("V",UPPER(J674)),LEN(J674)+1),IFERROR(FIND("W",UPPER(J674)),LEN(J674)+1),IFERROR(FIND("X",UPPER(J674)),LEN(J674)+1),IFERROR(FIND("Y",UPPER(J674)),LEN(J674)+1),IFERROR(FIND("Z",UPPER(J674)),LEN(J674)+1))-1),LEFT(TEXT(I674,"0"),LEN(TEXT(I674,"0"))-3)) -> 441857089 | Y674: =IF(ISNUMBER(SEARCH("(RP)",J674)),"RP","DC") -> DC | Z674: =IF(ISNUMBER(SEARCH("(RP)",J674)),O674,IF(RIGHT(TRIM(J674),3)=", S",O674,0)) -> 269 | AA674: =IF(ISNUMBER(SEARCH("(RP)",J674)),O674,IF(RIGHT(TRIM(J674),3)=", M",O674,0)) -> 0 | AB674: =IF(ISNUMBER(SEARCH("(RP)",J674)),O674,IF(RIGHT(TRIM(J674),3)=", L",O674,0)) -> 0 | AC674: =IF(ISNUMBER(SEARCH("(RP)",J674)),O674,IF(RIGHT(TRIM(J674),4)=", XL",O674,0)) -> 0 | AD674: =IF(ISNUMBER(SEARCH("(RP)",J674)),O674,IF(OR(RIGHT(TRIM(J674),5)=", XXL",RIGHT(TRIM(J674),5)=", 2XL"),O674,0)) -> 0 | AE674: {=IFERROR(_xlfn.XLOOKUP(H674,Sheet1!$G:$G,Sheet1!$F:$F),IFERROR(_xlfn.XLOOKUP(1,(--($X$2:$X$1074=X674))*(--ISNUMBER(MATCH($H$2:$H$1074,Sheet1!$G:$G,0))),_xlfn.XLOOKUP($H$2:$H$1074,Sheet1!$G:$G,Sheet1!$F:$F,"")),"NOT FOUND"))} -> YETKRTSCUT5008 | AF674: =IFERROR(IF(ISNUMBER(SEARCH("(RP)",J674)),TRIM(SUBSTITUTE(MID(J674,10,LEN(J674)),"(RP)","")),TRIM(MID(J674,FIND(",",J674)+1,FIND(",",J674,FIND(",",J674)+1)-FIND(",",J674)-1))),"") -> RUST | AG674: =IF(A674="SZAF","Bangalore",IF(A674="SAEX","JHAJJAR",IF(A674="S0EU","HARIPAL",""))) -> HARIPAL | AH674: =IF(OR(J674="",AE674="",AE674="NOT FOUND"),"",IF(Y674="RP",IFERROR(LEFT(_xlfn.XLOOKUP(AE674,Sheet1!$F:$F,Sheet1!$W:$W),FIND("-",_xlfn.XLOOKUP(AE674,Sheet1!$F:$F,Sheet1!$W:$W),FIND("-",_xlfn.XLOOKUP(AE674,Sheet1!$F:$F,Sheet1!$W:$W))+1))&AE674,"NOT FOUND"),LEFT(J674,FIND("-",J674,FIND("-",J674)+1))&AE674)) -> KRTS-APSU26-YETKRTSCUT5008
A675: SZAF | B675: 5112793037 | C675: 14.01.2026 | D675: 30.04.2026 | E675: 10337044 | F675: UNITED TEXTILE MILLS PRIVATE LIMITE | G675: 1 | H675: 8909284019864 | I675: 441857093001 | J675: KRTS-APSU26-RETKRTSCUT5007, BLACK, S | L675: EA | M675: 1 | N675: 30 | O675: 30 | Q675: 204.3 | R675: 204.3 | S675: 306.45 | T675: 6129 | U675: 5 | V675: INR | X675: =IF(ISNUMBER(VALUE(LEFT(J675,1))),LEFT(J675,MIN(IFERROR(FIND("A",UPPER(J675)),LEN(J675)+1),IFERROR(FIND("B",UPPER(J675)),LEN(J675)+1),IFERROR(FIND("C",UPPER(J675)),LEN(J675)+1),IFERROR(FIND("D",UPPER(J675)),LEN(J675)+1),IFERROR(FIND("E",UPPER(J675)),LEN(J675)+1),IFERROR(FIND("F",UPPER(J675)),LEN(J675)+1),IFERROR(FIND("G",UPPER(J675)),LEN(J675)+1),IFERROR(FIND("H",UPPER(J675)),LEN(J675)+1),IFERROR(FIND("I",UPPER(J675)),LEN(J675)+1),IFERROR(FIND("J",UPPER(J675)),LEN(J675)+1),IFERROR(FIND("K",UPPER(J675)),LEN(J675)+1),IFERROR(FIND("L",UPPER(J675)),LEN(J675)+1),IFERROR(FIND("M",UPPER(J675)),LEN(J675)+1),IFERROR(FIND("N",UPPER(J675)),LEN(J675)+1),IFERROR(FIND("O",UPPER(J675)),LEN(J675)+1),IFERROR(FIND("P",UPPER(J675)),LEN(J675)+1),IFERROR(FIND("Q",UPPER(J675)),LEN(J675)+1),IFERROR(FIND("R",UPPER(J675)),LEN(J675)+1),IFERROR(FIND("S",UPPER(J675)),LEN(J675)+1),IFERROR(FIND("T",UPPER(J675)),LEN(J675)+1),IFERROR(FIND("U",UPPER(J675)),LEN(J675)+1),IFERROR(FIND("V",UPPER(J675)),LEN(J675)+1),IFERROR(FIND("W",UPPER(J675)),LEN(J675)+1),IFERROR(FIND("X",UPPER(J675)),LEN(J675)+1),IFERROR(FIND("Y",UPPER(J675)),LEN(J675)+1),IFERROR(FIND("Z",UPPER(J675)),LEN(J675)+1))-1),LEFT(TEXT(I675,"0"),LEN(TEXT(I675,"0"))-3)) -> 441857093 | Y675: =IF(ISNUMBER(SEARCH("(RP)",J675)),"RP","DC") -> DC | Z675: =IF(ISNUMBER(SEARCH("(RP)",J675)),O675,IF(RIGHT(TRIM(J675),3)=", S",O675,0)) -> 30 | AA675: =IF(ISNUMBER(SEARCH("(RP)",J675)),O675,IF(RIGHT(TRIM(J675),3)=", M",O675,0)) -> 0 | AB675: =IF(ISNUMBER(SEARCH("(RP)",J675)),O675,IF(RIGHT(TRIM(J675),3)=", L",O675,0)) -> 0 | AC675: =IF(ISNUMBER(SEARCH("(RP)",J675)),O675,IF(RIGHT(TRIM(J675),4)=", XL",O675,0)) -> 0 | AD675: =IF(ISNUMBER(SEARCH("(RP)",J675)),O675,IF(OR(RIGHT(TRIM(J675),5)=", XXL",RIGHT(TRIM(J675),5)=", 2XL"),O675,0)) -> 0 | AE675: {=IFERROR(_xlfn.XLOOKUP(H675,Sheet1!$G:$G,Sheet1!$F:$F),IFERROR(_xlfn.XLOOKUP(1,(--($X$2:$X$1074=X675))*(--ISNUMBER(MATCH($H$2:$H$1074,Sheet1!$G:$G,0))),_xlfn.XLOOKUP($H$2:$H$1074,Sheet1!$G:$G,Sheet1!$F:$F,"")),"NOT FOUND"))} -> RETKRTSCUT5007 | AF675: =IFERROR(IF(ISNUMBER(SEARCH("(RP)",J675)),TRIM(SUBSTITUTE(MID(J675,10,LEN(J675)),"(RP)","")),TRIM(MID(J675,FIND(",",J675)+1,FIND(",",J675,FIND(",",J675)+1)-FIND(",",J675)-1))),"") -> BLACK | AG675: =IF(A675="SZAF","Bangalore",IF(A675="SAEX","JHAJJAR",IF(A675="S0EU","HARIPAL",""))) -> Bangalore | AH675: =IF(OR(J675="",AE675="",AE675="NOT FOUND"),"",IF(Y675="RP",IFERROR(LEFT(_xlfn.XLOOKUP(AE675,Sheet1!$F:$F,Sheet1!$W:$W),FIND("-",_xlfn.XLOOKUP(AE675,Sheet1!$F:$F,Sheet1!$W:$W),FIND("-",_xlfn.XLOOKUP(AE675,Sheet1!$F:$F,Sheet1!$W:$W))+1))&AE675,"NOT FOUND"),LEFT(J675,FIND("-",J675,FIND("-",J675)+1))&AE675)) -> KRTS-APSU26-RETKRTSCUT5007
A676: SZAF | B676: 5112793037 | C676: 14.01.2026 | D676: 30.04.2026 | E676: 10337044 | F676: UNITED TEXTILE MILLS PRIVATE LIMITE | G676: 2 | H676: 8909284019857 | I676: 441857093002 | J676: KRTS-APSU26-RETKRTSCUT5007, BLACK, M | L676: EA | M676: 1 | N676: 363 | O676: 363 | Q676: 204.3 | R676: 204.3 | S676: 3708.05 | T676: 74160.9 | U676: 5 | V676: INR | X676: =IF(ISNUMBER(VALUE(LEFT(J676,1))),LEFT(J676,MIN(IFERROR(FIND("A",UPPER(J676)),LEN(J676)+1),IFERROR(FIND("B",UPPER(J676)),LEN(J676)+1),IFERROR(FIND("C",UPPER(J676)),LEN(J676)+1),IFERROR(FIND("D",UPPER(J676)),LEN(J676)+1),IFERROR(FIND("E",UPPER(J676)),LEN(J676)+1),IFERROR(FIND("F",UPPER(J676)),LEN(J676)+1),IFERROR(FIND("G",UPPER(J676)),LEN(J676)+1),IFERROR(FIND("H",UPPER(J676)),LEN(J676)+1),IFERROR(FIND("I",UPPER(J676)),LEN(J676)+1),IFERROR(FIND("J",UPPER(J676)),LEN(J676)+1),IFERROR(FIND("K",UPPER(J676)),LEN(J676)+1),IFERROR(FIND("L",UPPER(J676)),LEN(J676)+1),IFERROR(FIND("M",UPPER(J676)),LEN(J676)+1),IFERROR(FIND("N",UPPER(J676)),LEN(J676)+1),IFERROR(FIND("O",UPPER(J676)),LEN(J676)+1),IFERROR(FIND("P",UPPER(J676)),LEN(J676)+1),IFERROR(FIND("Q",UPPER(J676)),LEN(J676)+1),IFERROR(FIND("R",UPPER(J676)),LEN(J676)+1),IFERROR(FIND("S",UPPER(J676)),LEN(J676)+1),IFERROR(FIND("T",UPPER(J676)),LEN(J676)+1),IFERROR(FIND("U",UPPER(J676)),LEN(J676)+1),IFERROR(FIND("V",UPPER(J676)),LEN(J676)+1),IFERROR(FIND("W",UPPER(J676)),LEN(J676)+1),IFERROR(FIND("X",UPPER(J676)),LEN(J676)+1),IFERROR(FIND("Y",UPPER(J676)),LEN(J676)+1),IFERROR(FIND("Z",UPPER(J676)),LEN(J676)+1))-1),LEFT(TEXT(I676,"0"),LEN(TEXT(I676,"0"))-3)) -> 441857093 | Y676: =IF(ISNUMBER(SEARCH("(RP)",J676)),"RP","DC") -> DC | Z676: =IF(ISNUMBER(SEARCH("(RP)",J676)),O676,IF(RIGHT(TRIM(J676),3)=", S",O676,0)) -> 0 | AA676: =IF(ISNUMBER(SEARCH("(RP)",J676)),O676,IF(RIGHT(TRIM(J676),3)=", M",O676,0)) -> 363 | AB676: =IF(ISNUMBER(SEARCH("(RP)",J676)),O676,IF(RIGHT(TRIM(J676),3)=", L",O676,0)) -> 0 | AC676: =IF(ISNUMBER(SEARCH("(RP)",J676)),O676,IF(RIGHT(TRIM(J676),4)=", XL",O676,0)) -> 0 | AD676: =IF(ISNUMBER(SEARCH("(RP)",J676)),O676,IF(OR(RIGHT(TRIM(J676),5)=", XXL",RIGHT(TRIM(J676),5)=", 2XL"),O676,0)) -> 0 | AE676: {=IFERROR(_xlfn.XLOOKUP(H676,Sheet1!$G:$G,Sheet1!$F:$F),IFERROR(_xlfn.XLOOKUP(1,(--($X$2:$X$1074=X676))*(--ISNUMBER(MATCH($H$2:$H$1074,Sheet1!$G:$G,0))),_xlfn.XLOOKUP($H$2:$H$1074,Sheet1!$G:$G,Sheet1!$F:$F,"")),"NOT FOUND"))} -> RETKRTSCUT5007 | AF676: =IFERROR(IF(ISNUMBER(SEARCH("(RP)",J676)),TRIM(SUBSTITUTE(MID(J676,10,LEN(J676)),"(RP)","")),TRIM(MID(J676,FIND(",",J676)+1,FIND(",",J676,FIND(",",J676)+1)-FIND(",",J676)-1))),"") -> BLACK | AG676: =IF(A676="SZAF","Bangalore",IF(A676="SAEX","JHAJJAR",IF(A676="S0EU","HARIPAL",""))) -> Bangalore | AH676: =IF(OR(J676="",AE676="",AE676="NOT FOUND"),"",IF(Y676="RP",IFERROR(LEFT(_xlfn.XLOOKUP(AE676,Sheet1!$F:$F,Sheet1!$W:$W),FIND("-",_xlfn.XLOOKUP(AE676,Sheet1!$F:$F,Sheet1!$W:$W),FIND("-",_xlfn.XLOOKUP(AE676,Sheet1!$F:$F,Sheet1!$W:$W))+1))&AE676,"NOT FOUND"),LEFT(J676,FIND("-",J676,FIND("-",J676)+1))&AE676)) -> KRTS-APSU26-RETKRTSCUT5007
A677: SZAF | B677: 5112793037 | C677: 14.01.2026 | D677: 30.04.2026 | E677: 10337044 | F677: UNITED TEXTILE MILLS PRIVATE LIMITE | G677: 3 | H677: 8909284019840 | I677: 441857093003 | J677: KRTS-APSU26-RETKRTSCUT5007, BLACK, L | L677: EA | M677: 1 | N677: 409 | O677: 409 | Q677: 204.3 | R677: 204.3 | S677: 4177.94 | T677: 83558.7 | U677: 5 | V677: INR | X677: =IF(ISNUMBER(VALUE(LEFT(J677,1))),LEFT(J677,MIN(IFERROR(FIND("A",UPPER(J677)),LEN(J677)+1),IFERROR(FIND("B",UPPER(J677)),LEN(J677)+1),IFERROR(FIND("C",UPPER(J677)),LEN(J677)+1),IFERROR(FIND("D",UPPER(J677)),LEN(J677)+1),IFERROR(FIND("E",UPPER(J677)),LEN(J677)+1),IFERROR(FIND("F",UPPER(J677)),LEN(J677)+1),IFERROR(FIND("G",UPPER(J677)),LEN(J677)+1),IFERROR(FIND("H",UPPER(J677)),LEN(J677)+1),IFERROR(FIND("I",UPPER(J677)),LEN(J677)+1),IFERROR(FIND("J",UPPER(J677)),LEN(J677)+1),IFERROR(FIND("K",UPPER(J677)),LEN(J677)+1),IFERROR(FIND("L",UPPER(J677)),LEN(J677)+1),IFERROR(FIND("M",UPPER(J677)),LEN(J677)+1),IFERROR(FIND("N",UPPER(J677)),LEN(J677)+1),IFERROR(FIND("O",UPPER(J677)),LEN(J677)+1),IFERROR(FIND("P",UPPER(J677)),LEN(J677)+1),IFERROR(FIND("Q",UPPER(J677)),LEN(J677)+1),IFERROR(FIND("R",UPPER(J677)),LEN(J677)+1),IFERROR(FIND("S",UPPER(J677)),LEN(J677)+1),IFERROR(FIND("T",UPPER(J677)),LEN(J677)+1),IFERROR(FIND("U",UPPER(J677)),LEN(J677)+1),IFERROR(FIND("V",UPPER(J677)),LEN(J677)+1),IFERROR(FIND("W",UPPER(J677)),LEN(J677)+1),IFERROR(FIND("X",UPPER(J677)),LEN(J677)+1),IFERROR(FIND("Y",UPPER(J677)),LEN(J677)+1),IFERROR(FIND("Z",UPPER(J677)),LEN(J677)+1))-1),LEFT(TEXT(I677,"0"),LEN(TEXT(I677,"0"))-3)) -> 441857093 | Y677: =IF(ISNUMBER(SEARCH("(RP)",J677)),"RP","DC") -> DC | Z677: =IF(ISNUMBER(SEARCH("(RP)",J677)),O677,IF(RIGHT(TRIM(J677),3)=", S",O677,0)) -> 0 | AA677: =IF(ISNUMBER(SEARCH("(RP)",J677)),O677,IF(RIGHT(TRIM(J677),3)=", M",O677,0)) -> 0 | AB677: =IF(ISNUMBER(SEARCH("(RP)",J677)),O677,IF(RIGHT(TRIM(J677),3)=", L",O677,0)) -> 409 | AC677: =IF(ISNUMBER(SEARCH("(RP)",J677)),O677,IF(RIGHT(TRIM(J677),4)=", XL",O677,0)) -> 0 | AD677: =IF(ISNUMBER(SEARCH("(RP)",J677)),O677,IF(OR(RIGHT(TRIM(J677),5)=", XXL",RIGHT(TRIM(J677),5)=", 2XL"),O677,0)) -> 0 | AE677: {=IFERROR(_xlfn.XLOOKUP(H677,Sheet1!$G:$G,Sheet1!$F:$F),IFERROR(_xlfn.XLOOKUP(1,(--($X$2:$X$1074=X677))*(--ISNUMBER(MATCH($H$2:$H$1074,Sheet1!$G:$G,0))),_xlfn.XLOOKUP($H$2:$H$1074,Sheet1!$G:$G,Sheet1!$F:$F,"")),"NOT FOUND"))} -> RETKRTSCUT5007 | AF677: =IFERROR(IF(ISNUMBER(SEARCH("(RP)",J677)),TRIM(SUBSTITUTE(MID(J677,10,LEN(J677)),"(RP)","")),TRIM(MID(J677,FIND(",",J677)+1,FIND(",",J677,FIND(",",J677)+1)-FIND(",",J677)-1))),"") -> BLACK | AG677: =IF(A677="SZAF","Bangalore",IF(A677="SAEX","JHAJJAR",IF(A677="S0EU","HARIPAL",""))) -> Bangalore | AH677: =IF(OR(J677="",AE677="",AE677="NOT FOUND"),"",IF(Y677="RP",IFERROR(LEFT(_xlfn.XLOOKUP(AE677,Sheet1!$F:$F,Sheet1!$W:$W),FIND("-",_xlfn.XLOOKUP(AE677,Sheet1!$F:$F,Sheet1!$W:$W),FIND("-",_xlfn.XLOOKUP(AE677,Sheet1!$F:$F,Sheet1!$W:$W))+1))&AE677,"NOT FOUND"),LEFT(J677,FIND("-",J677,FIND("-",J677)+1))&AE677)) -> KRTS-APSU26-RETKRTSCUT5007
A678: SZAF | B678: 5112793037 | C678: 14.01.2026 | D678: 30.04.2026 | E678: 10337044 | F678: UNITED TEXTILE MILLS PRIVATE LIMITE | G678: 4 | H678: 8909284019833 | I678: 441857093004 | J678: KRTS-APSU26-RETKRTSCUT5007, BLACK, XL | L678: EA | M678: 1 | N678: 477 | O678: 477 | Q678: 204.3 | R678: 204.3 | S678: 4872.56 | T678: 97451.1 | U678: 5 | V678: INR | X678: =IF(ISNUMBER(VALUE(LEFT(J678,1))),LEFT(J678,MIN(IFERROR(FIND("A",UPPER(J678)),LEN(J678)+1),IFERROR(FIND("B",UPPER(J678)),LEN(J678)+1),IFERROR(FIND("C",UPPER(J678)),LEN(J678)+1),IFERROR(FIND("D",UPPER(J678)),LEN(J678)+1),IFERROR(FIND("E",UPPER(J678)),LEN(J678)+1),IFERROR(FIND("F",UPPER(J678)),LEN(J678)+1),IFERROR(FIND("G",UPPER(J678)),LEN(J678)+1),IFERROR(FIND("H",UPPER(J678)),LEN(J678)+1),IFERROR(FIND("I",UPPER(J678)),LEN(J678)+1),IFERROR(FIND("J",UPPER(J678)),LEN(J678)+1),IFERROR(FIND("K",UPPER(J678)),LEN(J678)+1),IFERROR(FIND("L",UPPER(J678)),LEN(J678)+1),IFERROR(FIND("M",UPPER(J678)),LEN(J678)+1),IFERROR(FIND("N",UPPER(J678)),LEN(J678)+1),IFERROR(FIND("O",UPPER(J678)),LEN(J678)+1),IFERROR(FIND("P",UPPER(J678)),LEN(J678)+1),IFERROR(FIND("Q",UPPER(J678)),LEN(J678)+1),IFERROR(FIND("R",UPPER(J678)),LEN(J678)+1),IFERROR(FIND("S",UPPER(J678)),LEN(J678)+1),IFERROR(FIND("T",UPPER(J678)),LEN(J678)+1),IFERROR(FIND("U",UPPER(J678)),LEN(J678)+1),IFERROR(FIND("V",UPPER(J678)),LEN(J678)+1),IFERROR(FIND("W",UPPER(J678)),LEN(J678)+1),IFERROR(FIND("X",UPPER(J678)),LEN(J678)+1),IFERROR(FIND("Y",UPPER(J678)),LEN(J678)+1),IFERROR(FIND("Z",UPPER(J678)),LEN(J678)+1))-1),LEFT(TEXT(I678,"0"),LEN(TEXT(I678,"0"))-3)) -> 441857093 | Y678: =IF(ISNUMBER(SEARCH("(RP)",J678)),"RP","DC") -> DC | Z678: =IF(ISNUMBER(SEARCH("(RP)",J678)),O678,IF(RIGHT(TRIM(J678),3)=", S",O678,0)) -> 0 | AA678: =IF(ISNUMBER(SEARCH("(RP)",J678)),O678,IF(RIGHT(TRIM(J678),3)=", M",O678,0)) -> 0 | AB678: =IF(ISNUMBER(SEARCH("(RP)",J678)),O678,IF(RIGHT(TRIM(J678),3)=", L",O678,0)) -> 0 | AC678: =IF(ISNUMBER(SEARCH("(RP)",J678)),O678,IF(RIGHT(TRIM(J678),4)=", XL",O678,0)) -> 477 | AD678: =IF(ISNUMBER(SEARCH("(RP)",J678)),O678,IF(OR(RIGHT(TRIM(J678),5)=", XXL",RIGHT(TRIM(J678),5)=", 2XL"),O678,0)) -> 0 | AE678: {=IFERROR(_xlfn.XLOOKUP(H678,Sheet1!$G:$G,Sheet1!$F:$F),IFERROR(_xlfn.XLOOKUP(1,(--($X$2:$X$1074=X678))*(--ISNUMBER(MATCH($H$2:$H$1074,Sheet1!$G:$G,0))),_xlfn.XLOOKUP($H$2:$H$1074,Sheet1!$G:$G,Sheet1!$F:$F,"")),"NOT FOUND"))} -> RETKRTSCUT5007 | AF678: =IFERROR(IF(ISNUMBER(SEARCH("(RP)",J678)),TRIM(SUBSTITUTE(MID(J678,10,LEN(J678)),"(RP)","")),TRIM(MID(J678,FIND(",",J678)+1,FIND(",",J678,FIND(",",J678)+1)-FIND(",",J678)-1))),"") -> BLACK | AG678: =IF(A678="SZAF","Bangalore",IF(A678="SAEX","JHAJJAR",IF(A678="S0EU","HARIPAL",""))) -> Bangalore | AH678: =IF(OR(J678="",AE678="",AE678="NOT FOUND"),"",IF(Y678="RP",IFERROR(LEFT(_xlfn.XLOOKUP(AE678,Sheet1!$F:$F,Sheet1!$W:$W),FIND("-",_xlfn.XLOOKUP(AE678,Sheet1!$F:$F,Sheet1!$W:$W),FIND("-",_xlfn.XLOOKUP(AE678,Sheet1!$F:$F,Sheet1!$W:$W))+1))&AE678,"NOT FOUND"),LEFT(J678,FIND("-",J678,FIND("-",J678)+1))&AE678)) -> KRTS-APSU26-RETKRTSCUT5007
A679: SZAF | B679: 5112793037 | C679: 14.01.2026 | D679: 30.04.2026 | E679: 10337044 | F679: UNITED TEXTILE MILLS PRIVATE LIMITE | G679: 5 | H679: 8909284019826 | I679: 441857093005 | J679: KRTS-APSU26-RETKRTSCUT5007, BLACK, 2XL | L679: EA | M679: 1 | N679: 90 | O679: 90 | Q679: 204.3 | R679: 204.3 | S679: 919.35 | T679: 18387 | U679: 5 | V679: INR | X679: =IF(ISNUMBER(VALUE(LEFT(J679,1))),LEFT(J679,MIN(IFERROR(FIND("A",UPPER(J679)),LEN(J679)+1),IFERROR(FIND("B",UPPER(J679)),LEN(J679)+1),IFERROR(FIND("C",UPPER(J679)),LEN(J679)+1),IFERROR(FIND("D",UPPER(J679)),LEN(J679)+1),IFERROR(FIND("E",UPPER(J679)),LEN(J679)+1),IFERROR(FIND("F",UPPER(J679)),LEN(J679)+1),IFERROR(FIND("G",UPPER(J679)),LEN(J679)+1),IFERROR(FIND("H",UPPER(J679)),LEN(J679)+1),IFERROR(FIND("I",UPPER(J679)),LEN(J679)+1),IFERROR(FIND("J",UPPER(J679)),LEN(J679)+1),IFERROR(FIND("K",UPPER(J679)),LEN(J679)+1),IFERROR(FIND("L",UPPER(J679)),LEN(J679)+1),IFERROR(FIND("M",UPPER(J679)),LEN(J679)+1),IFERROR(FIND("N",UPPER(J679)),LEN(J679)+1),IFERROR(FIND("O",UPPER(J679)),LEN(J679)+1),IFERROR(FIND("P",UPPER(J679)),LEN(J679)+1),IFERROR(FIND("Q",UPPER(J679)),LEN(J679)+1),IFERROR(FIND("R",UPPER(J679)),LEN(J679)+1),IFERROR(FIND("S",UPPER(J679)),LEN(J679)+1),IFERROR(FIND("T",UPPER(J679)),LEN(J679)+1),IFERROR(FIND("U",UPPER(J679)),LEN(J679)+1),IFERROR(FIND("V",UPPER(J679)),LEN(J679)+1),IFERROR(FIND("W",UPPER(J679)),LEN(J679)+1),IFERROR(FIND("X",UPPER(J679)),LEN(J679)+1),IFERROR(FIND("Y",UPPER(J679)),LEN(J679)+1),IFERROR(FIND("Z",UPPER(J679)),LEN(J679)+1))-1),LEFT(TEXT(I679,"0"),LEN(TEXT(I679,"0"))-3)) -> 441857093 | Y679: =IF(ISNUMBER(SEARCH("(RP)",J679)),"RP","DC") -> DC | Z679: =IF(ISNUMBER(SEARCH("(RP)",J679)),O679,IF(RIGHT(TRIM(J679),3)=", S",O679,0)) -> 0 | AA679: =IF(ISNUMBER(SEARCH("(RP)",J679)),O679,IF(RIGHT(TRIM(J679),3)=", M",O679,0)) -> 0 | AB679: =IF(ISNUMBER(SEARCH("(RP)",J679)),O679,IF(RIGHT(TRIM(J679),3)=", L",O679,0)) -> 0 | AC679: =IF(ISNUMBER(SEARCH("(RP)",J679)),O679,IF(RIGHT(TRIM(J679),4)=", XL",O679,0)) -> 0 | AD679: =IF(ISNUMBER(SEARCH("(RP)",J679)),O679,IF(OR(RIGHT(TRIM(J679),5)=", XXL",RIGHT(TRIM(J679),5)=", 2XL"),O679,0)) -> 90 | AE679: {=IFERROR(_xlfn.XLOOKUP(H679,Sheet1!$G:$G,Sheet1!$F:$F),IFERROR(_xlfn.XLOOKUP(1,(--($X$2:$X$1074=X679))*(--ISNUMBER(MATCH($H$2:$H$1074,Sheet1!$G:$G,0))),_xlfn.XLOOKUP($H$2:$H$1074,Sheet1!$G:$G,Sheet1!$F:$F,"")),"NOT FOUND"))} -> RETKRTSCUT5007 | AF679: =IFERROR(IF(ISNUMBER(SEARCH("(RP)",J679)),TRIM(SUBSTITUTE(MID(J679,10,LEN(J679)),"(RP)","")),TRIM(MID(J679,FIND(",",J679)+1,FIND(",",J679,FIND(",",J679)+1)-FIND(",",J679)-1))),"") -> BLACK | AG679: =IF(A679="SZAF","Bangalore",IF(A679="SAEX","JHAJJAR",IF(A679="S0EU","HARIPAL",""))) -> Bangalore | AH679: =IF(OR(J679="",AE679="",AE679="NOT FOUND"),"",IF(Y679="RP",IFERROR(LEFT(_xlfn.XLOOKUP(AE679,Sheet1!$F:$F,Sheet1!$W:$W),FIND("-",_xlfn.XLOOKUP(AE679,Sheet1!$F:$F,Sheet1!$W:$W),FIND("-",_xlfn.XLOOKUP(AE679,Sheet1!$F:$F,Sheet1!$W:$W))+1))&AE679,"NOT FOUND"),LEFT(J679,FIND("-",J679,FIND("-",J679)+1))&AE679)) -> KRTS-APSU26-RETKRTSCUT5007
A680: SAEX | B680: 5112793031 | C680: 14.01.2026 | D680: 30.04.2026 | E680: 10337044 | F680: UNITED TEXTILE MILLS PRIVATE LIMITE | G680: 1 | H680: 8909284019864 | I680: 441857093001 | J680: KRTS-APSU26-RETKRTSCUT5007, BLACK, S | L680: EA | M680: 1 | N680: 30 | O680: 30 | Q680: 204.3 | R680: 204.3 | S680: 306.45 | T680: 6129 | U680: 5 | V680: INR | X680: =IF(ISNUMBER(VALUE(LEFT(J680,1))),LEFT(J680,MIN(IFERROR(FIND("A",UPPER(J680)),LEN(J680)+1),IFERROR(FIND("B",UPPER(J680)),LEN(J680)+1),IFERROR(FIND("C",UPPER(J680)),LEN(J680)+1),IFERROR(FIND("D",UPPER(J680)),LEN(J680)+1),IFERROR(FIND("E",UPPER(J680)),LEN(J680)+1),IFERROR(FIND("F",UPPER(J680)),LEN(J680)+1),IFERROR(FIND("G",UPPER(J680)),LEN(J680)+1),IFERROR(FIND("H",UPPER(J680)),LEN(J680)+1),IFERROR(FIND("I",UPPER(J680)),LEN(J680)+1),IFERROR(FIND("J",UPPER(J680)),LEN(J680)+1),IFERROR(FIND("K",UPPER(J680)),LEN(J680)+1),IFERROR(FIND("L",UPPER(J680)),LEN(J680)+1),IFERROR(FIND("M",UPPER(J680)),LEN(J680)+1),IFERROR(FIND("N",UPPER(J680)),LEN(J680)+1),IFERROR(FIND("O",UPPER(J680)),LEN(J680)+1),IFERROR(FIND("P",UPPER(J680)),LEN(J680)+1),IFERROR(FIND("Q",UPPER(J680)),LEN(J680)+1),IFERROR(FIND("R",UPPER(J680)),LEN(J680)+1),IFERROR(FIND("S",UPPER(J680)),LEN(J680)+1),IFERROR(FIND("T",UPPER(J680)),LEN(J680)+1),IFERROR(FIND("U",UPPER(J680)),LEN(J680)+1),IFERROR(FIND("V",UPPER(J680)),LEN(J680)+1),IFERROR(FIND("W",UPPER(J680)),LEN(J680)+1),IFERROR(FIND("X",UPPER(J680)),LEN(J680)+1),IFERROR(FIND("Y",UPPER(J680)),LEN(J680)+1),IFERROR(FIND("Z",UPPER(J680)),LEN(J680)+1))-1),LEFT(TEXT(I680,"0"),LEN(TEXT(I680,"0"))-3)) -> 441857093 | Y680: =IF(ISNUMBER(SEARCH("(RP)",J680)),"RP","DC") -> DC | Z680: =IF(ISNUMBER(SEARCH("(RP)",J680)),O680,IF(RIGHT(TRIM(J680),3)=", S",O680,0)) -> 30 | AA680: =IF(ISNUMBER(SEARCH("(RP)",J680)),O680,IF(RIGHT(TRIM(J680),3)=", M",O680,0)) -> 0 | AB680: =IF(ISNUMBER(SEARCH("(RP)",J680)),O680,IF(RIGHT(TRIM(J680),3)=", L",O680,0)) -> 0 | AC680: =IF(ISNUMBER(SEARCH("(RP)",J680)),O680,IF(RIGHT(TRIM(J680),4)=", XL",O680,0)) -> 0 | AD680: =IF(ISNUMBER(SEARCH("(RP)",J680)),O680,IF(OR(RIGHT(TRIM(J680),5)=", XXL",RIGHT(TRIM(J680),5)=", 2XL"),O680,0)) -> 0 | AE680: {=IFERROR(_xlfn.XLOOKUP(H680,Sheet1!$G:$G,Sheet1!$F:$F),IFERROR(_xlfn.XLOOKUP(1,(--($X$2:$X$1074=X680))*(--ISNUMBER(MATCH($H$2:$H$1074,Sheet1!$G:$G,0))),_xlfn.XLOOKUP($H$2:$H$1074,Sheet1!$G:$G,Sheet1!$F:$F,"")),"NOT FOUND"))} -> RETKRTSCUT5007 | AF680: =IFERROR(IF(ISNUMBER(SEARCH("(RP)",J680)),TRIM(SUBSTITUTE(MID(J680,10,LEN(J680)),"(RP)","")),TRIM(MID(J680,FIND(",",J680)+1,FIND(",",J680,FIND(",",J680)+1)-FIND(",",J680)-1))),"") -> BLACK | AG680: =IF(A680="SZAF","Bangalore",IF(A680="SAEX","JHAJJAR",IF(A680="S0EU","HARIPAL",""))) -> JHAJJAR | AH680: =IF(OR(J680="",AE680="",AE680="NOT FOUND"),"",IF(Y680="RP",IFERROR(LEFT(_xlfn.XLOOKUP(AE680,Sheet1!$F:$F,Sheet1!$W:$W),FIND("-",_xlfn.XLOOKUP(AE680,Sheet1!$F:$F,Sheet1!$W:$W),FIND("-",_xlfn.XLOOKUP(AE680,Sheet1!$F:$F,Sheet1!$W:$W))+1))&AE680,"NOT FOUND"),LEFT(J680,FIND("-",J680,FIND("-",J680)+1))&AE680)) -> KRTS-APSU26-RETKRTSCUT5007
A681: SAEX | B681: 5112793031 | C681: 14.01.2026 | D681: 30.04.2026 | E681: 10337044 | F681: UNITED TEXTILE MILLS PRIVATE LIMITE | G681: 2 | H681: 8909284019857 | I681: 441857093002 | J681: KRTS-APSU26-RETKRTSCUT5007, BLACK, M | L681: EA | M681: 1 | N681: 183 | O681: 183 | Q681: 204.3 | R681: 204.3 | S681: 1869.35 | T681: 37386.9 | U681: 5 | V681: INR | X681: =IF(ISNUMBER(VALUE(LEFT(J681,1))),LEFT(J681,MIN(IFERROR(FIND("A",UPPER(J681)),LEN(J681)+1),IFERROR(FIND("B",UPPER(J681)),LEN(J681)+1),IFERROR(FIND("C",UPPER(J681)),LEN(J681)+1),IFERROR(FIND("D",UPPER(J681)),LEN(J681)+1),IFERROR(FIND("E",UPPER(J681)),LEN(J681)+1),IFERROR(FIND("F",UPPER(J681)),LEN(J681)+1),IFERROR(FIND("G",UPPER(J681)),LEN(J681)+1),IFERROR(FIND("H",UPPER(J681)),LEN(J681)+1),IFERROR(FIND("I",UPPER(J681)),LEN(J681)+1),IFERROR(FIND("J",UPPER(J681)),LEN(J681)+1),IFERROR(FIND("K",UPPER(J681)),LEN(J681)+1),IFERROR(FIND("L",UPPER(J681)),LEN(J681)+1),IFERROR(FIND("M",UPPER(J681)),LEN(J681)+1),IFERROR(FIND("N",UPPER(J681)),LEN(J681)+1),IFERROR(FIND("O",UPPER(J681)),LEN(J681)+1),IFERROR(FIND("P",UPPER(J681)),LEN(J681)+1),IFERROR(FIND("Q",UPPER(J681)),LEN(J681)+1),IFERROR(FIND("R",UPPER(J681)),LEN(J681)+1),IFERROR(FIND("S",UPPER(J681)),LEN(J681)+1),IFERROR(FIND("T",UPPER(J681)),LEN(J681)+1),IFERROR(FIND("U",UPPER(J681)),LEN(J681)+1),IFERROR(FIND("V",UPPER(J681)),LEN(J681)+1),IFERROR(FIND("W",UPPER(J681)),LEN(J681)+1),IFERROR(FIND("X",UPPER(J681)),LEN(J681)+1),IFERROR(FIND("Y",UPPER(J681)),LEN(J681)+1),IFERROR(FIND("Z",UPPER(J681)),LEN(J681)+1))-1),LEFT(TEXT(I681,"0"),LEN(TEXT(I681,"0"))-3)) -> 441857093 | Y681: =IF(ISNUMBER(SEARCH("(RP)",J681)),"RP","DC") -> DC | Z681: =IF(ISNUMBER(SEARCH("(RP)",J681)),O681,IF(RIGHT(TRIM(J681),3)=", S",O681,0)) -> 0 | AA681: =IF(ISNUMBER(SEARCH("(RP)",J681)),O681,IF(RIGHT(TRIM(J681),3)=", M",O681,0)) -> 183 | AB681: =IF(ISNUMBER(SEARCH("(RP)",J681)),O681,IF(RIGHT(TRIM(J681),3)=", L",O681,0)) -> 0 | AC681: =IF(ISNUMBER(SEARCH("(RP)",J681)),O681,IF(RIGHT(TRIM(J681),4)=", XL",O681,0)) -> 0 | AD681: =IF(ISNUMBER(SEARCH("(RP)",J681)),O681,IF(OR(RIGHT(TRIM(J681),5)=", XXL",RIGHT(TRIM(J681),5)=", 2XL"),O681,0)) -> 0 | AE681: {=IFERROR(_xlfn.XLOOKUP(H681,Sheet1!$G:$G,Sheet1!$F:$F),IFERROR(_xlfn.XLOOKUP(1,(--($X$2:$X$1074=X681))*(--ISNUMBER(MATCH($H$2:$H$1074,Sheet1!$G:$G,0))),_xlfn.XLOOKUP($H$2:$H$1074,Sheet1!$G:$G,Sheet1!$F:$F,"")),"NOT FOUND"))} -> RETKRTSCUT5007 | AF681: =IFERROR(IF(ISNUMBER(SEARCH("(RP)",J681)),TRIM(SUBSTITUTE(MID(J681,10,LEN(J681)),"(RP)","")),TRIM(MID(J681,FIND(",",J681)+1,FIND(",",J681,FIND(",",J681)+1)-FIND(",",J681)-1))),"") -> BLACK | AG681: =IF(A681="SZAF","Bangalore",IF(A681="SAEX","JHAJJAR",IF(A681="S0EU","HARIPAL",""))) -> JHAJJAR | AH681: =IF(OR(J681="",AE681="",AE681="NOT FOUND"),"",IF(Y681="RP",IFERROR(LEFT(_xlfn.XLOOKUP(AE681,Sheet1!$F:$F,Sheet1!$W:$W),FIND("-",_xlfn.XLOOKUP(AE681,Sheet1!$F:$F,Sheet1!$W:$W),FIND("-",_xlfn.XLOOKUP(AE681,Sheet1!$F:$F,Sheet1!$W:$W))+1))&AE681,"NOT FOUND"),LEFT(J681,FIND("-",J681,FIND("-",J681)+1))&AE681)) -> KRTS-APSU26-RETKRTSCUT5007
A682: SAEX | B682: 5112793031 | C682: 14.01.2026 | D682: 30.04.2026 | E682: 10337044 | F682: UNITED TEXTILE MILLS PRIVATE LIMITE | G682: 3 | H682: 8909284019840 | I682: 441857093003 | J682: KRTS-APSU26-RETKRTSCUT5007, BLACK, L | L682: EA | M682: 1 | N682: 205 | O682: 205 | Q682: 204.3 | R682: 204.3 | S682: 2094.08 | T682: 41881.5 | U682: 5 | V682: INR | X682: =IF(ISNUMBER(VALUE(LEFT(J682,1))),LEFT(J682,MIN(IFERROR(FIND("A",UPPER(J682)),LEN(J682)+1),IFERROR(FIND("B",UPPER(J682)),LEN(J682)+1),IFERROR(FIND("C",UPPER(J682)),LEN(J682)+1),IFERROR(FIND("D",UPPER(J682)),LEN(J682)+1),IFERROR(FIND("E",UPPER(J682)),LEN(J682)+1),IFERROR(FIND("F",UPPER(J682)),LEN(J682)+1),IFERROR(FIND("G",UPPER(J682)),LEN(J682)+1),IFERROR(FIND("H",UPPER(J682)),LEN(J682)+1),IFERROR(FIND("I",UPPER(J682)),LEN(J682)+1),IFERROR(FIND("J",UPPER(J682)),LEN(J682)+1),IFERROR(FIND("K",UPPER(J682)),LEN(J682)+1),IFERROR(FIND("L",UPPER(J682)),LEN(J682)+1),IFERROR(FIND("M",UPPER(J682)),LEN(J682)+1),IFERROR(FIND("N",UPPER(J682)),LEN(J682)+1),IFERROR(FIND("O",UPPER(J682)),LEN(J682)+1),IFERROR(FIND("P",UPPER(J682)),LEN(J682)+1),IFERROR(FIND("Q",UPPER(J682)),LEN(J682)+1),IFERROR(FIND("R",UPPER(J682)),LEN(J682)+1),IFERROR(FIND("S",UPPER(J682)),LEN(J682)+1),IFERROR(FIND("T",UPPER(J682)),LEN(J682)+1),IFERROR(FIND("U",UPPER(J682)),LEN(J682)+1),IFERROR(FIND("V",UPPER(J682)),LEN(J682)+1),IFERROR(FIND("W",UPPER(J682)),LEN(J682)+1),IFERROR(FIND("X",UPPER(J682)),LEN(J682)+1),IFERROR(FIND("Y",UPPER(J682)),LEN(J682)+1),IFERROR(FIND("Z",UPPER(J682)),LEN(J682)+1))-1),LEFT(TEXT(I682,"0"),LEN(TEXT(I682,"0"))-3)) -> 441857093 | Y682: =IF(ISNUMBER(SEARCH("(RP)",J682)),"RP","DC") -> DC | Z682: =IF(ISNUMBER(SEARCH("(RP)",J682)),O682,IF(RIGHT(TRIM(J682),3)=", S",O682,0)) -> 0 | AA682: =IF(ISNUMBER(SEARCH("(RP)",J682)),O682,IF(RIGHT(TRIM(J682),3)=", M",O682,0)) -> 0 | AB682: =IF(ISNUMBER(SEARCH("(RP)",J682)),O682,IF(RIGHT(TRIM(J682),3)=", L",O682,0)) -> 205 | AC682: =IF(ISNUMBER(SEARCH("(RP)",J682)),O682,IF(RIGHT(TRIM(J682),4)=", XL",O682,0)) -> 0 | AD682: =IF(ISNUMBER(SEARCH("(RP)",J682)),O682,IF(OR(RIGHT(TRIM(J682),5)=", XXL",RIGHT(TRIM(J682),5)=", 2XL"),O682,0)) -> 0 | AE682: {=IFERROR(_xlfn.XLOOKUP(H682,Sheet1!$G:$G,Sheet1!$F:$F),IFERROR(_xlfn.XLOOKUP(1,(--($X$2:$X$1074=X682))*(--ISNUMBER(MATCH($H$2:$H$1074,Sheet1!$G:$G,0))),_xlfn.XLOOKUP($H$2:$H$1074,Sheet1!$G:$G,Sheet1!$F:$F,"")),"NOT FOUND"))} -> RETKRTSCUT5007 | AF682: =IFERROR(IF(ISNUMBER(SEARCH("(RP)",J682)),TRIM(SUBSTITUTE(MID(J682,10,LEN(J682)),"(RP)","")),TRIM(MID(J682,FIND(",",J682)+1,FIND(",",J682,FIND(",",J682)+1)-FIND(",",J682)-1))),"") -> BLACK | AG682: =IF(A682="SZAF","Bangalore",IF(A682="SAEX","JHAJJAR",IF(A682="S0EU","HARIPAL",""))) -> JHAJJAR | AH682: =IF(OR(J682="",AE682="",AE682="NOT FOUND"),"",IF(Y682="RP",IFERROR(LEFT(_xlfn.XLOOKUP(AE682,Sheet1!$F:$F,Sheet1!$W:$W),FIND("-",_xlfn.XLOOKUP(AE682,Sheet1!$F:$F,Sheet1!$W:$W),FIND("-",_xlfn.XLOOKUP(AE682,Sheet1!$F:$F,Sheet1!$W:$W))+1))&AE682,"NOT FOUND"),LEFT(J682,FIND("-",J682,FIND("-",J682)+1))&AE682)) -> KRTS-APSU26-RETKRTSCUT5007
A683: SAEX | B683: 5112793031 | C683: 14.01.2026 | D683: 30.04.2026 | E683: 10337044 | F683: UNITED TEXTILE MILLS PRIVATE LIMITE | G683: 4 | H683: 8909284019833 | I683: 441857093004 | J683: KRTS-APSU26-RETKRTSCUT5007, BLACK, XL | L683: EA | M683: 1 | N683: 240 | O683: 240 | Q683: 204.3 | R683: 204.3 | S683: 2451.6 | T683: 49032 | U683: 5 | V683: INR | X683: =IF(ISNUMBER(VALUE(LEFT(J683,1))),LEFT(J683,MIN(IFERROR(FIND("A",UPPER(J683)),LEN(J683)+1),IFERROR(FIND("B",UPPER(J683)),LEN(J683)+1),IFERROR(FIND("C",UPPER(J683)),LEN(J683)+1),IFERROR(FIND("D",UPPER(J683)),LEN(J683)+1),IFERROR(FIND("E",UPPER(J683)),LEN(J683)+1),IFERROR(FIND("F",UPPER(J683)),LEN(J683)+1),IFERROR(FIND("G",UPPER(J683)),LEN(J683)+1),IFERROR(FIND("H",UPPER(J683)),LEN(J683)+1),IFERROR(FIND("I",UPPER(J683)),LEN(J683)+1),IFERROR(FIND("J",UPPER(J683)),LEN(J683)+1),IFERROR(FIND("K",UPPER(J683)),LEN(J683)+1),IFERROR(FIND("L",UPPER(J683)),LEN(J683)+1),IFERROR(FIND("M",UPPER(J683)),LEN(J683)+1),IFERROR(FIND("N",UPPER(J683)),LEN(J683)+1),IFERROR(FIND("O",UPPER(J683)),LEN(J683)+1),IFERROR(FIND("P",UPPER(J683)),LEN(J683)+1),IFERROR(FIND("Q",UPPER(J683)),LEN(J683)+1),IFERROR(FIND("R",UPPER(J683)),LEN(J683)+1),IFERROR(FIND("S",UPPER(J683)),LEN(J683)+1),IFERROR(FIND("T",UPPER(J683)),LEN(J683)+1),IFERROR(FIND("U",UPPER(J683)),LEN(J683)+1),IFERROR(FIND("V",UPPER(J683)),LEN(J683)+1),IFERROR(FIND("W",UPPER(J683)),LEN(J683)+1),IFERROR(FIND("X",UPPER(J683)),LEN(J683)+1),IFERROR(FIND("Y",UPPER(J683)),LEN(J683)+1),IFERROR(FIND("Z",UPPER(J683)),LEN(J683)+1))-1),LEFT(TEXT(I683,"0"),LEN(TEXT(I683,"0"))-3)) -> 441857093 | Y683: =IF(ISNUMBER(SEARCH("(RP)",J683)),"RP","DC") -> DC | Z683: =IF(ISNUMBER(SEARCH("(RP)",J683)),O683,IF(RIGHT(TRIM(J683),3)=", S",O683,0)) -> 0 | AA683: =IF(ISNUMBER(SEARCH("(RP)",J683)),O683,IF(RIGHT(TRIM(J683),3)=", M",O683,0)) -> 0 | AB683: =IF(ISNUMBER(SEARCH("(RP)",J683)),O683,IF(RIGHT(TRIM(J683),3)=", L",O683,0)) -> 0 | AC683: =IF(ISNUMBER(SEARCH("(RP)",J683)),O683,IF(RIGHT(TRIM(J683),4)=", XL",O683,0)) -> 240 | AD683: =IF(ISNUMBER(SEARCH("(RP)",J683)),O683,IF(OR(RIGHT(TRIM(J683),5)=", XXL",RIGHT(TRIM(J683),5)=", 2XL"),O683,0)) -> 0 | AE683: {=IFERROR(_xlfn.XLOOKUP(H683,Sheet1!$G:$G,Sheet1!$F:$F),IFERROR(_xlfn.XLOOKUP(1,(--($X$2:$X$1074=X683))*(--ISNUMBER(MATCH($H$2:$H$1074,Sheet1!$G:$G,0))),_xlfn.XLOOKUP($H$2:$H$1074,Sheet1!$G:$G,Sheet1!$F:$F,"")),"NOT FOUND"))} -> RETKRTSCUT5007 | AF683: =IFERROR(IF(ISNUMBER(SEARCH("(RP)",J683)),TRIM(SUBSTITUTE(MID(J683,10,LEN(J683)),"(RP)","")),TRIM(MID(J683,FIND(",",J683)+1,FIND(",",J683,FIND(",",J683)+1)-FIND(",",J683)-1))),"") -> BLACK | AG683: =IF(A683="SZAF","Bangalore",IF(A683="SAEX","JHAJJAR",IF(A683="S0EU","HARIPAL",""))) -> JHAJJAR | AH683: =IF(OR(J683="",AE683="",AE683="NOT FOUND"),"",IF(Y683="RP",IFERROR(LEFT(_xlfn.XLOOKUP(AE683,Sheet1!$F:$F,Sheet1!$W:$W),FIND("-",_xlfn.XLOOKUP(AE683,Sheet1!$F:$F,Sheet1!$W:$W),FIND("-",_xlfn.XLOOKUP(AE683,Sheet1!$F:$F,Sheet1!$W:$W))+1))&AE683,"NOT FOUND"),LEFT(J683,FIND("-",J683,FIND("-",J683)+1))&AE683)) -> KRTS-APSU26-RETKRTSCUT5007
A684: SAEX | B684: 5112793031 | C684: 14.01.2026 | D684: 30.04.2026 | E684: 10337044 | F684: UNITED TEXTILE MILLS PRIVATE LIMITE | G684: 5 | H684: 8909284019826 | I684: 441857093005 | J684: KRTS-APSU26-RETKRTSCUT5007, BLACK, 2XL | L684: EA | M684: 1 | N684: 45 | O684: 45 | Q684: 204.3 | R684: 204.3 | S684: 459.68 | T684: 9193.5 | U684: 5 | V684: INR | X684: =IF(ISNUMBER(VALUE(LEFT(J684,1))),LEFT(J684,MIN(IFERROR(FIND("A",UPPER(J684)),LEN(J684)+1),IFERROR(FIND("B",UPPER(J684)),LEN(J684)+1),IFERROR(FIND("C",UPPER(J684)),LEN(J684)+1),IFERROR(FIND("D",UPPER(J684)),LEN(J684)+1),IFERROR(FIND("E",UPPER(J684)),LEN(J684)+1),IFERROR(FIND("F",UPPER(J684)),LEN(J684)+1),IFERROR(FIND("G",UPPER(J684)),LEN(J684)+1),IFERROR(FIND("H",UPPER(J684)),LEN(J684)+1),IFERROR(FIND("I",UPPER(J684)),LEN(J684)+1),IFERROR(FIND("J",UPPER(J684)),LEN(J684)+1),IFERROR(FIND("K",UPPER(J684)),LEN(J684)+1),IFERROR(FIND("L",UPPER(J684)),LEN(J684)+1),IFERROR(FIND("M",UPPER(J684)),LEN(J684)+1),IFERROR(FIND("N",UPPER(J684)),LEN(J684)+1),IFERROR(FIND("O",UPPER(J684)),LEN(J684)+1),IFERROR(FIND("P",UPPER(J684)),LEN(J684)+1),IFERROR(FIND("Q",UPPER(J684)),LEN(J684)+1),IFERROR(FIND("R",UPPER(J684)),LEN(J684)+1),IFERROR(FIND("S",UPPER(J684)),LEN(J684)+1),IFERROR(FIND("T",UPPER(J684)),LEN(J684)+1),IFERROR(FIND("U",UPPER(J684)),LEN(J684)+1),IFERROR(FIND("V",UPPER(J684)),LEN(J684)+1),IFERROR(FIND("W",UPPER(J684)),LEN(J684)+1),IFERROR(FIND("X",UPPER(J684)),LEN(J684)+1),IFERROR(FIND("Y",UPPER(J684)),LEN(J684)+1),IFERROR(FIND("Z",UPPER(J684)),LEN(J684)+1))-1),LEFT(TEXT(I684,"0"),LEN(TEXT(I684,"0"))-3)) -> 441857093 | Y684: =IF(ISNUMBER(SEARCH("(RP)",J684)),"RP","DC") -> DC | Z684: =IF(ISNUMBER(SEARCH("(RP)",J684)),O684,IF(RIGHT(TRIM(J684),3)=", S",O684,0)) -> 0 | AA684: =IF(ISNUMBER(SEARCH("(RP)",J684)),O684,IF(RIGHT(TRIM(J684),3)=", M",O684,0)) -> 0 | AB684: =IF(ISNUMBER(SEARCH("(RP)",J684)),O684,IF(RIGHT(TRIM(J684),3)=", L",O684,0)) -> 0 | AC684: =IF(ISNUMBER(SEARCH("(RP)",J684)),O684,IF(RIGHT(TRIM(J684),4)=", XL",O684,0)) -> 0 | AD684: =IF(ISNUMBER(SEARCH("(RP)",J684)),O684,IF(OR(RIGHT(TRIM(J684),5)=", XXL",RIGHT(TRIM(J684),5)=", 2XL"),O684,0)) -> 45 | AE684: {=IFERROR(_xlfn.XLOOKUP(H684,Sheet1!$G:$G,Sheet1!$F:$F),IFERROR(_xlfn.XLOOKUP(1,(--($X$2:$X$1074=X684))*(--ISNUMBER(MATCH($H$2:$H$1074,Sheet1!$G:$G,0))),_xlfn.XLOOKUP($H$2:$H$1074,Sheet1!$G:$G,Sheet1!$F:$F,"")),"NOT FOUND"))} -> RETKRTSCUT5007 | AF684: =IFERROR(IF(ISNUMBER(SEARCH("(RP)",J684)),TRIM(SUBSTITUTE(MID(J684,10,LEN(J684)),"(RP)","")),TRIM(MID(J684,FIND(",",J684)+1,FIND(",",J684,FIND(",",J684)+1)-FIND(",",J684)-1))),"") -> BLACK | AG684: =IF(A684="SZAF","Bangalore",IF(A684="SAEX","JHAJJAR",IF(A684="S0EU","HARIPAL",""))) -> JHAJJAR | AH684: =IF(OR(J684="",AE684="",AE684="NOT FOUND"),"",IF(Y684="RP",IFERROR(LEFT(_xlfn.XLOOKUP(AE684,Sheet1!$F:$F,Sheet1!$W:$W),FIND("-",_xlfn.XLOOKUP(AE684,Sheet1!$F:$F,Sheet1!$W:$W),FIND("-",_xlfn.XLOOKUP(AE684,Sheet1!$F:$F,Sheet1!$W:$W))+1))&AE684,"NOT FOUND"),LEFT(J684,FIND("-",J684,FIND("-",J684)+1))&AE684)) -> KRTS-APSU26-RETKRTSCUT5007
A685: S0EU | B685: 5112793025 | C685: 14.01.2026 | D685: 30.04.2026 | E685: 10337044 | F685: UNITED TEXTILE MILLS PRIVATE LIMITE | G685: 1 | H685: 8909284019864 | I685: 441857093001 | J685: KRTS-APSU26-RETKRTSCUT5007, BLACK, S | L685: EA | M685: 1 | N685: 30 | O685: 30 | Q685: 204.3 | R685: 204.3 | S685: 306.45 | T685: 6129 | U685: 5 | V685: INR | X685: =IF(ISNUMBER(VALUE(LEFT(J685,1))),LEFT(J685,MIN(IFERROR(FIND("A",UPPER(J685)),LEN(J685)+1),IFERROR(FIND("B",UPPER(J685)),LEN(J685)+1),IFERROR(FIND("C",UPPER(J685)),LEN(J685)+1),IFERROR(FIND("D",UPPER(J685)),LEN(J685)+1),IFERROR(FIND("E",UPPER(J685)),LEN(J685)+1),IFERROR(FIND("F",UPPER(J685)),LEN(J685)+1),IFERROR(FIND("G",UPPER(J685)),LEN(J685)+1),IFERROR(FIND("H",UPPER(J685)),LEN(J685)+1),IFERROR(FIND("I",UPPER(J685)),LEN(J685)+1),IFERROR(FIND("J",UPPER(J685)),LEN(J685)+1),IFERROR(FIND("K",UPPER(J685)),LEN(J685)+1),IFERROR(FIND("L",UPPER(J685)),LEN(J685)+1),IFERROR(FIND("M",UPPER(J685)),LEN(J685)+1),IFERROR(FIND("N",UPPER(J685)),LEN(J685)+1),IFERROR(FIND("O",UPPER(J685)),LEN(J685)+1),IFERROR(FIND("P",UPPER(J685)),LEN(J685)+1),IFERROR(FIND("Q",UPPER(J685)),LEN(J685)+1),IFERROR(FIND("R",UPPER(J685)),LEN(J685)+1),IFERROR(FIND("S",UPPER(J685)),LEN(J685)+1),IFERROR(FIND("T",UPPER(J685)),LEN(J685)+1),IFERROR(FIND("U",UPPER(J685)),LEN(J685)+1),IFERROR(FIND("V",UPPER(J685)),LEN(J685)+1),IFERROR(FIND("W",UPPER(J685)),LEN(J685)+1),IFERROR(FIND("X",UPPER(J685)),LEN(J685)+1),IFERROR(FIND("Y",UPPER(J685)),LEN(J685)+1),IFERROR(FIND("Z",UPPER(J685)),LEN(J685)+1))-1),LEFT(TEXT(I685,"0"),LEN(TEXT(I685,"0"))-3)) -> 441857093 | Y685: =IF(ISNUMBER(SEARCH("(RP)",J685)),"RP","DC") -> DC | Z685: =IF(ISNUMBER(SEARCH("(RP)",J685)),O685,IF(RIGHT(TRIM(J685),3)=", S",O685,0)) -> 30 | AA685: =IF(ISNUMBER(SEARCH("(RP)",J685)),O685,IF(RIGHT(TRIM(J685),3)=", M",O685,0)) -> 0 | AB685: =IF(ISNUMBER(SEARCH("(RP)",J685)),O685,IF(RIGHT(TRIM(J685),3)=", L",O685,0)) -> 0 | AC685: =IF(ISNUMBER(SEARCH("(RP)",J685)),O685,IF(RIGHT(TRIM(J685),4)=", XL",O685,0)) -> 0 | AD685: =IF(ISNUMBER(SEARCH("(RP)",J685)),O685,IF(OR(RIGHT(TRIM(J685),5)=", XXL",RIGHT(TRIM(J685),5)=", 2XL"),O685,0)) -> 0 | AE685: {=IFERROR(_xlfn.XLOOKUP(H685,Sheet1!$G:$G,Sheet1!$F:$F),IFERROR(_xlfn.XLOOKUP(1,(--($X$2:$X$1074=X685))*(--ISNUMBER(MATCH($H$2:$H$1074,Sheet1!$G:$G,0))),_xlfn.XLOOKUP($H$2:$H$1074,Sheet1!$G:$G,Sheet1!$F:$F,"")),"NOT FOUND"))} -> RETKRTSCUT5007 | AF685: =IFERROR(IF(ISNUMBER(SEARCH("(RP)",J685)),TRIM(SUBSTITUTE(MID(J685,10,LEN(J685)),"(RP)","")),TRIM(MID(J685,FIND(",",J685)+1,FIND(",",J685,FIND(",",J685)+1)-FIND(",",J685)-1))),"") -> BLACK | AG685: =IF(A685="SZAF","Bangalore",IF(A685="SAEX","JHAJJAR",IF(A685="S0EU","HARIPAL",""))) -> HARIPAL | AH685: =IF(OR(J685="",AE685="",AE685="NOT FOUND"),"",IF(Y685="RP",IFERROR(LEFT(_xlfn.XLOOKUP(AE685,Sheet1!$F:$F,Sheet1!$W:$W),FIND("-",_xlfn.XLOOKUP(AE685,Sheet1!$F:$F,Sheet1!$W:$W),FIND("-",_xlfn.XLOOKUP(AE685,Sheet1!$F:$F,Sheet1!$W:$W))+1))&AE685,"NOT FOUND"),LEFT(J685,FIND("-",J685,FIND("-",J685)+1))&AE685)) -> KRTS-APSU26-RETKRTSCUT5007
A686: S0EU | B686: 5112793025 | C686: 14.01.2026 | D686: 30.04.2026 | E686: 10337044 | F686: UNITED TEXTILE MILLS PRIVATE LIMITE | G686: 2 | H686: 8909284019857 | I686: 441857093002 | J686: KRTS-APSU26-RETKRTSCUT5007, BLACK, M | L686: EA | M686: 1 | N686: 173 | O686: 173 | Q686: 204.3 | R686: 204.3 | S686: 1767.2 | T686: 35343.9 | U686: 5 | V686: INR | X686: =IF(ISNUMBER(VALUE(LEFT(J686,1))),LEFT(J686,MIN(IFERROR(FIND("A",UPPER(J686)),LEN(J686)+1),IFERROR(FIND("B",UPPER(J686)),LEN(J686)+1),IFERROR(FIND("C",UPPER(J686)),LEN(J686)+1),IFERROR(FIND("D",UPPER(J686)),LEN(J686)+1),IFERROR(FIND("E",UPPER(J686)),LEN(J686)+1),IFERROR(FIND("F",UPPER(J686)),LEN(J686)+1),IFERROR(FIND("G",UPPER(J686)),LEN(J686)+1),IFERROR(FIND("H",UPPER(J686)),LEN(J686)+1),IFERROR(FIND("I",UPPER(J686)),LEN(J686)+1),IFERROR(FIND("J",UPPER(J686)),LEN(J686)+1),IFERROR(FIND("K",UPPER(J686)),LEN(J686)+1),IFERROR(FIND("L",UPPER(J686)),LEN(J686)+1),IFERROR(FIND("M",UPPER(J686)),LEN(J686)+1),IFERROR(FIND("N",UPPER(J686)),LEN(J686)+1),IFERROR(FIND("O",UPPER(J686)),LEN(J686)+1),IFERROR(FIND("P",UPPER(J686)),LEN(J686)+1),IFERROR(FIND("Q",UPPER(J686)),LEN(J686)+1),IFERROR(FIND("R",UPPER(J686)),LEN(J686)+1),IFERROR(FIND("S",UPPER(J686)),LEN(J686)+1),IFERROR(FIND("T",UPPER(J686)),LEN(J686)+1),IFERROR(FIND("U",UPPER(J686)),LEN(J686)+1),IFERROR(FIND("V",UPPER(J686)),LEN(J686)+1),IFERROR(FIND("W",UPPER(J686)),LEN(J686)+1),IFERROR(FIND("X",UPPER(J686)),LEN(J686)+1),IFERROR(FIND("Y",UPPER(J686)),LEN(J686)+1),IFERROR(FIND("Z",UPPER(J686)),LEN(J686)+1))-1),LEFT(TEXT(I686,"0"),LEN(TEXT(I686,"0"))-3)) -> 441857093 | Y686: =IF(ISNUMBER(SEARCH("(RP)",J686)),"RP","DC") -> DC | Z686: =IF(ISNUMBER(SEARCH("(RP)",J686)),O686,IF(RIGHT(TRIM(J686),3)=", S",O686,0)) -> 0 | AA686: =IF(ISNUMBER(SEARCH("(RP)",J686)),O686,IF(RIGHT(TRIM(J686),3)=", M",O686,0)) -> 173 | AB686: =IF(ISNUMBER(SEARCH("(RP)",J686)),O686,IF(RIGHT(TRIM(J686),3)=", L",O686,0)) -> 0 | AC686: =IF(ISNUMBER(SEARCH("(RP)",J686)),O686,IF(RIGHT(TRIM(J686),4)=", XL",O686,0)) -> 0 | AD686: =IF(ISNUMBER(SEARCH("(RP)",J686)),O686,IF(OR(RIGHT(TRIM(J686),5)=", XXL",RIGHT(TRIM(J686),5)=", 2XL"),O686,0)) -> 0 | AE686: {=IFERROR(_xlfn.XLOOKUP(H686,Sheet1!$G:$G,Sheet1!$F:$F),IFERROR(_xlfn.XLOOKUP(1,(--($X$2:$X$1074=X686))*(--ISNUMBER(MATCH($H$2:$H$1074,Sheet1!$G:$G,0))),_xlfn.XLOOKUP($H$2:$H$1074,Sheet1!$G:$G,Sheet1!$F:$F,"")),"NOT FOUND"))} -> RETKRTSCUT5007 | AF686: =IFERROR(IF(ISNUMBER(SEARCH("(RP)",J686)),TRIM(SUBSTITUTE(MID(J686,10,LEN(J686)),"(RP)","")),TRIM(MID(J686,FIND(",",J686)+1,FIND(",",J686,FIND(",",J686)+1)-FIND(",",J686)-1))),"") -> BLACK | AG686: =IF(A686="SZAF","Bangalore",IF(A686="SAEX","JHAJJAR",IF(A686="S0EU","HARIPAL",""))) -> HARIPAL | AH686: =IF(OR(J686="",AE686="",AE686="NOT FOUND"),"",IF(Y686="RP",IFERROR(LEFT(_xlfn.XLOOKUP(AE686,Sheet1!$F:$F,Sheet1!$W:$W),FIND("-",_xlfn.XLOOKUP(AE686,Sheet1!$F:$F,Sheet1!$W:$W),FIND("-",_xlfn.XLOOKUP(AE686,Sheet1!$F:$F,Sheet1!$W:$W))+1))&AE686,"NOT FOUND"),LEFT(J686,FIND("-",J686,FIND("-",J686)+1))&AE686)) -> KRTS-APSU26-RETKRTSCUT5007
... A961: SZAF | B961: 5112223283 | C961: 04.12.2025 | D961: 30.06.2026 | E961: 10337044 | F961: UNITED TEXTILE MILLS PRIVATE LIMITE | G961: 5 | H961: 8909284092331 | I961: 441853743004 | J961: SKD-APSU26-YETCRDSFUT4017, NAVY, XL | L961: EA | M961: 1 | N961: 157 | O961: 157 | Q961: 0 | R961: 0 | S961: 0 | T961: 0 | U961: 0 | V961: INR | X961: =IF(ISNUMBER(VALUE(LEFT(J961,1))),LEFT(J961,MIN(IFERROR(FIND("A",UPPER(J961)),LEN(J961)+1),IFERROR(FIND("B",UPPER(J961)),LEN(J961)+1),IFERROR(FIND("C",UPPER(J961)),LEN(J961)+1),IFERROR(FIND("D",UPPER(J961)),LEN(J961)+1),IFERROR(FIND("E",UPPER(J961)),LEN(J961)+1),IFERROR(FIND("F",UPPER(J961)),LEN(J961)+1),IFERROR(FIND("G",UPPER(J961)),LEN(J961)+1),IFERROR(FIND("H",UPPER(J961)),LEN(J961)+1),IFERROR(FIND("I",UPPER(J961)),LEN(J961)+1),IFERROR(FIND("J",UPPER(J961)),LEN(J961)+1),IFERROR(FIND("K",UPPER(J961)),LEN(J961)+1),IFERROR(FIND("L",UPPER(J961)),LEN(J961)+1),IFERROR(FIND("M",UPPER(J961)),LEN(J961)+1),IFERROR(FIND("N",UPPER(J961)),LEN(J961)+1),IFERROR(FIND("O",UPPER(J961)),LEN(J961)+1),IFERROR(FIND("P",UPPER(J961)),LEN(J961)+1),IFERROR(FIND("Q",UPPER(J961)),LEN(J961)+1),IFERROR(FIND("R",UPPER(J961)),LEN(J961)+1),IFERROR(FIND("S",UPPER(J961)),LEN(J961)+1),IFERROR(FIND("T",UPPER(J961)),LEN(J961)+1),IFERROR(FIND("U",UPPER(J961)),LEN(J961)+1),IFERROR(FIND("V",UPPER(J961)),LEN(J961)+1),IFERROR(FIND("W",UPPER(J961)),LEN(J961)+1),IFERROR(FIND("X",UPPER(J961)),LEN(J961)+1),IFERROR(FIND("Y",UPPER(J961)),LEN(J961)+1),IFERROR(FIND("Z",UPPER(J961)),LEN(J961)+1))-1),LEFT(TEXT(I961,"0"),LEN(TEXT(I961,"0"))-3)) -> 441853743 | Y961: =IF(ISNUMBER(SEARCH("(RP)",J961)),"RP","DC") -> DC | Z961: =IF(ISNUMBER(SEARCH("(RP)",J961)),O961,IF(RIGHT(TRIM(J961),3)=", S",O961,0)) -> 0 | AA961: =IF(ISNUMBER(SEARCH("(RP)",J961)),O961,IF(RIGHT(TRIM(J961),3)=", M",O961,0)) -> 0 | AB961: =IF(ISNUMBER(SEARCH("(RP)",J961)),O961,IF(RIGHT(TRIM(J961),3)=", L",O961,0)) -> 0 | AC961: =IF(ISNUMBER(SEARCH("(RP)",J961)),O961,IF(RIGHT(TRIM(J961),4)=", XL",O961,0)) -> 157 | AD961: =IF(ISNUMBER(SEARCH("(RP)",J961)),O961,IF(OR(RIGHT(TRIM(J961),5)=", XXL",RIGHT(TRIM(J961),5)=", 2XL"),O961,0)) -> 0 | AE961: {=IFERROR(_xlfn.XLOOKUP(H961,Sheet1!$G:$G,Sheet1!$F:$F),IFERROR(_xlfn.XLOOKUP(1,(--($X$2:$X$1074=X961))*(--ISNUMBER(MATCH($H$2:$H$1074,Sheet1!$G:$G,0))),_xlfn.XLOOKUP($H$2:$H$1074,Sheet1!$G:$G,Sheet1!$F:$F,"")),"NOT FOUND"))} -> YETCRDSFUT4017 | AF961: =IFERROR(IF(ISNUMBER(SEARCH("(RP)",J961)),TRIM(SUBSTITUTE(MID(J961,10,LEN(J961)),"(RP)","")),TRIM(MID(J961,FIND(",",J961)+1,FIND(",",J961,FIND(",",J961)+1)-FIND(",",J961)-1))),"") -> NAVY | AG961: =IF(A961="SZAF","Bangalore",IF(A961="SAEX","JHAJJAR",IF(A961="S0EU","HARIPAL",""))) -> Bangalore | AH961: =IF(OR(J961="",AE961="",AE961="NOT FOUND"),"",IF(Y961="RP",IFERROR(LEFT(_xlfn.XLOOKUP(AE961,Sheet1!$F:$F,Sheet1!$W:$W),FIND("-",_xlfn.XLOOKUP(AE961,Sheet1!$F:$F,Sheet1!$W:$W),FIND("-",_xlfn.XLOOKUP(AE961,Sheet1!$F:$F,Sheet1!$W:$W))+1))&AE961,"NOT FOUND"),LEFT(J961,FIND("-",J961,FIND("-",J961)+1))&AE961)) -> SKD-APSU26-YETCRDSFUT4017
A962: SZAF | B962: 5112223283 | C962: 04.12.2025 | D962: 30.06.2026 | E962: 10337044 | F962: UNITED TEXTILE MILLS PRIVATE LIMITE | G962: 6 | H962: 8909284092324 | I962: 441853743005 | J962: SKD-APSU26-YETCRDSFUT4017, NAVY, 2XL | L962: EA | M962: 1 | N962: 157 | O962: 157 | Q962: 0 | R962: 0 | S962: 0 | T962: 0 | U962: 0 | X962: =IF(ISNUMBER(VALUE(LEFT(J962,1))),LEFT(J962,MIN(IFERROR(FIND("A",UPPER(J962)),LEN(J962)+1),IFERROR(FIND("B",UPPER(J962)),LEN(J962)+1),IFERROR(FIND("C",UPPER(J962)),LEN(J962)+1),IFERROR(FIND("D",UPPER(J962)),LEN(J962)+1),IFERROR(FIND("E",UPPER(J962)),LEN(J962)+1),IFERROR(FIND("F",UPPER(J962)),LEN(J962)+1),IFERROR(FIND("G",UPPER(J962)),LEN(J962)+1),IFERROR(FIND("H",UPPER(J962)),LEN(J962)+1),IFERROR(FIND("I",UPPER(J962)),LEN(J962)+1),IFERROR(FIND("J",UPPER(J962)),LEN(J962)+1),IFERROR(FIND("K",UPPER(J962)),LEN(J962)+1),IFERROR(FIND("L",UPPER(J962)),LEN(J962)+1),IFERROR(FIND("M",UPPER(J962)),LEN(J962)+1),IFERROR(FIND("N",UPPER(J962)),LEN(J962)+1),IFERROR(FIND("O",UPPER(J962)),LEN(J962)+1),IFERROR(FIND("P",UPPER(J962)),LEN(J962)+1),IFERROR(FIND("Q",UPPER(J962)),LEN(J962)+1),IFERROR(FIND("R",UPPER(J962)),LEN(J962)+1),IFERROR(FIND("S",UPPER(J962)),LEN(J962)+1),IFERROR(FIND("T",UPPER(J962)),LEN(J962)+1),IFERROR(FIND("U",UPPER(J962)),LEN(J962)+1),IFERROR(FIND("V",UPPER(J962)),LEN(J962)+1),IFERROR(FIND("W",UPPER(J962)),LEN(J962)+1),IFERROR(FIND("X",UPPER(J962)),LEN(J962)+1),IFERROR(FIND("Y",UPPER(J962)),LEN(J962)+1),IFERROR(FIND("Z",UPPER(J962)),LEN(J962)+1))-1),LEFT(TEXT(I962,"0"),LEN(TEXT(I962,"0"))-3)) -> 441853743 | Y962: =IF(ISNUMBER(SEARCH("(RP)",J962)),"RP","DC") -> DC | Z962: =IF(ISNUMBER(SEARCH("(RP)",J962)),O962,IF(RIGHT(TRIM(J962),3)=", S",O962,0)) -> 0 | AA962: =IF(ISNUMBER(SEARCH("(RP)",J962)),O962,IF(RIGHT(TRIM(J962),3)=", M",O962,0)) -> 0 | AB962: =IF(ISNUMBER(SEARCH("(RP)",J962)),O962,IF(RIGHT(TRIM(J962),3)=", L",O962,0)) -> 0 | AC962: =IF(ISNUMBER(SEARCH("(RP)",J962)),O962,IF(RIGHT(TRIM(J962),4)=", XL",O962,0)) -> 0 | AD962: =IF(ISNUMBER(SEARCH("(RP)",J962)),O962,IF(OR(RIGHT(TRIM(J962),5)=", XXL",RIGHT(TRIM(J962),5)=", 2XL"),O962,0)) -> 157 | AE962: {=IFERROR(_xlfn.XLOOKUP(H962,Sheet1!$G:$G,Sheet1!$F:$F),IFERROR(_xlfn.XLOOKUP(1,(--($X$2:$X$1074=X962))*(--ISNUMBER(MATCH($H$2:$H$1074,Sheet1!$G:$G,0))),_xlfn.XLOOKUP($H$2:$H$1074,Sheet1!$G:$G,Sheet1!$F:$F,"")),"NOT FOUND"))} -> YETCRDSFUT4017 | AF962: =IFERROR(IF(ISNUMBER(SEARCH("(RP)",J962)),TRIM(SUBSTITUTE(MID(J962,10,LEN(J962)),"(RP)","")),TRIM(MID(J962,FIND(",",J962)+1,FIND(",",J962,FIND(",",J962)+1)-FIND(",",J962)-1))),"") -> NAVY | AG962: =IF(A962="SZAF","Bangalore",IF(A962="SAEX","JHAJJAR",IF(A962="S0EU","HARIPAL",""))) -> Bangalore | AH962: =IF(OR(J962="",AE962="",AE962="NOT FOUND"),"",IF(Y962="RP",IFERROR(LEFT(_xlfn.XLOOKUP(AE962,Sheet1!$F:$F,Sheet1!$W:$W),FIND("-",_xlfn.XLOOKUP(AE962,Sheet1!$F:$F,Sheet1!$W:$W),FIND("-",_xlfn.XLOOKUP(AE962,Sheet1!$F:$F,Sheet1!$W:$W))+1))&AE962,"NOT FOUND"),LEFT(J962,FIND("-",J962,FIND("-",J962)+1))&AE962)) -> SKD-APSU26-YETCRDSFUT4017
